Workbook

Sheet 20pdts2007
A1: beta-07 | B1: M1 | C1: M2 | D1: Q1 | E1: Q2 | F1: Q3 | G1: Q4 | H1: Q5 | J1: Elasticité-revenu 2007 | K1: M1 | L1: M2 | M1: Q1 | N1: Q2 | O1: Q3 | P1: Q4 | Q1: Q5 | S1: Elasticité-Prix 2007 | T1: M1 | U1: M2 | V1: Q1 | W1: Q2 | X1: Q3 | Y1: Q4 | Z1: Q5 | AB1: CB | AC1: M1 | AD1: M2 | AE1: Q1 | AF1: Q2 | AG1: Q3 | AH1: Q4 | AI1: Q5 | AJ1: CB-2007
A2: A00 | B2: 0.0820532 | C2: 0.1443764 | D2: 0.1737262 | E2: 0.1675444 | F2: 0.1276257 | G2: 0.1394096 | H2: 0.0621852 | J2: A00 | K2: =B2/AC2 -> 0.60469571 | L2: =C2/AD2 -> 0.86485086 | M2: =D2/AE2 -> 1.0594818 | N2: =E2/AF2 -> 1.0043047 | O2: =F2/AG2 -> 0.76665567 | P2: =G2/AH2 -> 0.8744419 | Q2: =H2/AI2 -> 0.50513122 | S2: A00 | T2: =IF(T24=0,0,((1-B2)*(K24/T24))-1) -> -0.6378944 | U2: =IF(U24=0,0,((1-C2)*(L24/U24))-1) -> -0.93109298 | V2: =IF(V24=0,0,((1-D2)*(M24/V24))-1) -> -1.0635157 | W2: =IF(W24=0,0,((1-E2)*(N24/W24))-1) -> -1.0236482 | X2: =IF(X24=0,0,((1-F2)*(O24/X24))-1) -> -0.84829327 | Y2: =IF(Y24=0,0,((1-G2)*(P24/Y24))-1) -> -0.92918623 | Z2: =IF(Z24=0,0,((1-H2)*(Q24/Z24))-1) -> -0.46800237 | AB2: A00 | AC2: 0.13569337 | AD2: 0.16693792 | AE2: 0.16397281 | AF2: 0.16682626 | AG2: 0.16647069 | AH2: 0.15942694 | AI2: 0.12310702 | AJ2: A00
A3: B05 | B3: 0.0121311 | C3: 0.0101907 | D3: 0.0167558 | E3: 0.0128859 | F3: 0.0145282 | G3: 0.0135288 | H3: 0.0109444 | J3: B05 | K3: =B3/AC3 -> 0.79672414 | L3: =C3/AD3 -> 0.90588147 | M3: =D3/AE3 -> 1.2082265 | N3: =E3/AF3 -> 0.91454487 | O3: =F3/AG3 -> 1.0165672 | P3: =G3/AH3 -> 0.91256775 | Q3: =H3/AI3 -> 0.80714419 | S3: B05 | T3: =IF(T25=0,0,((1-B3)*(K25/T25))-1) -> -0.80650356 | U3: =IF(U25=0,0,((1-C3)*(L25/U25))-1) -> -1.7090431 | V3: =IF(V25=0,0,((1-D3)*(M25/V25))-1) -> -1.4068859 | W3: =IF(W25=0,0,((1-E3)*(N25/W25))-1) -> -1.1973496 | X3: =IF(X25=0,0,((1-F3)*(O25/X25))-1) -> -1.6986777 | Y3: =IF(Y25=0,0,((1-G3)*(P25/Y25))-1) -> -1.3728091 | Z3: =IF(Z25=0,0,((1-H3)*(Q25/Z25))-1) -> -0.15907545 | AB3: B05 | AC3: 0.015226224 | AD3: 0.011249485 | AE3: 0.013868095 | AF3: 0.014089959 | AG3: 0.014291431 | AH3: 0.014824981 | AI3: 0.013559411 | AJ3: B05
A4: C00 | B4: 0.0001982 | C4: 0.0005578 | D4: 0.0009737 | E4: 0.0008139 | F4: 0.0006021 | G4: 0.0004611 | H4: 9.75e-05 | J4: C00 | K4: =B4/AC4 -> 0.35494691 | L4: =C4/AD4 -> 0.53344062 | M4: =D4/AE4 -> 0.90076311 | N4: =E4/AF4 -> 0.8008729 | O4: =F4/AG4 -> 0.65372805 | P4: =G4/AH4 -> 0.58068732 | Q4: =H4/AI4 -> 0.21217624 | S4: C00 | T4: =IF(T26=0,0,((1-B4)*(K26/T26))-1) -> -0.55686678 | U4: =IF(U26=0,0,((1-C4)*(L26/U26))-1) -> -9.2478947 | V4: =IF(V26=0,0,((1-D4)*(M26/V26))-1) -> -3.5359134 | W4: =IF(W26=0,0,((1-E4)*(N26/W26))-1) -> -4.7544032 | X4: =IF(X26=0,0,((1-F4)*(O26/X26))-1) -> -11.391573 | Y4: =IF(Y26=0,0,((1-G4)*(P26/Y26))-1) -> -9.2650108 | Z4: =IF(Z26=0,0,((1-H4)*(Q26/Z26))-1) -> 19.183367 | AB4: C00 | AC4: 0.00055839337 | AD4: 0.0010456647 | AE4: 0.0010809723 | AF4: 0.0010162661 | AG4: 0.00092102519 | AH4: 0.00079405901 | AI4: 0.00045952366 | AJ4: C00
A5: D01 | B5: 0.1009344 | C5: 0.2196602 | D5: 0.3334779 | E5: 0.3124982 | F5: 0.1863854 | G5: 0.2261472 | H5: 0.0612799 | J5: D01 | K5: =B5/AC5 -> 0.44734105 | L5: =C5/AD5 -> 0.66142194 | M5: =D5/AE5 -> 0.95310351 | N5: =E5/AF5 -> 0.92861148 | O5: =F5/AG5 -> 0.59394059 | P5: =G5/AH5 -> 0.78101543 | Q5: =H5/AI5 -> 0.32079717 | S5: D01 | T5: =IF(T27=0,0,((1-B5)*(K27/T27))-1) -> -0.50357252 | U5: =IF(U27=0,0,((1-C5)*(L27/U27))-1) -> -0.75721682 | V5: =IF(V27=0,0,((1-D5)*(M27/V27))-1) -> -0.97417384 | W5: =IF(W27=0,0,((1-E5)*(N27/W27))-1) -> -0.95913487 | X5: =IF(X27=0,0,((1-F5)*(O27/X27))-1) -> -0.69528037 | Y5: =IF(Y27=0,0,((1-G5)*(P27/Y27))-1) -> -0.84897587 | Z5: =IF(Z27=0,0,((1-H5)*(Q27/Z27))-1) -> -0.31861566 | AB5: D01 | AC5: 0.22563187 | AD5: 0.33210298 | AE5: 0.34988634 | AF5: 0.33652201 | AG5: 0.31381152 | AH5: 0.28955536 | AI5: 0.19102381 | AJ5: D01
A6: D02 | B6: 0.0453148 | C6: 0.0418716 | D6: 0.0393097 | E6: 0.0488253 | F6: 0.0433693 | G6: 0.0556264 | H6: 0.0411768 | J6: D02 | K6: =B6/AC6 -> 1.1283871 | L6: =C6/AD6 -> 1.1208592 | M6: =D6/AE6 -> 1.4951245 | N6: =E6/AF6 -> 1.5885187 | O6: =F6/AG6 -> 1.2502422 | P6: =G6/AH6 -> 1.3739846 | Q6: =H6/AI6 -> 0.92753509 | S6: D02 | T6: =IF(T28=0,0,((1-B6)*(K28/T28))-1) -> -1.1252485 | U6: =IF(U28=0,0,((1-C6)*(L28/U28))-1) -> -1.3496387 | V6: =IF(V28=0,0,((1-D6)*(M28/V28))-1) -> -1.5798406 | W6: =IF(W28=0,0,((1-E6)*(N28/W28))-1) -> -1.6842183 | X6: =IF(X28=0,0,((1-F6)*(O28/X28))-1) -> -1.5122862 | Y6: =IF(Y28=0,0,((1-G6)*(P28/Y28))-1) -> -1.5141049 | Z6: =IF(Z28=0,0,((1-H6)*(Q28/Z28))-1) -> -0.73800221 | AB6: D02 | AC6: 0.040158912 | AD6: 0.0373567 | AE6: 0.026291924 | AF6: 0.030736371 | AG6: 0.03468872 | AH6: 0.040485462 | AI6: 0.044393792 | AJ6: D02
A7: D03 | B7: 0.0269556 | C7: 0.0349151 | D7: 0.0473511 | E7: 0.0370152 | F7: 0.0524851 | G7: 0.0485892 | H7: 0.0195122 | J7: D03 | K7: =B7/AC7 -> 0.6264359 | L7: =C7/AD7 -> 0.87446462 | M7: =D7/AE7 -> 1.1507789 | N7: =E7/AF7 -> 0.80882062 | O7: =F7/AG7 -> 1.1343109 | P7: =G7/AH7 -> 1.0577608 | Q7: =H7/AI7 -> 0.51212139 | S7: D03 | T7: =IF(T29=0,0,((1-B7)*(K29/T29))-1) -> -0.63905515 | U7: =IF(U29=0,0,((1-C7)*(L29/U29))-1) -> -1.0992216 | V7: =IF(V29=0,0,((1-D7)*(M29/V29))-1) -> -1.2096503 | W7: =IF(W29=0,0,((1-E7)*(N29/W29))-1) -> -0.90050697 | X7: =IF(X29=0,0,((1-F7)*(O29/X29))-1) -> -1.3299005 | Y7: =IF(Y29=0,0,((1-G7)*(P29/Y29))-1) -> -1.1978416 | Z7: =IF(Z29=0,0,((1-H7)*(Q29/Z29))-1) -> -0.29225831 | AB7: D03 | AC7: 0.043030101 | AD7: 0.039927401 | AE7: 0.041146999 | AF7: 0.045764412 | AG7: 0.046270473 | AH7: 0.045935905 | AI7: 0.038100732 | AJ7: D03
A8: D04 | B8: 0.1445375 | C8: 0.0989986 | D8: 0.0330414 | E8: 0.0344071 | F8: 0.0557996 | G8: 0.0512764 | H8: 0.1825572 | J8: D04 | K8: =B8/AC8 -> 2.3757601 | L8: =C8/AD8 -> 2.2444593 | M8: =D8/AE8 -> 1.3373422 | N8: =E8/AF8 -> 1.2700428 | O8: =F8/AG8 -> 1.7316479 | P8: =G8/AH8 -> 1.4080487 | Q8: =H8/AI8 -> 2.1603917 | S8: D04 | T8: =IF(T30=0,0,((1-B8)*(K30/T30))-1) -> -2.1784965 | U8: =IF(U30=0,0,((1-C8)*(L30/U30))-1) -> -2.3074986 | V8: =IF(V30=0,0,((1-D8)*(M30/V30))-1) -> -1.4377822 | W8: =IF(W30=0,0,((1-E8)*(N30/W30))-1) -> -1.4040662 | X8: =IF(X30=0,0,((1-F8)*(O30/X30))-1) -> -1.9807798 | Y8: =IF(Y30=0,0,((1-G8)*(P30/Y30))-1) -> -1.5668546 | Z8: =IF(Z30=0,0,((1-H8)*(Q30/Z30))-1) -> -1.862326 | AB8: D04 | AC8: 0.060838423 | AD8: 0.044107995 | AE8: 0.024706765 | AF8: 0.027091292 | AG8: 0.032223409 | AH8: 0.036416638 | AI8: 0.0845019 | AJ8: D04
A9: D05 | B9: 0.0186356 | C9: 0.0152416 | D9: 0.0085444 | E9: 0.0113368 | F9: 0.0128215 | G9: 0.0159069 | H9: 0.0184083 | J9: D05 | K9: =B9/AC9 -> 1.5265996 | L9: =C9/AD9 -> 1.4186744 | M9: =D9/AE9 -> 1.3555845 | N9: =E9/AF9 -> 1.5692898 | O9: =F9/AG9 -> 1.5340399 | P9: =G9/AH9 -> 1.6085943 | Q9: =H9/AI9 -> 1.1701574 | S9: D05 | T9: =IF(T31=0,0,((1-B9)*(K31/T31))-1) -> -1.5258499 | U9: =IF(U31=0,0,((1-C9)*(L31/U31))-1) -> -2.2479886 | V9: =IF(V31=0,0,((1-D9)*(M31/V31))-1) -> -1.8010186 | W9: =IF(W31=0,0,((1-E9)*(N31/W31))-1) -> -2.1131271 | X9: =IF(X31=0,0,((1-F9)*(O31/X31))-1) -> -2.6959749 | Y9: =IF(Y31=0,0,((1-G9)*(P31/Y31))-1) -> -2.2854663 | Z9: =IF(Z31=0,0,((1-H9)*(Q31/Z31))-1) -> -0.61084769 | AB9: D05 | AC9: 0.012207261 | AD9: 0.01074355 | AE9: 0.0063031115 | AF9: 0.0072241597 | AG9: 0.0083579962 | AH9: 0.0098886959 | AI9: 0.015731473 | AJ9: D05
A10: D23 | B10: 0.0897724 | C10: 0.0687347 | D10: 0.0384991 | E10: 0.0339502 | F10: 0.0261937 | G10: 0.0353616 | H10: 0.1131543 | J10: D23 | K10: =B10/AC10 -> 1.7702043 | L10: =C10/AD10 -> 1.3733701 | M10: =D10/AE10 -> 0.7483696 | N10: =E10/AF10 -> 0.75027971 | O10: =F10/AG10 -> 0.62101114 | P10: =G10/AH10 -> 0.89022998 | Q10: =H10/AI10 -> 1.900521 | S10: D23 | T10: =IF(T32=0,0,((1-B10)*(K32/T32))-1) -> -1.7030854 | U10: =IF(U32=0,0,((1-C10)*(L32/U32))-1) -> -1.5173539 | V10: =IF(V32=0,0,((1-D10)*(M32/V32))-1) -> -0.81134677 | W10: =IF(W32=0,0,((1-E10)*(N32/W32))-1) -> -0.84460294 | X10: =IF(X32=0,0,((1-F10)*(O32/X32))-1) -> -0.85940123 | Y10: =IF(Y32=0,0,((1-G10)*(P32/Y32))-1) -> -1.0616508 | Z10: =IF(Z32=0,0,((1-H10)*(Q32/Z32))-1) -> -1.6658523 | AB10: D23 | AC10: 0.050713016 | AD10: 0.050048199 | AE10: 0.051443966 | AF10: 0.045250057 | AG10: 0.042179115 | AH10: 0.03972187 | AI10: 0.05953857 | AJ10: D23
A11: E00 | B11: 0.012832 | C11: 0.0219682 | D11: 0.042856 | E11: 0.033251 | F11: 0.0218009 | G11: 0.0235227 | H11: 0.0094612 | J11: E00 | K11: =B11/AC11 -> 0.38571931 | L11: =C11/AD11 -> 0.5106725 | M11: =D11/AE11 -> 0.7078317 | N11: =E11/AF11 -> 0.6434147 | O11: =F11/AG11 -> 0.48770699 | P11: =G11/AH11 -> 0.61225276 | Q11: =H11/AI11 -> 0.38028638 | S11: E00 | T11: =IF(T33=0,0,((1-B11)*(K33/T33))-1) -> -0.39694833 | U11: =IF(U33=0,0,((1-C11)*(L33/U33))-1) -> -0.72870622 | V11: =IF(V33=0,0,((1-D11)*(M33/V33))-1) -> -0.76542553 | W11: =IF(W33=0,0,((1-E11)*(N33/W33))-1) -> -0.73049058 | X11: =IF(X33=0,0,((1-F11)*(O33/X33))-1) -> -0.71542339 | Y11: =IF(Y33=0,0,((1-G11)*(P33/Y33))-1) -> -0.79671555 | Z11: =IF(Z33=0,0,((1-H11)*(Q33/Z33))-1) -> -0.031262916 | AB11: E00 | AC11: 0.033267715 | AD11: 0.043018177 | AE11: 0.060545466 | AF11: 0.051678956 | AG11: 0.044700815 | AH11: 0.038419917 | AI11: 0.024879145 | AJ11: E00
A12: F45 | B12: 0.0313006 | C12: 0.054291 | D12: 0.030967 | E12: 0.0463624 | F12: 0.0288599 | G12: 0.0175927 | H12: 0.0290268 | J12: F45 | K12: =B12/AC12 -> 1.3112558 | L12: =C12/AD12 -> 1.4765662 | M12: =D12/AE12 -> 1.6711537 | N12: =E12/AF12 -> 2.2300531 | O12: =F12/AG12 -> 1.2623007 | P12: =G12/AH12 -> 0.67152646 | Q12: =H12/AI12 -> 0.87165062 | S12: F45 | T12: =IF(T34=0,0,((1-B12)*(K34/T34))-1) -> -1.3060886 | U12: =IF(U34=0,0,((1-C12)*(L34/U34))-1) -> -1.6851956 | V12: =IF(V34=0,0,((1-D12)*(M34/V34))-1) -> -1.7994724 | W12: =IF(W34=0,0,((1-E12)*(N34/W34))-1) -> -2.3574664 | X12: =IF(X34=0,0,((1-F12)*(O34/X34))-1) -> -1.6750633 | Y12: =IF(Y34=0,0,((1-G12)*(P34/Y34))-1) -> -0.9360088 | Z12: =IF(Z34=0,0,((1-H12)*(Q34/Z34))-1) -> -0.61547878 | AB12: F45 | AC12: 0.023870705 | AD12: 0.036768416 | AE12: 0.018530313 | AF12: 0.020789819 | AG12: 0.022862935 | AH12: 0.026198074 | AI12: 0.033300957 | AJ12: F45
A13: G00 | B13: 0.0383362 | C13: 0.0249249 | D13: 0.0028751 | E13: 0.0051592 | F13: 0.0046214 | G13: 0.009557 | H13: 0.0504283 | J13: G00 | K13: =B13/AC13 -> 3.1345558 | L13: =C13/AD13 -> 3.037674 | M13: =D13/AE13 -> 1.5272769 | N13: =E13/AF13 -> 2.0564493 | O13: =F13/AG13 -> 1.2022577 | P13: =G13/AH13 -> 1.8433186 | Q13: =H13/AI13 -> 2.5699361 | S13: G00 | T13: =IF(T35=0,0,((1-B13)*(K35/T35))-1) -> -3.061588 | U13: =IF(U35=0,0,((1-C13)*(L35/U35))-1) -> -4.0703434 | V13: =IF(V35=0,0,((1-D13)*(M35/V35))-1) -> -3.0359568 | W13: =IF(W35=0,0,((1-E13)*(N35/W35))-1) -> -3.6454687 | X13: =IF(X35=0,0,((1-F13)*(O35/X35))-1) -> -3.7637503 | Y13: =IF(Y35=0,0,((1-G13)*(P35/Y35))-1) -> -3.1531767 | Z13: =IF(Z35=0,0,((1-H13)*(Q35/Z35))-1) -> -2.0594184 | AB13: G00 | AC13: 0.012230186 | AD13: 0.0082052583 | AE13: 0.0018825008 | AF13: 0.0025087903 | AG13: 0.0038439347 | AH13: 0.0051846709 | AI13: 0.019622395 | AJ13: G00
... A21: OP0 | B21: 0.0595218 | C21: 0.044146 | D21: 0.0303179 | E21: 0.0290499 | F21: 0.0657309 | G21: 0.0453411 | H21: 0.0642622 | J21: OP0 | K21: =B21/AC21 -> 1.4112976 | L21: =C21/AD21 -> 1.4666599 | M21: =D21/AE21 -> 1.3202003 | N21: =E21/AF21 -> 1.0095392 | O21: =F21/AG21 -> 2.0659569 | P21: =G21/AH21 -> 1.3238973 | Q21: =H21/AI21 -> 1.3529573 | S21: OP0 | T21: =IF(T43=0,0,((1-B21)*(K43/T43))-1) -> -1.3893299 | U21: =IF(U43=0,0,((1-C21)*(L43/U43))-1) -> -1.7355895 | V21: =IF(V43=0,0,((1-D21)*(M43/V43))-1) -> -1.4308825 | W21: =IF(W43=0,0,((1-E21)*(N43/W43))-1) -> -1.1449405 | X21: =IF(X43=0,0,((1-F21)*(O43/X43))-1) -> -1.2367871 | Y21: =IF(Y43=0,0,((1-G21)*(P43/Y43))-1) -> -1.5015167 | Z21: =IF(Z43=0,0,((1-H21)*(Q43/Z43))-1) -> -1.1546702 | AB21: OP0 | AC21: 0.042175229 | AD21: 0.030099684 | AE21: 0.022964621 | AF21: 0.028775405 | AG21: 0.031816201 | AH21: 0.0342482 | AI21: 0.047497583 | AJ21: OP0
A23: alpha-07 | B23: M1 | C23: M2 | D23: Q1 | E23: Q2 | F23: Q3 | G23: Q4 | H23: Q5 | J23: CMIN | K23: M1 | L23: M2 | M23: Q1 | N23: Q2 | O23: Q3 | P23: Q4 | Q23: Q5 | S23: Cmoyen | T23: M1 | U23: M2 | V23: Q1 | W23: Q2 | X23: Q3 | Y23: Q4 | Z23: Q5
A24: A00 | B24: 3519.686 | C24: 982.9798 | D24: -182.8151 | E24: -22.64994 | F24: 1695.083 | G24: 1224.933 | H24: 8082.886 | J24: A00 | K24: 3512.2879 | L24: 585.75059 | M24: -236.25641 | N24: -149.46257 | O24: 1263.2685 | P24: 802.76576 | Q24: 9265.5097 | S24: A00 | T24: =Cmoyen!C3 -> 8903.7381 | U24: =Cmoyen!D3 -> 7273.3084 | V24: =Cmoyen!Q3 -> 3073.4509 | W24: =Cmoyen!R3 -> 5261.3341 | X24: =Cmoyen!S3 -> 7264.2987 | Y24: =Cmoyen!T3 -> 9755.9059 | Z24: =Cmoyen!U3 -> 16333.404
A25: B05 | B25: 203.093 | C25: 46.12926 | D25: -54.12654 | E25: 37.9723 | F25: -10.33008 | G25: 79.31883 | H25: 346.9522 | J25: B05 | K25: 195.69494 | L25: -351.09995 | M25: -107.56785 | N25: -88.840331 | O25: -442.14459 | P25: -342.84841 | Q25: 1529.5759 | S25: B05 | T25: =Cmoyen!C4 -> 999.09308 | U25: =Cmoyen!D4 -> 490.12816 | V25: =Cmoyen!Q4 -> 259.93889 | W25: =Cmoyen!R4 -> 444.3664 | X25: =Cmoyen!S4 -> 623.63664 | Y25: =Cmoyen!T4 -> 907.19373 | Z25: =Cmoyen!U4 -> 1799.0147
A26: C00 | B26: 23.63762 | C26: 21.25776 | D26: 2.010127 | E26: 6.382972 | F26: 13.91652 | G26: 20.37423 | H26: 48.03528 | J26: C00 | K26: 16.239565 | L26: -375.97145 | M26: -51.431184 | N26: -120.42966 | O26: -417.89799 | P26: -401.79301 | Q26: 1230.659 | S26: C00 | T26: =Cmoyen!C5 -> 36.639876 | U26: =Cmoyen!D5 -> 45.558503 | V26: =Cmoyen!Q5 -> 20.26138 | W26: =Cmoyen!R5 -> 32.050804 | X26: =Cmoyen!S5 -> 40.190871 | Y26: =Cmoyen!T5 -> 48.591316 | Z26: =Cmoyen!U5 -> 60.967972
A27: D01 | B27: 8182.226 | C27: 4899.013 | D27: 307.5542 | E27: 757.6595 | F27: 5560.505 | G27: 3880.171 | H27: 17213.97 | J27: D01 | K27: 8174.8279 | L27: 4501.7838 | M27: 254.11289 | N27: 630.84687 | O27: 5128.6905 | P27: 3458.0038 | Q27: 18396.594 | S27: D01 | T27: =Cmoyen!C6 -> 14805.197 | U27: =Cmoyen!D6 -> 14469.376 | V27: =Cmoyen!Q6 -> 6558.1514 | W27: =Cmoyen!R6 -> 10613.166 | X27: =Cmoyen!S6 -> 13693.826 | Y27: =Cmoyen!T6 -> 17718.93 | Z27: =Cmoyen!U6 -> 25344.363
A28: D02 | B28: -338.3088 | C28: -196.709 | D28: -244.0005 | E28: -570.4854 | F28: -378.7966 | G28: -926.5252 | H28: 426.8179 | J28: D02 | K28: -345.70686 | L28: -593.93821 | M28: -297.44181 | N28: -697.29803 | O28: -810.61111 | P28: -1348.6924 | Q28: 1609.4416 | S28: D02 | T28: =Cmoyen!C7 -> 2635.0914 | U28: =Cmoyen!D7 -> 1627.5919 | V28: =Cmoyen!Q7 -> 492.80694 | W28: =Cmoyen!R7 -> 969.35768 | X28: =Cmoyen!S7 -> 1513.7152 | Y28: =Cmoyen!T7 -> 2477.4505 | Z28: =Cmoyen!U7 -> 5890.0111
A29: D03 | B29: 1054.754 | C29: 218.3792 | D29: -116.2874 | E29: 275.9315 | F29: -271.1879 | G29: -162.3641 | H29: 2466.258 | J29: D03 | K29: 1047.3559 | L29: -178.85001 | M29: -169.72871 | N29: 149.11887 | O29: -703.00241 | P29: -584.53134 | Q29: 3648.8817 | S29: D03 | T29: =Cmoyen!C8 -> 2823.4891 | U29: =Cmoyen!D8 -> 1739.5947 | V29: =Cmoyen!Q8 -> 771.24545 | W29: =Cmoyen!R8 -> 1443.3091 | X29: =Cmoyen!S8 -> 2019.1094 | Y29: =Cmoyen!T8 -> 2810.9826 | Z29: =Cmoyen!U8 -> 5055.0703
A30: D04 | B30: -5492.049 | C30: -2391.524 | D30: -156.2211 | E30: -230.7233 | F30: -1028.797 | G30: -909.3222 | H30: -13009.62 | J30: D04 | K30: -5499.4471 | L30: -2788.7532 | M30: -209.66241 | N30: -357.53593 | O30: -1460.6115 | P30: -1331.4894 | Q30: -11826.996 | S30: D04 | T30: =Cmoyen!C9 -> 3992.0106 | U30: =Cmoyen!D9 -> 1921.7387 | V30: =Cmoyen!Q9 -> 463.09525 | W30: =Cmoyen!R9 -> 854.39989 | X30: =Cmoyen!S9 -> 1406.1362 | Y30: =Cmoyen!T9 -> 2228.4645 | Z30: =Cmoyen!U9 -> 11211.413
A31: D05 | B31: -421.8057 | C31: -195.9771 | D31: -42.00931 | E31: -129.7038 | F31: -194.7731 | G31: -368.2737 | H31: -355.1542 | J31: D05 | K31: -429.20376 | L31: -593.20631 | M31: -95.450621 | N31: -256.51643 | O31: -626.58761 | P31: -790.44094 | Q31: 827.46948 | S31: D05 | T31: =Cmoyen!C10 -> 800.99902 | U31: =Cmoyen!D10 -> 468.08512 | V31: =Cmoyen!Q10 -> 118.14339 | W31: =Cmoyen!R10 -> 227.83415 | X31: =Cmoyen!S10 -> 364.71874 | Y31: =Cmoyen!T10 -> 605.12473 | Z31: =Cmoyen!U10 -> 2087.1961
A32: D23 | B32: -2562.946 | C32: -814.149 | D32: 242.6336 | E32: 356.3714 | F32: 697.5578 | G32: 266.8178 | H32: -7113.544 | J32: D23 | K32: -2570.3441 | L32: -1211.3782 | M32: 189.19229 | N32: 229.55877 | O32: 265.74329 | P32: -155.34944 | Q32: -5930.9203 | S32: D23 | T32: =Cmoyen!C11 -> 3327.6159 | U32: =Cmoyen!D11 -> 2180.5471 | V32: =Cmoyen!Q11 -> 964.24832 | W32: =Cmoyen!R11 -> 1427.0875 | X32: =Cmoyen!S11 -> 1840.5744 | Y32: =Cmoyen!T11 -> 2430.7236 | Z32: =Cmoyen!U11 -> 7899.3666
A33: E00 | B33: 1340.92 | C33: 917.1245 | D33: 331.566 | E33: 581.1782 | F33: 999.285 | G33: 911.6127 | H33: 2045.601 | J33: E00 | K33: 1333.5219 | L33: 519.89529 | M33: 278.12469 | N33: 454.36557 | O33: 567.47049 | P33: 489.44546 | Q33: 3228.2247 | S33: E00 | T33: =Cmoyen!C12 -> 2182.9144 | U33: =Cmoyen!D12 -> 1874.2565 | V33: =Cmoyen!Q12 -> 1134.8438 | W33: =Cmoyen!R12 -> 1629.8409 | X33: =Cmoyen!S12 -> 1950.614 | Y33: =Cmoyen!T12 -> 2351.0524 | Z33: =Cmoyen!U12 -> 3300.8768
A34: F45 | B34: -487.5243 | C34: -763.4414 | D34: -233.1098 | E34: -806.5016 | F34: -261.6919 | G34: 526.5921 | H34: 567.0766 | J34: F45 | K34: -494.92236 | L34: -1160.6706 | M34: -286.55111 | N34: -933.31423 | O34: -693.50641 | P34: 104.42486 | Q34: 1749.7003 | S34: F45 | T34: =Cmoyen!C13 -> 1566.3146 | U34: =Cmoyen!D13 -> 1601.961 | V34: =Cmoyen!Q13 -> 347.32592 | W34: =Cmoyen!R13 -> 655.66527 | X34: =Cmoyen!S13 -> 997.67225 | Y34: =Cmoyen!T13 -> 1603.154 | Z34: =Cmoyen!U13 -> 4418.2531
A35: G00 | B35: -1712.986 | C35: -728.4591 | D35: -18.60448 | E35: -83.58695 | F35: -33.92428 | G35: -267.5598 | H35: -4087.219 | J35: G00 | K35: -1720.3841 | L35: -1125.6883 | M35: -72.045791 | N35: -210.39958 | O35: -465.73879 | P35: -689.72704 | Q35: -2904.5953 | S35: G00 | T35: =Cmoyen!C14 -> 802.50325 | U35: =Cmoyen!D14 -> 357.49443 | V35: =Cmoyen!Q14 -> 35.284959 | W35: =Cmoyen!R14 -> 79.121741 | X35: =Cmoyen!S14 -> 167.73817 | Y35: =Cmoyen!T14 -> 317.26859 | Z35: =Cmoyen!U14 -> 2603.4298
... A43: OP0 | B43: -1138.221 | C43: -611.984 | D43: -137.8271 | E43: -8.658228 | F43: 79.938 | G43: -678.8163 | H43: -2224.264 | J43: OP0 | K43: -1145.6191 | L43: -1009.2132 | M43: -191.26841 | N43: -135.47086 | O43: -351.87651 | P43: -1100.9835 | Q43: -1041.6403 | S43: OP0 | T43: =Cmoyen!C22 -> 2767.3952 | U43: =Cmoyen!D22 -> 1311.4114 | V43: =Cmoyen!Q22 -> 430.4411 | W43: =Cmoyen!R22 -> 907.51312 | X43: =Cmoyen!S22 -> 1388.3668 | Y43: =Cmoyen!T22 -> 2095.7701 | Z43: =Cmoyen!U22 -> 6301.8111

Sheet 20pdts2014
A1: beta-14 | B1: M1 | C1: M2 | D1: Q1 | E1: Q2 | F1: Q3 | G1: Q4 | H1: Q5 | J1: Elasticité-revenu 2014 | K1: M1 | L1: M2 | M1: Q1 | N1: Q2 | O1: Q3 | P1: Q4 | Q1: Q5 | S1: Elasticité-Prix 2014 | T1: M1 | U1: M2 | V1: Q1 | W1: Q2 | X1: Q3 | Y1: Q4 | Z1: Q5 | AB1: CB | AC1: M1 | AD1: M2 | AE1: Q1 | AF1: Q2 | AG1: Q3 | AH1: Q4 | AI1: Q5 | AJ1: CB-2014
A2: A00 | B2: 0.0470224 | C2: 0.1347135 | D2: 0.2015948 | E2: 0.1581558 | F2: 0.1443382 | G2: 0.1029208 | H2: 0.0378726 | J2: A00 | K2: =B2/AC2 -> 0.43941571 | L2: =C2/AD2 -> 0.68726763 | M2: =D2/AE2 -> 1.0081283 | N2: =E2/AF2 -> 0.92102559 | O2: =F2/AG2 -> 0.93601863 | P2: =G2/AH2 -> 0.7847426 | Q2: =H2/AI2 -> 0.44912121 | S2: A00 | T2: =IF(T24=0,0,((1-B2)*(K24/T24))-1) -> -0.46925147 | U2: =IF(U24=0,0,((1-C2)*(L24/U24))-1) -> -0.76764886 | V2: =IF(V24=0,0,((1-D2)*(M24/V24))-1) -> -1.0159987 | W2: =IF(W24=0,0,((1-E2)*(N24/W24))-1) -> -0.9571373 | X2: =IF(X24=0,0,((1-F2)*(O24/X24))-1) -> -0.96999894 | Y2: =IF(Y24=0,0,((1-G2)*(P24/Y24))-1) -> -0.83774863 | Z2: =IF(Z24=0,0,((1-H2)*(Q24/Z24))-1) -> -0.43986601 | AB2: A00 | AC2: 0.1070112 | AD2: 0.19601316 | AE2: 0.19996939 | AF2: 0.17171705 | AG2: 0.15420441 | AH2: 0.1311523 | AI2: 0.084326011 | AJ2: A00
A3: B05 | B3: 0.0131922 | C3: 0.0113468 | D3: 0.0136562 | E3: 0.0123499 | F3: 0.0132427 | G3: 0.0152598 | H3: 0.0124194 | J3: B05 | K3: =B3/AC3 -> 0.91298027 | L3: =C3/AD3 -> 0.87564473 | M3: =D3/AE3 -> 1.0302135 | N3: =E3/AF3 -> 0.84754111 | O3: =F3/AG3 -> 0.93151282 | P3: =G3/AH3 -> 1.0645746 | Q3: =H3/AI3 -> 0.89581221 | S3: B05 | T3: =IF(T25=0,0,((1-B3)*(K25/T25))-1) -> -0.94078405 | U3: =IF(U25=0,0,((1-C3)*(L25/U25))-1) -> -1.5381681 | V3: =IF(V25=0,0,((1-D3)*(M25/V25))-1) -> -1.2070165 | W3: =IF(W25=0,0,((1-E3)*(N25/W25))-1) -> -1.1760003 | X3: =IF(X25=0,0,((1-F3)*(O25/X25))-1) -> -1.2419467 | Y3: =IF(Y25=0,0,((1-G3)*(P25/Y25))-1) -> -1.3734577 | Z3: =IF(Z25=0,0,((1-H3)*(Q25/Z25))-1) -> -0.70906684 | AB3: B05 | AC3: 0.0144496 | AD3: 0.012958223 | AE3: 0.013255699 | AF3: 0.014571446 | AG3: 0.014216337 | AH3: 0.014334176 | AI3: 0.013863843 | AJ3: B05
A4: C00 | B4: 5.87e-05 | C4: 0.0005982 | D4: 0.0008966 | E4: 0.0007401 | F4: 0.0004352 | G4: 0.000316 | H4: 5.33e-05 | J4: C00 | K4: =B4/AC4 -> 0.14988081 | L4: =C4/AD4 -> 0.49977364 | M4: =D4/AE4 -> 0.70487045 | N4: =E4/AF4 -> 0.80695521 | O4: =F4/AG4 -> 0.6035612 | P4: =G4/AH4 -> 0.55729799 | Q4: =H4/AI4 -> 0.19943148 | S4: C00 | T4: =IF(T26=0,0,((1-B4)*(K26/T26))-1) -> -1.1464155 | U4: =IF(U26=0,0,((1-C4)*(L26/U26))-1) -> -7.7351474 | V4: =IF(V26=0,0,((1-D4)*(M26/V26))-1) -> -2.5757508 | W4: =IF(W26=0,0,((1-E4)*(N26/W26))-1) -> -6.056691 | X4: =IF(X26=0,0,((1-F4)*(O26/X26))-1) -> -6.7855923 | Y4: =IF(Y26=0,0,((1-G4)*(P26/Y26))-1) -> -8.5095617 | Z4: =IF(Z26=0,0,((1-H4)*(Q26/Z26))-1) -> 9.6770588 | AB4: C00 | AC4: 0.00039164453 | AD4: 0.0011969419 | AE4: 0.0012720068 | AF4: 0.00091715127 | AG4: 0.00072105364 | AH4: 0.0005670216 | AI4: 0.00026725971 | AJ4: C00
A5: D01 | B5: 0.1029789 | C5: 0.1940067 | D5: 0.2834289 | E5: 0.2450719 | F5: 0.2244558 | G5: 0.1793792 | H5: 0.0839503 | J5: D01 | K5: =B5/AC5 -> 0.49934654 | L5: =C5/AD5 -> 0.67609162 | M5: =D5/AE5 -> 0.94815138 | N5: =E5/AF5 -> 0.87102785 | O5: =F5/AG5 -> 0.8483727 | P5: =G5/AH5 -> 0.75780866 | Q5: =H5/AI5 -> 0.50813638 | S5: D01 | T5: =IF(T27=0,0,((1-B5)*(K27/T27))-1) -> -0.55260077 | U5: =IF(U27=0,0,((1-C5)*(L27/U27))-1) -> -0.76327063 | V5: =IF(V27=0,0,((1-D5)*(M27/V27))-1) -> -0.96855613 | W5: =IF(W27=0,0,((1-E5)*(N27/W27))-1) -> -0.91556335 | X5: =IF(X27=0,0,((1-F5)*(O27/X27))-1) -> -0.89547843 | Y5: =IF(Y27=0,0,((1-G5)*(P27/Y27))-1) -> -0.81688994 | Z5: =IF(Z27=0,0,((1-H5)*(Q27/Z27))-1) -> -0.53479219 | AB5: D01 | AC5: 0.20622732 | AD5: 0.28695327 | AE5: 0.2989279 | AF5: 0.28135943 | AG5: 0.26457216 | AH5: 0.23670777 | AI5: 0.16521214 | AJ5: D01
A6: D02 | B6: 0.0523622 | C6: 0.0476485 | D6: 0.0494428 | E6: 0.0499941 | F6: 0.0460122 | G6: 0.0492105 | H6: 0.0574054 | J6: D02 | K6: =B6/AC6 -> 1.3992968 | L6: =C6/AD6 -> 1.2880911 | M6: =D6/AE6 -> 1.6131836 | N6: =E6/AF6 -> 1.5097089 | O6: =F6/AG6 -> 1.2173575 | P6: =G6/AH6 -> 1.2576494 | Q6: =H6/AI6 -> 1.4575589 | S6: D02 | T6: =IF(T28=0,0,((1-B6)*(K28/T28))-1) -> -1.3882729 | U6: =IF(U28=0,0,((1-C6)*(L28/U28))-1) -> -1.4974515 | V6: =IF(V28=0,0,((1-D6)*(M28/V28))-1) -> -1.6567292 | W6: =IF(W28=0,0,((1-E6)*(N28/W28))-1) -> -1.6224516 | X6: =IF(X28=0,0,((1-F6)*(O28/X28))-1) -> -1.3199136 | Y6: =IF(Y28=0,0,((1-G6)*(P28/Y28))-1) -> -1.3545694 | Z6: =IF(Z28=0,0,((1-H6)*(Q28/Z28))-1) -> -1.3681163 | AB6: D02 | AC6: 0.037420366 | AD6: 0.036991562 | AE6: 0.030649209 | AF6: 0.033115059 | AG6: 0.037796784 | AH6: 0.03912895 | AI6: 0.039384618 | AJ6: D02
A7: D03 | B7: 0.0435263 | C7: 0.0539264 | D7: 0.0579767 | E7: 0.055323 | F7: 0.0536292 | G7: 0.0575638 | H7: 0.0398668 | J7: D03 | K7: =B7/AC7 -> 0.8938189 | L7: =C7/AD7 -> 1.0997427 | M7: =D7/AE7 -> 1.2205015 | N7: =E7/AF7 -> 1.1264975 | O7: =F7/AG7 -> 1.0895546 | P7: =G7/AH7 -> 1.1435966 | Q7: =H7/AI7 -> 0.83214508 | S7: D03 | T7: =IF(T29=0,0,((1-B7)*(K29/T29))-1) -> -0.90610565 | U7: =IF(U29=0,0,((1-C7)*(L29/U29))-1) -> -1.2615479 | V7: =IF(V29=0,0,((1-D7)*(M29/V29))-1) -> -1.2549474 | W7: =IF(W29=0,0,((1-E7)*(N29/W29))-1) -> -1.21218 | X7: =IF(X29=0,0,((1-F7)*(O29/X29))-1) -> -1.1704938 | Y7: =IF(Y29=0,0,((1-G7)*(P29/Y29))-1) -> -1.2197807 | Z7: =IF(Z29=0,0,((1-H7)*(Q29/Z29))-1) -> -0.78593367 | AB7: D03 | AC7: 0.048697001 | AD7: 0.049035472 | AE7: 0.047502358 | AF7: 0.049110626 | AG7: 0.049221215 | AH7: 0.050335754 | AI7: 0.047908473 | AJ7: D03
A8: D04 | B8: 0.0940943 | C8: 0.0607339 | D8: 0.020388 | E8: 0.0380171 | F8: 0.0332085 | G8: 0.0548393 | H8: 0.1115951 | J8: D04 | K8: =B8/AC8 -> 2.3605374 | L8: =C8/AD8 -> 2.3144919 | M8: =D8/AE8 -> 1.1481887 | N8: =E8/AF8 -> 1.8717413 | O8: =F8/AG8 -> 1.4716277 | P8: =G8/AH8 -> 1.7825806 | Q8: =H8/AI8 -> 1.9652021 | S8: D04 | T8: =IF(T30=0,0,((1-B8)*(K30/T30))-1) -> -2.2413891 | U8: =IF(U30=0,0,((1-C8)*(L30/U30))-1) -> -2.5448232 | V8: =IF(V30=0,0,((1-D8)*(M30/V30))-1) -> -1.2765565 | W8: =IF(W30=0,0,((1-E8)*(N30/W30))-1) -> -2.0668026 | X8: =IF(X30=0,0,((1-F8)*(O30/X30))-1) -> -1.6470233 | Y8: =IF(Y30=0,0,((1-G8)*(P30/Y30))-1) -> -1.878242 | Z8: =IF(Z30=0,0,((1-H8)*(Q30/Z30))-1) -> -1.8161916 | AB8: D04 | AC8: 0.039861389 | AD8: 0.026240706 | AE8: 0.017756663 | AF8: 0.020311087 | AG8: 0.02256583 | AH8: 0.030763995 | AI8: 0.056785559 | AJ8: D04
A9: D05 | B9: 0.0167256 | C9: 0.0161845 | D9: 0.0082578 | E9: 0.0072641 | F9: 0.0088088 | G9: 0.0155573 | H9: 0.0166634 | J9: D05 | K9: =B9/AC9 -> 1.6027839 | L9: =C9/AD9 -> 1.9366787 | M9: =D9/AE9 -> 1.8144895 | N9: =E9/AF9 -> 1.2806437 | O9: =F9/AG9 -> 1.2370681 | P9: =G9/AH9 -> 1.5930688 | Q9: =H9/AI9 -> 1.1697722 | S9: D05 | T9: =IF(T31=0,0,((1-B9)*(K31/T31))-1) -> -1.6294804 | U9: =IF(U31=0,0,((1-C9)*(L31/U31))-1) -> -2.9416329 | V9: =IF(V31=0,0,((1-D9)*(M31/V31))-1) -> -2.3267504 | W9: =IF(W31=0,0,((1-E9)*(N31/W31))-1) -> -2.1218688 | X9: =IF(X31=0,0,((1-F9)*(O31/X31))-1) -> -1.8557282 | Y9: =IF(Y31=0,0,((1-G9)*(P31/Y31))-1) -> -2.0385284 | Z9: =IF(Z31=0,0,((1-H9)*(Q31/Z31))-1) -> -0.98471783 | AB9: D05 | AC9: 0.010435343 | AD9: 0.0083568328 | AE9: 0.004551032 | AF9: 0.0056722256 | AG9: 0.0071207074 | AH9: 0.0097656173 | AI9: 0.014244996 | AJ9: D05
A10: D23 | B10: 0.0396437 | C10: 0.0470316 | D10: 0.0292885 | E10: 0.0364507 | F10: 0.0392104 | G10: 0.0476646 | H10: 0.0389674 | J10: D23 | K10: =B10/AC10 -> 1.1492443 | L10: =C10/AD10 -> 1.2253802 | M10: =D10/AE10 -> 0.7958992 | N10: =E10/AF10 -> 1.1013455 | O10: =F10/AG10 -> 1.2372241 | P10: =G10/AH10 -> 1.3914532 | Q10: =H10/AI10 -> 1.01196 | S10: D23 | T10: =IF(T32=0,0,((1-B10)*(K32/T32))-1) -> -1.1541921 | U10: =IF(U32=0,0,((1-C10)*(L32/U32))-1) -> -1.4299289 | V10: =IF(V32=0,0,((1-D10)*(M32/V32))-1) -> -0.86469977 | W10: =IF(W32=0,0,((1-E10)*(N32/W32))-1) -> -1.2379255 | X10: =IF(X32=0,0,((1-F10)*(O32/X32))-1) -> -1.3631172 | Y10: =IF(Y32=0,0,((1-G10)*(P32/Y32))-1) -> -1.4981911 | Z10: =IF(Z32=0,0,((1-H10)*(Q32/Z32))-1) -> -0.9456121 | AB10: D23 | AC10: 0.03449545 | AD10: 0.03838123 | AE10: 0.036799258 | AF10: 0.033096517 | AG10: 0.031692237 | AH10: 0.034255267 | AI10: 0.038506857 | AJ10: D23
A11: E00 | B11: 0.0136935 | C11: 0.0139224 | D11: 0.0296782 | E11: 0.0272576 | F11: 0.028407 | G11: 0.0203938 | H11: 0.0120507 | J11: E00 | K11: =B11/AC11 -> 0.33935849 | L11: =C11/AD11 -> 0.40911001 | M11: =D11/AE11 -> 0.56419093 | N11: =E11/AF11 -> 0.55677895 | O11: =F11/AG11 -> 0.62716771 | P11: =G11/AH11 -> 0.51664714 | Q11: =H11/AI11 -> 0.43526639 | S11: E00 | T11: =IF(T33=0,0,((1-B11)*(K33/T33))-1) -> -0.35794383 | U11: =IF(U33=0,0,((1-C11)*(L33/U33))-1) -> -0.66841785 | V11: =IF(V33=0,0,((1-D11)*(M33/V33))-1) -> -0.62105727 | W11: =IF(W33=0,0,((1-E11)*(N33/W33))-1) -> -0.66459743 | X11: =IF(X33=0,0,((1-F11)*(O33/X33))-1) -> -0.73341825 | Y11: =IF(Y33=0,0,((1-G11)*(P33/Y33))-1) -> -0.63844029 | Z11: =IF(Z33=0,0,((1-H11)*(Q33/Z33))-1) -> -0.34787286 | AB11: E00 | AC11: 0.040351134 | AD11: 0.034030944 | AE11: 0.052603115 | AF11: 0.048955874 | AG11: 0.045294105 | AH11: 0.039473363 | AI11: 0.027685804 | AJ11: E00
A12: F45 | B12: 0.0258411 | C12: 0.0640816 | D12: 0.0210816 | E12: 0.030812 | F12: 0.0388789 | G12: 0.0390992 | H12: 0.0239583 | J12: F45 | K12: =B12/AC12 -> 1.2938645 | L12: =C12/AD12 -> 2.177485 | M12: =D12/AE12 -> 1.929453 | N12: =E12/AF12 -> 1.9540441 | O12: =F12/AG12 -> 1.9035969 | P12: =G12/AH12 -> 1.5996144 | Q12: =H12/AI12 -> 0.86265025 | S12: F45 | T12: =IF(T34=0,0,((1-B12)*(K34/T34))-1) -> -1.3053063 | U12: =IF(U34=0,0,((1-C12)*(L34/U34))-1) -> -2.377605 | V12: =IF(V34=0,0,((1-D12)*(M34/V34))-1) -> -2.1232328 | W12: =IF(W34=0,0,((1-E12)*(N34/W34))-1) -> -2.2207943 | X12: =IF(X34=0,0,((1-F12)*(O34/X34))-1) -> -2.0783226 | Y12: =IF(Y34=0,0,((1-G12)*(P34/Y34))-1) -> -1.7534853 | Z12: =IF(Z34=0,0,((1-H12)*(Q34/Z34))-1) -> -0.7731724 | AB12: F45 | AC12: 0.019972029 | AD12: 0.029429181 | AE12: 0.010926206 | AF12: 0.015768324 | AG12: 0.020423914 | AH12: 0.02444289 | AI12: 0.027772901 | AJ12: F45
A13: G00 | B13: 0.0223932 | C13: 0.0293234 | D13: 0.0105011 | E13: 0.0124613 | F13: 0.0201053 | G13: 0.0325594 | H13: 0.0207139 | J13: G00 | K13: =B13/AC13 -> 1.7969774 | L13: =C13/AD13 -> 2.5575422 | M13: =D13/AE13 -> 2.6253203 | N13: =E13/AF13 -> 2.525217 | O13: =F13/AG13 -> 2.729942 | P13: =G13/AH13 -> 2.4549828 | Q13: =H13/AI13 -> 1.1079869 | S13: G00 | T13: =IF(T35=0,0,((1-B13)*(K35/T35))-1) -> -1.8097463 | U13: =IF(U35=0,0,((1-C13)*(L35/U35))-1) -> -3.2454699 | V13: =IF(V35=0,0,((1-D13)*(M35/V35))-1) -> -3.1974184 | W13: =IF(W35=0,0,((1-E13)*(N35/W35))-1) -> -3.4704182 | X13: =IF(X35=0,0,((1-F13)*(O35/X35))-1) -> -3.2885067 | Y13: =IF(Y35=0,0,((1-G13)*(P35/Y35))-1) -> -2.7366304 | Z13: =IF(Z35=0,0,((1-H13)*(Q35/Z35))-1) -> -0.96747661 | AB13: G00 | AC13: 0.012461593 | AD13: 0.011465461 | AE13: 0.003999931 | AF13: 0.0049347442 | AG13: 0.0073647352 | AH13: 0.013262578 | AI13: 0.018695076 | AJ13: G00
... A21: OP0 | B21: 0.0872994 | C21: 0.0490094 | D21: 0.0342167 | E21: 0.0389905 | F21: 0.038869 | G21: 0.0416842 | H21: 0.0998879 | J21: OP0 | K21: =B21/AC21 -> 1.8280613 | L21: =C21/AD21 -> 1.6947389 | M21: =D21/AE21 -> 1.3759452 | N21: =E21/AF21 -> 1.2817967 | O21: =F21/AG21 -> 1.1785491 | P21: =G21/AH21 -> 1.1449787 | Q21: =H21/AI21 -> 1.6479335 | S21: OP0 | T21: =IF(T43=0,0,((1-B21)*(K43/T43))-1) -> -1.7632311 | U21: =IF(U43=0,0,((1-C21)*(L43/U43))-1) -> -1.945646 | V21: =IF(V43=0,0,((1-D21)*(M43/V43))-1) -> -1.4555749 | W21: =IF(W43=0,0,((1-E21)*(N43/W43))-1) -> -1.423029 | X21: =IF(X43=0,0,((1-F21)*(O43/X43))-1) -> -1.3015678 | Y21: =IF(Y43=0,0,((1-G21)*(P43/Y43))-1) -> -1.2576663 | Z21: =IF(Z43=0,0,((1-H21)*(Q43/Z43))-1) -> -1.544013 | AB21: OP0 | AC21: 0.047755182 | AD21: 0.028918554 | AE21: 0.024867778 | AF21: 0.03041863 | AG21: 0.032980383 | AH21: 0.036406091 | AI21: 0.060614035 | AJ21: OP0
A23: alpha-14 | B23: M1 | C23: M2 | D23: Q1 | E23: Q2 | F23: Q3 | G23: Q4 | H23: Q5 | J23: CMIN | K23: M1 | L23: M2 | M23: Q1 | N23: Q2 | O23: Q3 | P23: Q4 | Q23: Q5 | S23: Cmoyen | T23: M1 | U23: M2 | V23: Q1 | W23: Q2 | X23: Q3 | Y23: Q4 | Z23: Q5
A24: A00 | B24: 5124.199 | C24: 3423.398 | D24: -60.96007 | E24: 696.0611 | F24: 628.7005 | G24: 2336.466 | H24: 6589.361 | J24: A00 | K24: 5090.8615 | L24: 2939.4734 | M24: -150.27922 | N24: 448.75598 | O24: 344.53113 | P24: 1963.1735 | Q24: 6963.8056 | S24: A00 | T24: =Cmoyen!F3 -> 9140.8204 | U24: =Cmoyen!G3 -> 10946.736 | V24: =Cmoyen!X3 -> 7499.5859 | W24: =Cmoyen!Y3 -> 8813.7856 | X24: =Cmoyen!Z3 -> 9826.3904 | Y24: =Cmoyen!AA3 -> 10854.282 | Z24: =Cmoyen!AB3 -> 11961.545
A25: B05 | B25: 107.4033 | C25: 89.99472 | D25: -15.02138 | E25: 114.026 | F25: 62.04597 | G25: -76.60921 | H25: 204.8908 | J25: B05 | K25: 74.06584 | L25: -393.92985 | M25: -104.34053 | N25: -133.27912 | O25: -222.1234 | P25: -449.90173 | Q25: 579.33538 | S25: B05 | T25: =Cmoyen!F4 -> 1234.2746 | U25: =Cmoyen!G4 -> 723.67721 | V25: =Cmoyen!X4 -> 497.13735 | W25: =Cmoyen!Y4 -> 747.9141 | X25: =Cmoyen!Z4 -> 905.90974 | Y25: =Cmoyen!AA4 -> 1186.3092 | Z25: =Cmoyen!AB4 -> 1966.5698
A26: C00 | B26: 28.43899 | C26: 33.44046 | D26: 14.08062 | E26: 9.085246 | F26: 18.21835 | G26: 20.7783 | H26: 30.34938 | J26: C00 | K26: -4.8984704 | L26: -450.48411 | M26: -75.238531 | N26: -238.21987 | O26: -265.95102 | P26: -352.51422 | Q26: 404.79396 | S26: C00 | T26: =Cmoyen!F5 -> 33.453998 | U26: =Cmoyen!G5 -> 66.845549 | V26: =Cmoyen!X5 -> 47.704923 | W26: =Cmoyen!Y5 -> 47.074967 | X26: =Cmoyen!Z5 -> 45.947808 | Y26: =Cmoyen!AA5 -> 46.927215 | Z26: =Cmoyen!AB5 -> 37.910476
A27: D01 | B27: 8819.409 | C27: 5190.785 | D27: 581.2645 | E27: 1862.541 | F27: 2556.339 | G27: 4744.56 | H27: 11526.89 | J27: D01 | K27: 8786.0715 | L27: 4706.8604 | M27: 491.94535 | N27: 1615.2359 | O27: 2272.1696 | P27: 4371.2675 | Q27: 11901.335 | S27: D01 | T27: =Cmoyen!F6 -> 17615.792 | U27: =Cmoyen!G6 -> 16025.464 | V27: =Cmoyen!X6 -> 11210.893 | W27: =Cmoyen!Y6 -> 14441.441 | X27: =Cmoyen!Z6 -> 16859.371 | Y27: =Cmoyen!AA6 -> 19590.147 | Z27: =Cmoyen!AB6 -> 23435.148
A28: D02 | B28: -1276.323 | C28: -595.1602 | D28: -704.8282 | E28: -866.3581 | F28: -523.5154 | G28: -834.3551 | H28: -2556.232 | J28: D02 | K28: -1309.6605 | L28: -1079.0848 | M28: -794.14735 | N28: -1113.6632 | O28: -807.68477 | P28: -1207.6476 | Q28: -2181.7874 | S28: D02 | T28: =Cmoyen!F7 -> 3196.4211 | U28: =Cmoyen!G7 -> 2065.8658 | V28: =Cmoyen!X7 -> 1149.4578 | W28: =Cmoyen!Y7 -> 1699.7091 | X28: =Cmoyen!Z7 -> 2408.5301 | Y28: =Cmoyen!AA7 -> 3238.3469 | Z28: =Cmoyen!AB7 -> 5586.6618
A29: D03 | B29: 441.68 | C29: -273.1456 | D29: -392.8261 | E29: -318.8634 | F29: -280.8934 | G29: -598.1996 | H29: 1140.703 | J29: D03 | K29: 408.34254 | L29: -757.07017 | M29: -482.14525 | N29: -566.16852 | O29: -565.06277 | P29: -971.49212 | Q29: 1515.1476 | S29: D03 | T29: =Cmoyen!F8 -> 4159.6633 | U29: =Cmoyen!G8 -> 2738.4814 | V29: =Cmoyen!X8 -> 1781.5128 | W29: =Cmoyen!Y8 -> 2520.7195 | X29: =Cmoyen!Z8 -> 3136.5308 | Y29: =Cmoyen!AA8 -> 4165.8321 | Z29: =Cmoyen!AB8 -> 6795.7605
A30: D04 | B30: -4632.54 | C30: -1926.342 | D30: -98.68393 | E30: -908.8043 | F30: -678.1864 | G30: -1992.499 | H30: -7774.668 | J30: D04 | K30: -4665.8775 | L30: -2410.2666 | M30: -188.00308 | N30: -1156.1094 | O30: -962.35577 | P30: -2365.7915 | Q30: -7400.2234 | S30: D04 | T30: =Cmoyen!F9 -> 3404.9316 | U30: =Cmoyen!G9 -> 1465.4633 | V30: =Cmoyen!X9 -> 665.94005 | W30: =Cmoyen!Y9 -> 1042.5148 | X30: =Cmoyen!Z9 -> 1437.9657 | Y30: =Cmoyen!AA9 -> 2546.0558 | Z30: =Cmoyen!AB9 -> 8054.9648
A31: D05 | B31: -537.313 | C31: -437.1496 | D31: -139.0167 | E31: -81.70624 | F31: -107.5714 | G31: -479.3222 | H31: -343.0416 | J31: D05 | K31: -570.65046 | L31: -921.07417 | M31: -228.33585 | N31: -329.01136 | O31: -391.74077 | P31: -852.61472 | Q31: 31.402978 | S31: D05 | T31: =Cmoyen!F10 -> 891.37963 | U31: =Cmoyen!G10 -> 466.7036 | V31: =Cmoyen!X10 -> 170.6804 | W31: =Cmoyen!Y10 -> 291.14045 | X31: =Cmoyen!Z10 -> 453.75389 | Y31: =Cmoyen!AA10 -> 808.21123 | Z31: =Cmoyen!AB10 -> 2020.6359
A32: D23 | B32: -439.7566 | C32: -483.0976 | D32: 281.682 | E32: -172.1624 | F32: -479.0838 | G32: -1109.767 | H32: -65.32395 | J32: D23 | K32: -473.09406 | L32: -967.02217 | M32: 192.36285 | N32: -419.46752 | O32: -763.25317 | P32: -1483.0595 | Q32: 309.12063 | S32: D23 | T32: =Cmoyen!F11 -> 2946.5769 | U32: =Cmoyen!G11 -> 2143.4745 | V32: =Cmoyen!X11 -> 1380.1072 | W32: =Cmoyen!Y11 -> 1698.7574 | X32: =Cmoyen!Z11 -> 2019.5291 | Y32: =Cmoyen!AA11 -> 2834.9966 | Z32: =Cmoyen!AB11 -> 5462.1524
A33: E00 | B33: 2277.079 | C33: 1123.002 | D33: 859.7666 | E33: 1113.713 | F33: 1076.096 | G33: 1579.044 | H33: 2217.827 | J33: E00 | K33: 2243.7415 | L33: 639.07743 | M33: 770.44745 | N33: 866.40788 | O33: 791.92663 | P33: 1205.7515 | Q33: 2592.2716 | S33: E00 | T33: =Cmoyen!F12 -> 3446.7652 | U33: =Cmoyen!G12 -> 1900.5243 | V33: =Cmoyen!X12 -> 1972.8099 | W33: =Cmoyen!Y12 -> 2512.7765 | X33: =Cmoyen!Z12 -> 2886.283 | Y33: =Cmoyen!AA12 -> 3266.8508 | Z33: =Cmoyen!AB12 -> 3927.1987
A34: F45 | B34: -501.3305 | C34: -1935.234 | D34: -380.8633 | E34: -772.1522 | F34: -1176.012 | G34: -1212.966 | H34: 541.0895 | J34: F45 | K34: -534.66796 | L34: -2419.1586 | M34: -470.18245 | N34: -1019.4573 | O34: -1460.1814 | P34: -1586.2585 | Q34: 915.53408 | S34: F45 | T34: =Cmoyen!F13 -> 1705.9965 | U34: =Cmoyen!G13 -> 1643.5299 | V34: =Cmoyen!X13 -> 409.77281 | W34: =Cmoyen!Y13 -> 809.34667 | X34: =Cmoyen!Z13 -> 1301.4761 | Y34: =Cmoyen!AA13 -> 2022.9155 | Z34: =Cmoyen!AB13 -> 3939.5533
A35: G00 | B35: -848.3492 | C35: -997.3093 | D35: -243.8185 | E35: -386.3166 | F35: -811.8725 | G35: -1597.025 | H35: -286.3723 | J35: G00 | K35: -881.68666 | L35: -1481.2339 | M35: -333.13765 | N35: -633.62172 | O35: -1096.0419 | P35: -1970.3175 | Q35: 88.072278 | S35: G00 | T35: =Cmoyen!F14 -> 1064.4604 | U35: =Cmoyen!G14 -> 640.31098 | V35: =Cmoyen!X14 -> 150.01209 | W35: =Cmoyen!Y14 -> 253.28746 | X35: =Cmoyen!Z14 -> 469.30411 | Y35: =Cmoyen!AA14 -> 1097.6228 | Z35: =Cmoyen!AB14 -> 2651.8746
... A43: OP0 | B43: -3377.839 | C43: -1122.012 | D43: -350.6182 | E43: -439.9709 | F43: -375.2402 | G43: -436.8253 | H43: -5570.953 | J43: OP0 | K43: -3411.1765 | L43: -1605.9366 | M43: -439.93735 | N43: -687.27602 | O43: -659.40957 | P43: -810.11782 | Q43: -5196.5084 | S43: OP0 | T43: =Cmoyen!F22 -> 4079.2138 | U43: =Cmoyen!G22 -> 1615.013 | V43: =Cmoyen!X22 -> 932.63295 | W43: =Cmoyen!Y22 -> 1561.3084 | X43: =Cmoyen!Z22 -> 2101.6139 | Y43: =Cmoyen!AA22 -> 3013.0007 | Z43: =Cmoyen!AB22 -> 8598.0296
J45: VAR Elasticité-revenu 2014/2007 | K45: M1 | L45: M2 | M45: Q1 | N45: Q2 | O45: Q3 | P45: Q4 | Q45: Q5
J46: A00 | K46: =IF('20pdts2007'!K2=0,0,'20pdts2014'!K2/'20pdts2007'!K2-1) -> -0.27332756 | L46: =IF('20pdts2007'!L2=0,0,'20pdts2014'!L2/'20pdts2007'!L2-1) -> -0.20533393 | M46: =IF('20pdts2007'!M2=0,0,'20pdts2014'!M2/'20pdts2007'!M2-1) -> -0.048470354 | N46: =IF('20pdts2007'!N2=0,0,'20pdts2014'!N2/'20pdts2007'!N2-1) -> -0.082922194 | O46: =IF('20pdts2007'!O2=0,0,'20pdts2014'!O2/'20pdts2007'!O2-1) -> 0.22091138 | P46: =IF('20pdts2007'!P2=0,0,'20pdts2014'!P2/'20pdts2007'!P2-1) -> -0.10257892 | Q46: =IF('20pdts2007'!Q2=0,0,'20pdts2014'!Q2/'20pdts2007'!Q2-1) -> -0.1108821
J47: B05 | K47: =IF('20pdts2007'!K3=0,0,'20pdts2014'!K3/'20pdts2007'!K3-1) -> 0.14591767 | L47: =IF('20pdts2007'!L3=0,0,'20pdts2014'!L3/'20pdts2007'!L3-1) -> -0.033378261 | M47: =IF('20pdts2007'!M3=0,0,'20pdts2014'!M3/'20pdts2007'!M3-1) -> -0.14733413 | N47: =IF('20pdts2007'!N3=0,0,'20pdts2014'!N3/'20pdts2007'!N3-1) -> -0.073264593 | O47: =IF('20pdts2007'!O3=0,0,'20pdts2014'!O3/'20pdts2007'!O3-1) -> -0.083668225 | P47: =IF('20pdts2007'!P3=0,0,'20pdts2014'!P3/'20pdts2007'!P3-1) -> 0.1665705 | Q47: =IF('20pdts2007'!Q3=0,0,'20pdts2014'!Q3/'20pdts2007'!Q3-1) -> 0.109854
J48: C00 | K48: =IF('20pdts2007'!K4=0,0,'20pdts2014'!K4/'20pdts2007'!K4-1) -> -0.57773738 | L48: =IF('20pdts2007'!L4=0,0,'20pdts2014'!L4/'20pdts2007'!L4-1) -> -0.063112894 | M48: =IF('20pdts2007'!M4=0,0,'20pdts2014'!M4/'20pdts2007'!M4-1) -> -0.21747412 | N48: =IF('20pdts2007'!N4=0,0,'20pdts2014'!N4/'20pdts2007'!N4-1) -> 0.0075946106 | O48: =IF('20pdts2007'!O4=0,0,'20pdts2014'!O4/'20pdts2007'!O4-1) -> -0.076739623 | P48: =IF('20pdts2007'!P4=0,0,'20pdts2014'!P4/'20pdts2007'!P4-1) -> -0.040278706 | Q48: =IF('20pdts2007'!Q4=0,0,'20pdts2014'!Q4/'20pdts2007'!Q4-1) -> -0.060066849
J49: D01 | K49: =IF('20pdts2007'!K5=0,0,'20pdts2014'!K5/'20pdts2007'!K5-1) -> 0.11625467 | L49: =IF('20pdts2007'!L5=0,0,'20pdts2014'!L5/'20pdts2007'!L5-1) -> 0.022179001 | M49: =IF('20pdts2007'!M5=0,0,'20pdts2014'!M5/'20pdts2007'!M5-1) -> -0.0051957965 | N49: =IF('20pdts2007'!N5=0,0,'20pdts2014'!N5/'20pdts2007'!N5-1) -> -0.062010468 | O49: =IF('20pdts2007'!O5=0,0,'20pdts2014'!O5/'20pdts2007'!O5-1) -> 0.42837974 | P49: =IF('20pdts2007'!P5=0,0,'20pdts2014'!P5/'20pdts2007'!P5-1) -> -0.029713586 | Q49: =IF('20pdts2007'!Q5=0,0,'20pdts2014'!Q5/'20pdts2007'!Q5-1) -> 0.58398023
J50: D02 | K50: =IF('20pdts2007'!K6=0,0,'20pdts2014'!K6/'20pdts2007'!K6-1) -> 0.24008579 | L50: =IF('20pdts2007'!L6=0,0,'20pdts2014'!L6/'20pdts2007'!L6-1) -> 0.14919972 | M50: =IF('20pdts2007'!M6=0,0,'20pdts2014'!M6/'20pdts2007'!M6-1) -> 0.078962684 | N50: =IF('20pdts2007'!N6=0,0,'20pdts2014'!N6/'20pdts2007'!N6-1) -> -0.04961214 | O50: =IF('20pdts2007'!O6=0,0,'20pdts2014'!O6/'20pdts2007'!O6-1) -> -0.026302603 | P50: =IF('20pdts2007'!P6=0,0,'20pdts2014'!P6/'20pdts2007'!P6-1) -> -0.084669928 | Q50: =IF('20pdts2007'!Q6=0,0,'20pdts2014'!Q6/'20pdts2007'!Q6-1) -> 0.57143259
J51: D03 | K51: =IF('20pdts2007'!K7=0,0,'20pdts2014'!K7/'20pdts2007'!K7-1) -> 0.42683219 | L51: =IF('20pdts2007'!L7=0,0,'20pdts2014'!L7/'20pdts2007'!L7-1) -> 0.25761823 | M51: =IF('20pdts2007'!M7=0,0,'20pdts2014'!M7/'20pdts2007'!M7-1) -> 0.060587284 | N51: =IF('20pdts2007'!N7=0,0,'20pdts2014'!N7/'20pdts2007'!N7-1) -> 0.39276561 | O51: =IF('20pdts2007'!O7=0,0,'20pdts2014'!O7/'20pdts2007'!O7-1) -> -0.039456809 | P51: =IF('20pdts2007'!P7=0,0,'20pdts2014'!P7/'20pdts2007'!P7-1) -> 0.081148634 | Q51: =IF('20pdts2007'!Q7=0,0,'20pdts2014'!Q7/'20pdts2007'!Q7-1) -> 0.62489812
J52: D04 | K52: =IF('20pdts2007'!K8=0,0,'20pdts2014'!K8/'20pdts2007'!K8-1) -> -0.0064075238 | L52: =IF('20pdts2007'!L8=0,0,'20pdts2014'!L8/'20pdts2007'!L8-1) -> 0.031202403 | M52: =IF('20pdts2007'!M8=0,0,'20pdts2014'!M8/'20pdts2007'!M8-1) -> -0.14143991 | N52: =IF('20pdts2007'!N8=0,0,'20pdts2014'!N8/'20pdts2007'!N8-1) -> 0.4737624 | O52: =IF('20pdts2007'!O8=0,0,'20pdts2014'!O8/'20pdts2007'!O8-1) -> -0.15015767 | P52: =IF('20pdts2007'!P8=0,0,'20pdts2014'!P8/'20pdts2007'!P8-1) -> 0.26599353 | Q52: =IF('20pdts2007'!Q8=0,0,'20pdts2014'!Q8/'20pdts2007'!Q8-1) -> -0.090349159
J53: D05 | K53: =IF('20pdts2007'!K9=0,0,'20pdts2014'!K9/'20pdts2007'!K9-1) -> 0.04990456 | L53: =IF('20pdts2007'!L9=0,0,'20pdts2014'!L9/'20pdts2007'!L9-1) -> 0.36513256 | M53: =IF('20pdts2007'!M9=0,0,'20pdts2014'!M9/'20pdts2007'!M9-1) -> 0.33852931 | N53: =IF('20pdts2007'!N9=0,0,'20pdts2014'!N9/'20pdts2007'!N9-1) -> -0.18393421 | O53: =IF('20pdts2007'!O9=0,0,'20pdts2014'!O9/'20pdts2007'!O9-1) -> -0.19358807 | P53: =IF('20pdts2007'!P9=0,0,'20pdts2014'!P9/'20pdts2007'!P9-1) -> -0.009651614 | Q53: =IF('20pdts2007'!Q9=0,0,'20pdts2014'!Q9/'20pdts2007'!Q9-1) -> -0.00032921886
J54: D23 | K54: =IF('20pdts2007'!K10=0,0,'20pdts2014'!K10/'20pdts2007'!K10-1) -> -0.35078436 | L54: =IF('20pdts2007'!L10=0,0,'20pdts2014'!L10/'20pdts2007'!L10-1) -> -0.10775673 | M54: =IF('20pdts2007'!M10=0,0,'20pdts2014'!M10/'20pdts2007'!M10-1) -> 0.063510865 | N54: =IF('20pdts2007'!N10=0,0,'20pdts2014'!N10/'20pdts2007'!N10-1) -> 0.46791319 | O54: =IF('20pdts2007'!O10=0,0,'20pdts2014'!O10/'20pdts2007'!O10-1) -> 0.99227362 | P54: =IF('20pdts2007'!P10=0,0,'20pdts2014'!P10/'20pdts2007'!P10-1) -> 0.56302661 | Q54: =IF('20pdts2007'!Q10=0,0,'20pdts2014'!Q10/'20pdts2007'!Q10-1) -> -0.46753546
J55: E00 | K55: =IF('20pdts2007'!K11=0,0,'20pdts2014'!K11/'20pdts2007'!K11-1) -> -0.12019315 | L55: =IF('20pdts2007'!L11=0,0,'20pdts2014'!L11/'20pdts2007'!L11-1) -> -0.19887989 | M55: =IF('20pdts2007'!M11=0,0,'20pdts2014'!M11/'20pdts2007'!M11-1) -> -0.20293069 | N55: =IF('20pdts2007'!N11=0,0,'20pdts2014'!N11/'20pdts2007'!N11-1) -> -0.13464995 | O55: =IF('20pdts2007'!O11=0,0,'20pdts2014'!O11/'20pdts2007'!O11-1) -> 0.28595184 | P55: =IF('20pdts2007'!P11=0,0,'20pdts2014'!P11/'20pdts2007'!P11-1) -> -0.15615384 | Q55: =IF('20pdts2007'!Q11=0,0,'20pdts2014'!Q11/'20pdts2007'!Q11-1) -> 0.14457528
J56: F45 | K56: =IF('20pdts2007'!K12=0,0,'20pdts2014'!K12/'20pdts2007'!K12-1) -> -0.013263035 | L56: =IF('20pdts2007'!L12=0,0,'20pdts2014'!L12/'20pdts2007'!L12-1) -> 0.47469518 | M56: =IF('20pdts2007'!M12=0,0,'20pdts2014'!M12/'20pdts2007'!M12-1) -> 0.15456347 | N56: =IF('20pdts2007'!N12=0,0,'20pdts2014'!N12/'20pdts2007'!N12-1) -> -0.12376791 | O56: =IF('20pdts2007'!O12=0,0,'20pdts2014'!O12/'20pdts2007'!O12-1) -> 0.50803752 | P56: =IF('20pdts2007'!P12=0,0,'20pdts2014'!P12/'20pdts2007'!P12-1) -> 1.3820572 | Q56: =IF('20pdts2007'!Q12=0,0,'20pdts2014'!Q12/'20pdts2007'!Q12-1) -> -0.010325657
J57: G00 | K57: =IF('20pdts2007'!K13=0,0,'20pdts2014'!K13/'20pdts2007'!K13-1) -> -0.42672024 | L57: =IF('20pdts2007'!L13=0,0,'20pdts2014'!L13/'20pdts2007'!L13-1) -> -0.15805904 | M57: =IF('20pdts2007'!M13=0,0,'20pdts2014'!M13/'20pdts2007'!M13-1) -> 0.71895498 | N57: =IF('20pdts2007'!N13=0,0,'20pdts2014'!N13/'20pdts2007'!N13-1) -> 0.22795006 | O57: =IF('20pdts2007'!O13=0,0,'20pdts2014'!O13/'20pdts2007'!O13-1) -> 1.2706796 | P57: =IF('20pdts2007'!P13=0,0,'20pdts2014'!P13/'20pdts2007'!P13-1) -> 0.33182774 | Q57: =IF('20pdts2007'!Q13=0,0,'20pdts2014'!Q13/'20pdts2007'!Q13-1) -> -0.56886596
... J65: OP0 | K65: =IF('20pdts2007'!K21=0,0,'20pdts2014'!K21/'20pdts2007'!K21-1) -> 0.29530529 | L65: =IF('20pdts2007'!L21=0,0,'20pdts2014'!L21/'20pdts2007'!L21-1) -> 0.15550915 | M65: =IF('20pdts2007'!M21=0,0,'20pdts2014'!M21/'20pdts2007'!M21-1) -> 0.042224563 | N65: =IF('20pdts2007'!N21=0,0,'20pdts2014'!N21/'20pdts2007'!N21-1) -> 0.2696849 | O65: =IF('20pdts2007'!O21=0,0,'20pdts2014'!O21/'20pdts2007'!O21-1) -> -0.4295384 | P65: =IF('20pdts2007'!P21=0,0,'20pdts2014'!P21/'20pdts2007'!P21-1) -> -0.13514536 | Q65: =IF('20pdts2007'!Q21=0,0,'20pdts2014'!Q21/'20pdts2007'!Q21-1) -> 0.21802334

Sheet 60pdts2007
A1: beta-07 | B1: M1 | C1: M2 | D1: Q1 | E1: Q2 | F1: Q3 | G1: Q4 | H1: Q5 | J1: Elasticité-revenu 2007 | K1: M1 | L1: M2 | M1: Q1 | N1: Q2 | O1: Q3 | P1: Q4 | Q1: Q5 | S1: Elasticité-Prix 2007 | T1: M1 | U1: M2 | V1: Q1 | W1: Q2 | X1: Q3 | Y1: Q4 | Z1: Q5 | AB1: CB | AC1: M1 | AD1: M2 | AE1: Q1 | AF1: Q2 | AG1: Q3 | AH1: Q4 | AI1: Q5 | AJ1: CB-2007
A2: G01 | B2: 0.0187501 | C2: 0.0450117 | D2: 0.0989937 | E2: 0.0884269 | F2: 0.0734788 | G2: 0.054636 | H2: 0.0155113 | J2: G01 | K2: =IF(AC2=0,0,B2/AC2) -> 0.29891619 | L2: =IF(AD2=0,0,C2/AD2) -> 0.45614943 | M2: =IF(AE2=0,0,D2/AE2) -> 0.80344403 | N2: =IF(AF2=0,0,E2/AF2) -> 0.81076652 | O2: =IF(AG2=0,0,F2/AG2) -> 0.77423129 | P2: =IF(AH2=0,0,G2/AH2) -> 0.66247003 | Q2: =IF(AI2=0,0,H2/AI2) -> 0.32521352 | S2: G01 | T2: =IF(T52=0,0,((1-B2)*(K52/T52))-1) -> 0.034785149 | U2: =IF(U52=0,0,((1-C2)*(L52/U52))-1) -> -0.40851501 | V2: =IF(V52=0,0,((1-D2)*(M52/V52))-1) -> -0.84206145 | W2: =IF(W52=0,0,((1-E2)*(N52/W52))-1) -> -0.83376801 | X2: =IF(X52=0,0,((1-F2)*(O52/X52))-1) -> -0.80038434 | Y2: =IF(Y52=0,0,((1-G2)*(P52/Y52))-1) -> -0.65149517 | Z2: =IF(Z52=0,0,((1-H2)*(Q52/Z52))-1) -> 0.22125846 | AB2: G01 | AC2: 0.062726948 | AD2: 0.098677533 | AE2: 0.12321169 | AF2: 0.1090658 | AG2: 0.09490549 | AH2: 0.082473165 | AI2: 0.047695741 | AJ2: G01
A3: G02 | B3: 0.0206129 | C3: 0.0218548 | D3: 0.0292642 | E3: 0.0355814 | F3: 0.0289323 | G3: 0.0282661 | H3: 0.0168328 | J3: G02 | K3: =IF(AC3=0,0,B3/AC3) -> 0.59546444 | L3: =IF(AD3=0,0,C3/AD3) -> 0.80568398 | M3: =IF(AE3=0,0,D3/AE3) -> 1.0235349 | N3: =IF(AF3=0,0,E3/AF3) -> 1.1137533 | O3: =IF(AG3=0,0,F3/AG3) -> 0.84743054 | P3: =IF(AH3=0,0,G3/AH3) -> 0.80169306 | Q3: =IF(AI3=0,0,H3/AI3) -> 0.5405861 | S3: G02 | T3: =IF(T53=0,0,((1-B3)*(K53/T53))-1) -> 0.02350758 | U3: =IF(U53=0,0,((1-C3)*(L53/U53))-1) -> -0.54123327 | V3: =IF(V53=0,0,((1-D3)*(M53/V53))-1) -> -1.1117996 | W3: =IF(W53=0,0,((1-E3)*(N53/W53))-1) -> -1.1323451 | X3: =IF(X53=0,0,((1-F3)*(O53/X53))-1) -> -0.87971109 | Y3: =IF(Y53=0,0,((1-G3)*(P53/Y53))-1) -> -0.73656943 | Z3: =IF(Z53=0,0,((1-H3)*(Q53/Z53))-1) -> 0.30362711 | AB3: G02 | AC3: 0.034616509 | AD3: 0.027125772 | AE3: 0.028591305 | AF3: 0.031947289 | AG3: 0.034141205 | AH3: 0.035258008 | AI3: 0.031138056 | AJ3: G02
A4: G03 | B4: 0.0093069 | C4: 0.0324212 | D4: 0.0524832 | E4: 0.0519227 | F4: 0.0414569 | G4: 0.0338878 | H4: 0.0065255 | J4: G03 | K4: =IF(AC4=0,0,B4/AC4) -> 0.31269045 | L4: =IF(AD4=0,0,C4/AD4) -> 0.60997196 | M4: =IF(AE4=0,0,D4/AE4) -> 0.95972233 | N4: =IF(AF4=0,0,E4/AF4) -> 0.99678347 | O4: =IF(AG4=0,0,F4/AG4) -> 0.87863885 | P4: =IF(AH4=0,0,G4/AH4) -> 0.80661268 | Q4: =IF(AI4=0,0,H4/AI4) -> 0.25849365 | S4: G03 | T4: =IF(T54=0,0,((1-B4)*(K54/T54))-1) -> 0.41891883 | U4: =IF(U54=0,0,((1-C4)*(L54/U54))-1) -> -0.48697093 | V4: =IF(V54=0,0,((1-D4)*(M54/V54))-1) -> -1.0072317 | W4: =IF(W54=0,0,((1-E4)*(N54/W54))-1) -> -1.0106001 | X4: =IF(X54=0,0,((1-F4)*(O54/X54))-1) -> -0.90357254 | Y4: =IF(Y54=0,0,((1-G4)*(P54/Y54))-1) -> -0.75415213 | Z4: =IF(Z54=0,0,((1-H4)*(Q54/Z54))-1) -> 0.79853211 | AB4: G03 | AC4: 0.029763941 | AD4: 0.053151952 | AE4: 0.054685817 | AF4: 0.05209025 | AG4: 0.047183094 | AH4: 0.042012481 | AI4: 0.025244333 | AJ4: G03
A5: G04 | B5: 0.0564788 | C5: 0.1115151 | D5: 0.113481 | E5: 0.1308921 | F5: 0.1287152 | G5: 0.1138738 | H5: 0.0482654 | J5: G04 | K5: =IF(AC5=0,0,B5/AC5) -> 0.58936227 | L5: =IF(AD5=0,0,C5/AD5) -> 0.95359603 | M5: =IF(AE5=0,0,D5/AE5) -> 1.03195 | N5: =IF(AF5=0,0,E5/AF5) -> 1.147645 | O5: =IF(AG5=0,0,F5/AG5) -> 1.1527621 | P5: =IF(AH5=0,0,G5/AH5) -> 0.99849025 | Q5: =IF(AI5=0,0,H5/AI5) -> 0.53480866 | S5: G04 | T5: =IF(T55=0,0,((1-B5)*(K55/T55))-1) -> -0.39425179 | U5: =IF(U55=0,0,((1-C5)*(L55/U55))-1) -> -0.90215709 | V5: =IF(V55=0,0,((1-D5)*(M55/V55))-1) -> -1.0494462 | W5: =IF(W55=0,0,((1-E5)*(N55/W55))-1) -> -1.134034 | X5: =IF(X55=0,0,((1-F5)*(O55/X55))-1) -> -1.1407437 | Y5: =IF(Y55=0,0,((1-G5)*(P55/Y55))-1) -> -0.97872266 | Z5: =IF(Z55=0,0,((1-H5)*(Q55/Z55))-1) -> -0.2727138 | AB5: G04 | AC5: 0.095830362 | AD5: 0.11694166 | AE5: 0.10996754 | AF5: 0.11405277 | AG5: 0.11165808 | AH5: 0.11404598 | AI5: 0.090247978 | AJ5: G04
A6: G05 | B6: 0.0130662 | C6: 0.0109763 | D6: 0.0134419 | E6: 0.0095894 | F6: 0.0127218 | G6: 0.0118986 | H6: 0.0123905 | J6: G05 | K6: =IF(AC6=0,0,B6/AC6) -> 0.79672229 | L6: =IF(AD6=0,0,C6/AD6) -> 0.90588528 | M6: =IF(AE6=0,0,D6/AE6) -> 0.90924878 | N6: =IF(AF6=0,0,E6/AF6) -> 0.68396292 | O6: =IF(AG6=0,0,F6/AG6) -> 0.81859974 | P6: =IF(AH6=0,0,G6/AH6) -> 0.79912442 | Q6: =IF(AI6=0,0,H6/AI6) -> 0.80723397 | S6: G05 | T6: =IF(T56=0,0,((1-B6)*(K56/T56))-1) -> 0.53493309 | U6: =IF(U56=0,0,((1-C6)*(L56/U56))-1) -> -0.29869044 | V6: =IF(V56=0,0,((1-D6)*(M56/V56))-1) -> -1.0853139 | W6: =IF(W56=0,0,((1-E6)*(N56/W56))-1) -> -0.73997014 | X6: =IF(X56=0,0,((1-F6)*(O56/X56))-1) -> -0.88314248 | Y6: =IF(Y56=0,0,((1-G6)*(P56/Y56))-1) -> -0.63121097 | Z6: =IF(Z56=0,0,((1-H6)*(Q56/Z56))-1) -> 0.92646252 | AB6: G05 | AC6: 0.016399943 | AD6: 0.012116656 | AE6: 0.014783523 | AF6: 0.014020351 | AG6: 0.015540928 | AH6: 0.014889546 | AI6: 0.015349329 | AJ6: G05
A7: G06 | B7: 0.0099108 | C7: 0.0340422 | D7: 0.0613363 | E7: 0.0552145 | F7: 0.0480111 | G7: 0.0388069 | H7: 0.0078959 | J7: G06 | K7: =IF(AC7=0,0,B7/AC7) -> 0.29135356 | L7: =IF(AD7=0,0,C7/AD7) -> 0.66763854 | M7: =IF(AE7=0,0,D7/AE7) -> 1.0434813 | N7: =IF(AF7=0,0,E7/AF7) -> 0.97172687 | O7: =IF(AG7=0,0,F7/AG7) -> 0.95743946 | P7: =IF(AH7=0,0,G7/AH7) -> 0.87822895 | Q7: =IF(AI7=0,0,H7/AI7) -> 0.29702477 | S7: G06 | T7: =IF(T57=0,0,((1-B7)*(K57/T57))-1) -> 0.34697665 | U7: =IF(U57=0,0,((1-C7)*(L57/U57))-1) -> -0.53778923 | V7: =IF(V57=0,0,((1-D7)*(M57/V57))-1) -> -1.0826533 | W7: =IF(W57=0,0,((1-E7)*(N57/W57))-1) -> -0.98575698 | X7: =IF(X57=0,0,((1-F7)*(O57/X57))-1) -> -0.97808213 | Y7: =IF(Y57=0,0,((1-G7)*(P57/Y57))-1) -> -0.82713245 | Z7: =IF(Z57=0,0,((1-H7)*(Q57/Z57))-1) -> 0.70441026 | AB7: G06 | AC7: 0.034016403 | AD7: 0.050988968 | AE7: 0.058780448 | AF7: 0.056821008 | AG7: 0.050145312 | AH7: 0.04418768 | AI7: 0.026583305 | AJ7: G06
A8: G07 | B8: 0.003922 | C8: 0.011604 | D8: 0.0172521 | E8: 0.0196611 | F8: 0.0171507 | G8: 0.0121642 | H8: 0.0034879 | J8: G07 | K8: =IF(AC8=0,0,B8/AC8) -> 0.30043915 | L8: =IF(AD8=0,0,C8/AD8) -> 0.64974666 | M8: =IF(AE8=0,0,D8/AE8) -> 0.85168512 | N8: =IF(AF8=0,0,E8/AF8) -> 0.91655754 | O8: =IF(AG8=0,0,F8/AG8) -> 0.91605225 | P8: =IF(AH8=0,0,G8/AH8) -> 0.72899064 | Q8: =IF(AI8=0,0,H8/AI8) -> 0.35605862 | S8: G07 | T8: =IF(T58=0,0,((1-B8)*(K58/T58))-1) -> 1.3886353 | U8: =IF(U58=0,0,((1-C8)*(L58/U58))-1) -> -0.24141939 | V8: =IF(V58=0,0,((1-D8)*(M58/V58))-1) -> -0.9813548 | W8: =IF(W58=0,0,((1-E8)*(N58/W58))-1) -> -0.95247102 | X8: =IF(X58=0,0,((1-F8)*(O58/X58))-1) -> -0.968923 | Y8: =IF(Y58=0,0,((1-G8)*(P58/Y58))-1) -> -0.58036338 | Z8: =IF(Z58=0,0,((1-H8)*(Q58/Z58))-1) -> 2.3865239 | AB8: G07 | AC8: 0.013054224 | AD8: 0.017859269 | AE8: 0.02025643 | AF8: 0.021451026 | AG8: 0.018722404 | AH8: 0.01668636 | AI8: 0.0097958589 | AJ8: G07
A9: G08 | B9: 0.018127 | C9: 0.0353989 | D9: 0.028647 | E9: 0.0380489 | F9: 0.0323319 | G9: 0.0325771 | H9: 0.0155415 | J9: G08 | K9: =IF(AC9=0,0,B9/AC9) -> 0.75371663 | L9: =IF(AD9=0,0,C9/AD9) -> 1.1722626 | M9: =IF(AE9=0,0,D9/AE9) -> 1.4667909 | N9: =IF(AF9=0,0,E9/AF9) -> 1.515512 | O9: =IF(AG9=0,0,F9/AG9) -> 1.2436673 | P9: =IF(AH9=0,0,G9/AH9) -> 1.1115554 | Q9: =IF(AI9=0,0,H9/AI9) -> 0.60912714 | S9: G08 | T9: =IF(T59=0,0,((1-B9)*(K59/T59))-1) -> 0.14703017 | U9: =IF(U59=0,0,((1-C9)*(L59/U59))-1) -> -0.92813828 | V9: =IF(V59=0,0,((1-D9)*(M59/V59))-1) -> -1.5837274 | W9: =IF(W59=0,0,((1-E9)*(N59/W59))-1) -> -1.5246309 | X9: =IF(X59=0,0,((1-F9)*(O59/X59))-1) -> -1.2722533 | Y9: =IF(Y59=0,0,((1-G9)*(P59/Y59))-1) -> -1.023211 | Z9: =IF(Z59=0,0,((1-H9)*(Q59/Z59))-1) -> 0.42588639 | AB9: G08 | AC9: 0.024050153 | AD9: 0.030197072 | AE9: 0.019530391 | AF9: 0.025106301 | AG9: 0.025997227 | AH9: 0.02930767 | AI9: 0.025514378 | AJ9: G08
A10: G09 | B10: 0.0050681 | C10: 0.0120172 | D10: 0.0294931 | E10: 0.0237853 | F10: 0.0140136 | G10: 0.013014 | H10: 0.0050898 | J10: G09 | K10: =IF(AC10=0,0,B10/AC10) -> 0.40796649 | L10: =IF(AD10=0,0,C10/AD10) -> 0.44341527 | M10: =IF(AE10=0,0,D10/AE10) -> 0.86699336 | N10: =IF(AF10=0,0,E10/AF10) -> 0.88231311 | O10: =IF(AG10=0,0,F10/AG10) -> 0.63321431 | P10: =IF(AH10=0,0,G10/AH10) -> 0.73034553 | Q10: =IF(AI10=0,0,H10/AI10) -> 0.50918648 | S10: G09 | T10: =IF(T60=0,0,((1-B10)*(K60/T60))-1) -> 1.3647913 | U10: =IF(U60=0,0,((1-C10)*(L60/U60))-1) -> -0.17846266 | V10: =IF(V60=0,0,((1-D10)*(M60/V60))-1) -> -0.94566499 | W10: =IF(W60=0,0,((1-E10)*(N60/W60))-1) -> -0.91226993 | X10: =IF(X60=0,0,((1-F10)*(O60/X60))-1) -> -0.6820038 | Y10: =IF(Y60=0,0,((1-G10)*(P60/Y60))-1) -> -0.59170928 | Z10: =IF(Z60=0,0,((1-H10)*(Q60/Z60))-1) -> 2.1738799 | AB10: G09 | AC10: 0.012422834 | AD10: 0.027101457 | AE10: 0.034017677 | AF10: 0.02695789 | AG10: 0.022130896 | AH10: 0.017818963 | AI10: 0.0099959449 | AJ10: G09
A11: G10 | B11: 0.0007615 | C11: 0.000136 | D11: 0.0002725 | E11: 0.000163 | F11: 0.0003405 | G11: 0.0002334 | H11: 0.0007457 | J11: G10 | K11: =IF(AC11=0,0,B11/AC11) -> 1.6492917 | L11: =IF(AD11=0,0,C11/AD11) -> 0.94757217 | M11: =IF(AE11=0,0,D11/AE11) -> 3.0435244 | N11: =IF(AF11=0,0,E11/AF11) -> 0.98947822 | O11: =IF(AG11=0,0,F11/AG11) -> 1.5380999 | P11: =IF(AH11=0,0,G11/AH11) -> 0.86530395 | Q11: =IF(AI11=0,0,H11/AI11) -> 1.3847732 | S11: G10 | T11: =IF(T61=0,0,((1-B11)*(K61/T61))-1) -> 46.336445 | U11: =IF(U61=0,0,((1-C11)*(L61/U61))-1) -> 50.963266 | V11: =IF(V61=0,0,((1-D11)*(M61/V61))-1) -> -32.298107 | W11: =IF(W61=0,0,((1-E11)*(N61/W61))-1) -> -5.5408237 | X11: =IF(X61=0,0,((1-F11)*(O61/X61))-1) -> -5.9620374 | Y11: =IF(Y61=0,0,((1-G11)*(P61/Y61))-1) -> 8.6465939 | Z11: =IF(Z61=0,0,((1-H11)*(Q61/Z61))-1) -> 48.684165 | AB11: G10 | AC11: 0.00046171336 | AD11: 0.00014352469 | AE11: 8.9534358e-05 | AF11: 0.00016473329 | AG11: 0.00022137704 | AH11: 0.00026973181 | AI11: 0.00053849973 | AJ11: G10
A12: G11 | B12: 0.0033931 | C12: 0.0111897 | D12: 0.022242 | E12: 0.0193331 | F12: 0.0128523 | G12: 0.0119997 | H12: 0.0025898 | J12: G11 | K12: =IF(AC12=0,0,B12/AC12) -> 0.28828687 | L12: =IF(AD12=0,0,C12/AD12) -> 0.49642423 | M12: =IF(AE12=0,0,D12/AE12) -> 0.85594296 | N12: =IF(AF12=0,0,E12/AF12) -> 0.86300563 | O12: =IF(AG12=0,0,F12/AG12) -> 0.67596322 | P12: =IF(AH12=0,0,G12/AH12) -> 0.70618906 | Q12: =IF(AI12=0,0,H12/AI12) -> 0.26856503 | S12: G11 | T12: =IF(T62=0,0,((1-B12)*(K62/T62))-1) -> 1.5867304 | U12: =IF(U62=0,0,((1-C12)*(L62/U62))-1) -> -0.17517982 | V12: =IF(V62=0,0,((1-D12)*(M62/V62))-1) -> -0.95772975 | W12: =IF(W62=0,0,((1-E12)*(N62/W62))-1) -> -0.89848435 | X12: =IF(X62=0,0,((1-F12)*(O62/X62))-1) -> -0.73099271 | Y12: =IF(Y62=0,0,((1-G12)*(P62/Y62))-1) -> -0.56050034 | Z12: =IF(Z62=0,0,((1-H12)*(Q62/Z62))-1) -> 2.520365 | AB12: G11 | AC12: 0.011769873 | AD12: 0.0225406 | AE12: 0.025985376 | AF12: 0.022402055 | AG12: 0.019013313 | AH12: 0.016992192 | AI12: 0.0096431021 | AJ12: G11
A13: G12 | B13: 0.0028999 | C13: 0.0081623 | D13: 0.0158173 | E13: 0.0166396 | F13: 0.0108618 | G13: 0.0077995 | H13: 0.0024197 | J13: G12 | K13: =IF(AC13=0,0,B13/AC13) -> 0.35487166 | L13: =IF(AD13=0,0,C13/AD13) -> 0.53339468 | M13: =IF(AE13=0,0,D13/AE13) -> 0.89405974 | N13: =IF(AF13=0,0,E13/AF13) -> 1.1195783 | O13: =IF(AG13=0,0,F13/AG13) -> 0.82939494 | P13: =IF(AH13=0,0,G13/AH13) -> 0.66785942 | Q13: =IF(AI13=0,0,H13/AI13) -> 0.35760701 | S13: G12 | T13: =IF(T63=0,0,((1-B13)*(K63/T63))-1) -> 2.3487078 | U13: =IF(U63=0,0,((1-C13)*(L63/U63))-1) -> -0.054237699 | V13: =IF(V63=0,0,((1-D13)*(M63/V63))-1) -> -1.0414845 | W13: =IF(W63=0,0,((1-E13)*(N63/W63))-1) -> -1.1672071 | X13: =IF(X63=0,0,((1-F13)*(O63/X63))-1) -> -0.90524481 | Y13: =IF(Y63=0,0,((1-G13)*(P63/Y63))-1) -> -0.45241602 | Z13: =IF(Z63=0,0,((1-H13)*(Q63/Z63))-1) -> 3.6188627 | AB13: G12 | AC13: 0.0081716866 | AD13: 0.015302552 | AE13: 0.017691547 | AF13: 0.014862382 | AG13: 0.013096053 | AH13: 0.011678356 | AI13: 0.0067663662 | AJ13: G12
... A49: G76 | B49: 0.0499702 | C49: 0.0113828 | D49: 0.020195 | E49: 0.0213084 | F49: 0.0256024 | G49: 0.0264869 | H49: 0.0520874 | J49: G76 | K49: =IF(AC49=0,0,B49/AC49) -> 1.5290113 | L49: =IF(AD49=0,0,C49/AD49) -> 0.92870646 | M49: =IF(AE49=0,0,D49/AE49) -> 0.92889775 | N49: =IF(AF49=0,0,E49/AF49) -> 1.063885 | O49: =IF(AG49=0,0,F49/AG49) -> 1.1742778 | P49: =IF(AH49=0,0,G49/AH49) -> 1.3184659 | Q49: =IF(AI49=0,0,H49/AI49) -> 1.5813436 | S49: G76 | T49: =IF(T99=0,0,((1-B49)*(K99/T99))-1) -> -0.85803831 | U49: =IF(U99=0,0,((1-C49)*(L99/U99))-1) -> -0.32848301 | V49: =IF(V99=0,0,((1-D49)*(M99/V99))-1) -> -1.0484127 | W49: =IF(W99=0,0,((1-E49)*(N99/W99))-1) -> -1.0991697 | X49: =IF(X99=0,0,((1-F49)*(O99/X99))-1) -> -1.2136001 | Y49: =IF(Y99=0,0,((1-G49)*(P99/Y99))-1) -> -1.1856692 | Z49: =IF(Z99=0,0,((1-H49)*(Q99/Z99))-1) -> -0.77456884 | AB49: G76 | AC49: 0.03268138 | AD49: 0.012256618 | AE49: 0.021740821 | AF49: 0.020028856 | AG49: 0.021802677 | AH49: 0.020089182 | AI49: 0.032938698 | AJ49: G76
AB50: G81 | AC50: 0.0014336681 | AD50: 0.0010965798 | AE50: 0.00015416122 | AF50: 0.00034057245 | AG50: 0.0002577031 | AH50: 0.00075045919 | AI50: 0.002323807 | AJ50: G81
A51: alpha-07 | B51: M1 | C51: M2 | D51: Q1 | E51: Q2 | F51: Q3 | G51: Q4 | H51: Q5 | J51: CMIN | K51: M1 | L51: M2 | M51: Q1 | N51: Q2 | O51: Q3 | P51: Q4 | Q51: Q5 | S51: Cmoyen | T51: M1 | U51: M2 | V51: Q1 | W51: Q2 | X51: Q3 | Y51: Q4 | Z51: Q5 | AB51: G82 | AC51: 9.9706907e-05 | AD51: 3.6940122e-05 | AE51: 6.5290075e-05 | AF51: 2.0746227e-05 | AG51: 4.5520205e-05 | AH51: 2.6296905e-05 | AI51: 0.00013158971 | AJ51: G82
A52: G01 | B52: 2885.613 | C52: 2338.163 | D52: 587.9116 | E52: 725.1099 | F52: 936.6098 | G52: 1528.812 | H52: 3314.734 | J52: G01 | K52: 4340.487 | L52: 2662.8149 | M52: 524.3086 | N52: 698.76257 | O52: 893.78544 | P52: 1669.7508 | Q52: 6093.6653 | S52: G01 | T52: =Cmoyen!J3 -> 4115.9292 | U52: =Cmoyen!K3 -> 4299.2758 | V52: =Cmoyen!Q26 -> 2991.0707 | W52: =Cmoyen!R26 -> 3831.8327 | X52: =Cmoyen!S26 -> 4148.5281 | Y52: =Cmoyen!T26 -> 4529.4128 | Z52: =Cmoyen!U26 -> 4912.2646 | AB52: G83 | AC52: 0.00034034315 | AD52: 0.00017443126 | AE52: 1.3153813e-05 | AF52: 0.00016301588 | AG52: 8.7002328e-05 | AH52: 0.00017821566 | AI52: 0.00047237116 | AJ52: G83
A53: G02 | B53: 918.869 | C53: 229.6517 | D53: -16.33402 | E53: -127.6788 | F53: 227.6906 | G53: 383.9966 | H53: 1473.327 | J53: G02 | K53: 2373.743 | L53: 554.30361 | M53: -79.937018 | N53: -154.02613 | O53: 184.86624 | P53: 524.93537 | Q53: 4252.2583 | S53: G02 | T53: =Cmoyen!J4 -> 2271.4177 | U53: =Cmoyen!K4 -> 1181.8412 | V53: =Cmoyen!Q27 -> 694.07871 | W53: =Cmoyen!R27 -> 1122.4111 | X53: =Cmoyen!S27 -> 1492.3873 | Y53: =Cmoyen!T27 -> 1936.3641 | Z53: =Cmoyen!U27 -> 3206.9607 | AB53: G84 | AC53: 0.00010663388 | AD53: 0.00018122824 | AE53: 0.00014067579 | AF53: 0.00012612607 | AG53: 0.0001508274 | AH53: 0.00010369154 | AI53: 0.00013261734 | AJ53: G84
A54: G03 | B54: 1342.32 | C54: 903.2166 | D54: 53.47076 | E54: 5.885601 | F54: 250.3053 | G54: 446.2077 | H54: 1927.888 | J54: G03 | K54: 2797.194 | L54: 1227.8685 | M54: -10.132238 | N54: -20.461724 | O54: 207.48094 | P54: 587.14647 | Q54: 4706.8193 | S54: G03 | T54: =Cmoyen!J5 -> 1953.0087 | U54: =Cmoyen!K5 -> 2315.7743 | V54: =Cmoyen!Q28 -> 1327.5456 | W54: =Cmoyen!R28 -> 1830.0981 | X54: =Cmoyen!S28 -> 2062.477 | Y54: =Cmoyen!T28 -> 2307.3186 | Z54: =Cmoyen!U28 -> 2599.9564 | AB54: G85 | AC54: 0.017585505 | AD54: 0.019711668 | AE54: 0.0093725893 | AF54: 0.0092270792 | AG54: 0.011174943 | AH54: 0.016665828 | AI54: 0.024507278 | AJ54: G85
A55: G04 | B55: 2582.113 | C55: 236.4291 | D55: -85.29351 | E55: -591.6195 | F55: -745.6029 | G55: 9.455423 | H55: 4323.861 | J55: G04 | K55: 4036.987 | L55: 561.08101 | M55: -148.89651 | N55: -617.96683 | O55: -788.42726 | P55: 150.39419 | Q55: 7102.7923 | S55: G04 | T55: =Cmoyen!J6 -> 6288.0628 | U55: =Cmoyen!K6 -> 5095.0243 | V55: =Cmoyen!Q29 -> 2669.5572 | W55: =Cmoyen!R29 -> 4007.041 | X55: =Cmoyen!S29 -> 4880.8206 | Y55: =Cmoyen!T29 -> 6263.3868 | Z55: =Cmoyen!U29 -> 9294.7911 | AB55: G86 | AC55: 2.7507817e-05 | AD55: 5.0484834e-05 | AE55: 0 | AF55: 4.4652476e-05 | AG55: 4.2550045e-05 | AH55: 4.1963147e-05 | AI55: 3.1252689e-05 | AJ55: G86
A56: G05 | B56: 218.7485 | C56: 49.68516 | D56: 32.56812 | E56: 155.673 | F56: 123.2319 | G56: 164.2631 | H56: 304.7313 | J56: G05 | K56: 1673.6225 | L56: 374.33707 | M56: -31.034878 | N56: 129.32567 | O56: 80.407543 | P56: 305.20187 | Q56: 3083.6626 | S56: G05 | T56: =Cmoyen!J7 -> 1076.1085 | U56: =Cmoyen!K7 -> 527.90987 | V56: =Cmoyen!Q30 -> 358.88283 | W56: =Cmoyen!R30 -> 492.58005 | X56: =Cmoyen!S30 -> 679.32823 | Y56: =Cmoyen!T30 -> 817.73146 | Z56: =Cmoyen!U30 -> 1580.8532 | AB56: G87 | AC56: 0.021616668 | AD56: 0.009330451 | AE56: 0.0025390912 | AF56: 0.0047620606 | AG56: 0.0082873972 | AH56: 0.013480193 | AI56: 0.028104982 | AJ56: G87
A57: G06 | B57: 1581.728 | C57: 738.3527 | D57: -62.04559 | E57: 56.44243 | F57: 93.29043 | G57: 295.51 | H57: 1924.643 | J57: G06 | K57: 3036.602 | L57: 1063.0046 | M57: -125.64859 | N57: 30.095105 | O57: 50.466073 | P57: 436.44877 | Q57: 4703.5743 | S57: G06 | T57: =Cmoyen!J8 -> 2232.0408 | U57: =Cmoyen!K8 -> 2221.5354 | V57: =Cmoyen!Q31 -> 1426.9463 | W57: =Cmoyen!R31 -> 1996.3049 | X57: =Cmoyen!S31 -> 2191.9621 | Y57: =Cmoyen!T31 -> 2426.7802 | Z57: =Cmoyen!U31 -> 2737.8592 | AB57: G88 | AC57: 0.00015543346 | AD57: 4.5608738e-05 | AE57: 0 | AF57: 0 | AG57: 6.3074185e-05 | AH57: 4.7655539e-05 | AI57: 0.00021912373 | AJ57: G88
A58: G07 | B58: 599.2247 | C58: 272.5366 | D58: 72.93259 | E58: 62.88562 | F58: 68.70151 | G58: 248.3568 | H58: 649.6641 | J58: G07 | K58: 2054.0987 | L58: 597.18851 | M58: 9.3295918 | N58: 36.538295 | O58: 25.877153 | P58: 389.29557 | Q58: 3428.5954 | S58: G07 | T58: =Cmoyen!J9 -> 856.57384 | U58: =Cmoyen!K9 -> 778.10944 | V58: =Cmoyen!Q32 -> 491.7424 | W58: =Cmoyen!R32 -> 753.6436 | X58: =Cmoyen!S32 -> 818.39752 | Y58: =Cmoyen!T32 -> 916.41216 | Z58: =Cmoyen!U32 -> 1008.892 | AB58: G89 | AC58: 0.018931498 | AD58: 0.023836049 | AE58: 0.026336955 | AF58: 0.028124007 | AG58: 0.026759707 | AH58: 0.024132106 | AI58: 0.014155286 | AJ58: G89
A59: G08 | B59: 388.6598 | C59: -226.6371 | D59: -221.3142 | E59: -454.7152 | F59: -276.9005 | G59: -179.5566 | H59: 1027.12 | J59: G08 | K59: 1843.5338 | L59: 98.014813 | M59: -284.9172 | N59: -481.06253 | O59: -319.72486 | P59: -38.617833 | Q59: 3806.0513 | S59: G08 | T59: =Cmoyen!J10 -> 1578.0893 | U59: =Cmoyen!K10 -> 1315.6545 | V59: =Cmoyen!Q33 -> 474.11717 | W59: =Cmoyen!R33 -> 882.06516 | X59: =Cmoyen!S33 -> 1136.3961 | Y59: =Cmoyen!T33 -> 1609.5725 | Z59: =Cmoyen!U33 -> 2627.7687 | AB59: G91 | AC59: 0.0085392339 | AD59: 0.0024540144 | AE59: 0.0015125411 | AF59: 0.002260148 | AG59: 0.0029486681 | AH59: 0.0041902574 | AI59: 0.010743954 | AJ59: G91
A60: G09 | B60: 482.5911 | C60: 657.2036 | D60: 109.8369 | E60: 111.4625 | F60: 354.823 | G60: 263.8889 | H60: 505.2915 | J60: G09 | K60: 1937.4651 | L60: 981.85551 | M60: 46.233902 | N60: 85.115175 | O60: 311.99864 | P60: 404.82767 | Q60: 3284.2228 | S60: G09 | T60: =Cmoyen!J11 -> 815.14416 | U60: =Cmoyen!K11 -> 1180.7818 | V60: =Cmoyen!Q34 -> 825.80859 | W60: =Cmoyen!R34 -> 947.11746 | X60: =Cmoyen!S34 -> 967.39023 | Y60: =Cmoyen!T34 -> 978.61456 | Z60: =Cmoyen!U34 -> 1029.4992 | AB60: G92 | AC60: 0.016348953 | AD60: 0.013437388 | AE60: 0.0051689327 | AF60: 0.0061057566 | AG60: 0.0083344192 | AH60: 0.010390623 | AI60: 0.023586039 | AJ60: G92
A61: G10 | B61: -19.6732 | C61: 0.329963 | D61: -4.442736 | E61: 0.0625217 | F61: -5.20903 | G61: 1.99564 | H61: -21.3419 | J61: G10 | K61: 1435.2008 | L61: 324.98188 | M61: -68.045734 | N61: -26.284804 | O61: -48.033387 | P61: 142.93441 | Q61: 2757.5894 | S61: G10 | T61: =Cmoyen!J12 -> 30.296062 | U61: =Cmoyen!K12 -> 6.2532189 | V61: =Cmoyen!Q35 -> 2.1735242 | W61: =Cmoyen!R35 -> 5.7876106 | X61: =Cmoyen!S35 -> 9.6768782 | Y61: =Cmoyen!T35 -> 14.813627 | Z61: =Cmoyen!U35 -> 55.460993 | AB61: G93 | AC61: 0.0024428907 | AD61: 0.0073226651 | AE61: 0.0039060561 | AF61: 0.0037211999 | AG61: 0.0035822132 | AH61: 0.0043395976 | AI61: 0.0038979731 | AJ61: G93
A62: G11 | B62: 549.6572 | C62: 494.5459 | D62: 90.87438 | E62: 107.821 | F62: 269.3109 | G62: 274.1874 | H62: 726.4301 | J62: G11 | K62: 2004.5312 | L62: 819.19781 | M62: 27.271382 | N62: 81.473675 | O62: 226.48654 | P62: 415.12617 | Q62: 3505.3614 | S62: G11 | T62: =Cmoyen!J13 -> 772.29911 | U62: =Cmoyen!K13 -> 982.0701 | V62: =Cmoyen!Q36 -> 630.81753 | W62: =Cmoyen!R36 -> 787.05632 | X62: =Cmoyen!S36 -> 831.11379 | Y62: =Cmoyen!T36 -> 933.20842 | Z62: =Cmoyen!U36 -> 993.1593 | AB62: G94 | AC62: 0.003698769 | AD62: 0.00055811599 | AE62: 0.00082356871 | AF62: 0.0013689533 | AG62: 0.001821192 | AH62: 0.0029530622 | AI62: 0.0035452521 | AJ62: G94
A63: G12 | B63: 345.9196 | C63: 311.0921 | D63: 45.5 | E63: -62.43946 | F63: 97.66331 | G63: 213.0278 | H63: 447.6665 | J63: G12 | K63: 1800.7936 | L63: 635.74401 | M63: -18.102998 | N63: -88.786785 | O63: 54.838953 | P63: 353.96657 | Q63: 3226.5978 | S63: G12 | T63: =Cmoyen!J14 -> 536.19831 | U63: =Cmoyen!K14 -> 666.71602 | V63: =Cmoyen!Q37 -> 429.47764 | W63: =Cmoyen!R37 -> 522.16331 | X63: =Cmoyen!S37 -> 572.45733 | Y63: =Cmoyen!T37 -> 641.37341 | Z63: =Cmoyen!U37 -> 696.87943
A64: G13 | B64: -112.6771 | C64: -69.01381 | D64: -30.44011 | E64: -30.57275 | F64: 18.02133 | G64: -32.17086 | H64: -105.0211 | J64: G13 | K64: 1342.1969 | L64: 255.6381 | M64: -94.043108 | N64: -56.920075 | O64: -24.803027 | P64: 108.76791 | Q64: 2673.9102 | S64: G13 | T64: =Cmoyen!J15 -> 240.22902 | U64: =Cmoyen!K15 -> 82.301144 | V64: =Cmoyen!Q38 -> 23.640429 | W64: =Cmoyen!R38 -> 56.356396 | X64: =Cmoyen!S38 -> 84.299052 | Y64: =Cmoyen!T38 -> 149.80361 | Z64: =Cmoyen!U38 -> 446.6012
A65: G14 | B65: -6.699583 | C65: 0 | D65: 0 | E65: 0 | F65: 0 | G65: 0.0157486 | H65: -6.343379 | J65: G14 | K65: 1448.1744 | L65: 324.65191 | M65: -63.602998 | N65: -26.347325 | O65: -42.824357 | P65: 140.95452 | Q65: 2772.588 | S65: G14 | T65: =Cmoyen!J16 -> 5.2022972 | U65: =Cmoyen!K16 -> 0 | V65: =Cmoyen!Q39 -> 0 | W65: =Cmoyen!R39 -> 0 | X65: =Cmoyen!S39 -> 0 | Y65: =Cmoyen!T39 -> 0.19839679 | Z65: =Cmoyen!U39 -> 11.945445
A66: G15 | B66: -9.375196 | C66: -67.04198 | D66: -67.36474 | E66: -168.8471 | F66: -469.0312 | G66: -276.3741 | H66: 65.56363 | J66: G15 | K66: 1445.4988 | L66: 257.60993 | M66: -130.96774 | N66: -195.19443 | O66: -511.85556 | P66: -135.43533 | Q66: 2844.495 | S66: G15 | T66: =Cmoyen!J17 -> 1486.1472 | U66: =Cmoyen!K17 -> 902.00036 | V66: =Cmoyen!Q40 -> 348.28444 | W66: =Cmoyen!R40 -> 673.60418 | X66: =Cmoyen!S40 -> 1019.0226 | Y66: =Cmoyen!T40 -> 1362.0975 | Z66: =Cmoyen!U40 -> 2290.8265
A67: G17 | B67: 134.8508 | C67: 9.930388 | D67: 31.53018 | E67: 47.39019 | F67: 44.41359 | G67: -35.56989 | H67: 60.46097 | J67: G17 | K67: 1589.7248 | L67: 334.5823 | M67: -32.072818 | N67: 21.042865 | O67: 1.5892328 | P67: 105.36888 | Q67: 2839.3923 | S67: G17 | T67: =Cmoyen!J18 -> 117.49906 | U67: =Cmoyen!K18 -> 42.8201 | V67: =Cmoyen!Q41 -> 67.585868 | W67: =Cmoyen!R41 -> 116.99678 | X67: =Cmoyen!S41 -> 109.37345 | Y67: =Cmoyen!T41 -> 97.845023 | Z67: =Cmoyen!U41 -> 56.499182
A68: G18 | B68: -0.7216583 | C68: 0.3706409 | D68: 0.6614408 | E68: -4.788807 | F68: 2.760952 | G68: 0.0876726 | H68: 1.385015 | J68: G18 | K68: 1454.1523 | L68: 325.02255 | M68: -62.941557 | N68: -31.136132 | O68: -40.063405 | P68: 141.02644 | Q68: 2780.3164 | S68: G18 | T68: =Cmoyen!J19 -> 5.347398 | U68: =Cmoyen!K19 -> 3.2496423 | V68: =Cmoyen!Q42 -> 0.92307692 | W68: =Cmoyen!R42 -> 1.9372486 | X68: =Cmoyen!S42 -> 3.1531729 | Y68: =Cmoyen!T42 -> 4.1930528 | Z68: =Cmoyen!U42 -> 9.7424986
A69: G21 | B69: -200.3526 | C69: -33.51077 | D69: -90.40554 | E69: -165.5465 | F69: -51.01762 | G69: -109.8088 | H69: -44.13976 | J69: G21 | K69: 1254.5214 | L69: 291.14114 | M69: -154.00854 | N69: -191.89383 | O69: -93.841977 | P69: 31.129967 | Q69: 2734.7916 | S69: G21 | T69: =Cmoyen!J20 -> 920.94562 | U69: =Cmoyen!K20 -> 537.73391 | V69: =Cmoyen!Q43 -> 198.53488 | W69: =Cmoyen!R43 -> 362.52132 | X69: =Cmoyen!S43 -> 528.99344 | Y69: =Cmoyen!T43 -> 712.91917 | Z69: =Cmoyen!U43 -> 1618.7627
A70: G22 | B70: 80.71498 | C70: 69.69001 | D70: -20.92074 | E70: -22.82428 | F70: -33.27934 | G70: 27.04367 | H70: 3.830997 | J70: G22 | K70: 1535.589 | L70: 394.34192 | M70: -84.523738 | N70: -49.171605 | O70: -76.103697 | P70: 167.98244 | Q70: 2782.7623 | S70: G22 | T70: =Cmoyen!J21 -> 371.61908 | U70: =Cmoyen!K21 -> 275.06795 | V70: =Cmoyen!Q44 -> 172.82826 | W70: =Cmoyen!R44 -> 272.64924 | X70: =Cmoyen!S44 -> 324.88694 | Y70: =Cmoyen!T44 -> 331.33734 | Z70: =Cmoyen!U44 -> 480.55646
A71: G23 | B71: 14.34002 | C71: 5.520504 | D71: -3.128429 | E71: -7.648489 | F71: -7.195447 | G71: -0.3456514 | H71: 47.11821 | J71: G23 | K71: 1469.214 | L71: 330.17242 | M71: -66.731427 | N71: -33.995814 | O71: -50.019804 | P71: 140.59312 | Q71: 2826.0496 | S71: G23 | T71: =Cmoyen!J22 -> 41.21519 | U71: =Cmoyen!K22 -> 33.791845 | V71: =Cmoyen!Q45 -> 13.427549 | W71: =Cmoyen!R45 -> 22.208367 | X71: =Cmoyen!S45 -> 29.119621 | Y71: =Cmoyen!T45 -> 35.60187 | Z71: =Cmoyen!U45 -> 73.360611
A72: G24 | B72: 51.08326 | C72: -5.302085 | D72: -2.971127 | E72: 0.02791 | F72: -23.08839 | G72: -28.056 | H72: 109.2699 | J72: G24 | K72: 1505.9572 | L72: 319.34983 | M72: -66.574125 | N72: -26.319415 | O72: -65.912747 | P72: 112.88277 | Q72: 2888.2012 | S72: G24 | T72: =Cmoyen!J23 -> 177.49672 | U72: =Cmoyen!K23 -> 138.60193 | V72: =Cmoyen!Q46 -> 56.840787 | W72: =Cmoyen!R46 -> 99.475463 | X72: =Cmoyen!S46 -> 132.07367 | Y72: =Cmoyen!T46 -> 178.29259 | Z72: =Cmoyen!U46 -> 277.99182
A73: G25 | B73: -160.5285 | C73: -11.44525 | D73: -9.159247 | E73: 1.797376 | F73: -50.27123 | G73: -2.428149 | H73: -285.7761 | J73: G25 | K73: 1294.3455 | L73: 313.20666 | M73: -72.762245 | N73: -24.549949 | O73: -93.095587 | P73: 138.51062 | Q73: 2493.1552 | S73: G25 | T73: =Cmoyen!J24 -> 73.440225 | U73: =Cmoyen!K24 -> 38.733548 | V73: =Cmoyen!Q47 -> 14.229875 | W73: =Cmoyen!R47 -> 27.497184 | X73: =Cmoyen!S47 -> 34.840992 | Y73: =Cmoyen!T47 -> 44.167669 | Z73: =Cmoyen!U47 -> 140.5461
A74: G26 | B74: 38.09565 | C74: 12.30695 | D74: -8.923052 | E74: -6.611664 | F74: -20.51538 | G74: 28.4139 | H74: 36.03427 | J74: G26 | K74: 1492.9696 | L74: 336.95886 | M74: -72.52605 | N74: -32.958989 | O74: -63.339737 | P74: 169.35267 | Q74: 2814.9656 | S74: G26 | T74: =Cmoyen!J25 -> 75.590483 | U74: =Cmoyen!K25 -> 39.562947 | V74: =Cmoyen!Q48 -> 24.052773 | W74: =Cmoyen!R48 -> 34.401448 | X74: =Cmoyen!S48 -> 49.374179 | Y74: =Cmoyen!T48 -> 92.644623 | Z74: =Cmoyen!U48 -> 85.681397
... A99: G76 | B99: -1134.433 | C99: 38.07226 | D99: 37.52521 | E99: -44.95561 | F99: -166.0946 | G99: -351.36 | H99: -1972.153 | J99: G76 | K99: 320.44098 | L99: 362.72417 | M99: -26.077788 | N99: -71.302935 | O99: -208.91896 | P99: -210.42123 | Q99: 806.77834 | S99: G76 | T99: =Cmoyen!J50 -> 2144.4412 | U99: =Cmoyen!K50 -> 534.00787 | V99: =Cmoyen!Q73 -> 527.77728 | W99: =Cmoyen!R73 -> 703.6782 | X99: =Cmoyen!S73 -> 953.04303 | Y99: =Cmoyen!T73 -> 1103.2946 | Z99: =Cmoyen!U73 -> 3392.4119

Sheet 60pdts2014
A1: beta-14 | B1: M1 | C1: M2 | D1: Q1 | E1: Q2 | F1: Q3 | G1: Q4 | H1: Q5 | J1: Elasticité-revenu 2014 | K1: M1 | L1: M2 | M1: Q1 | N1: Q2 | O1: Q3 | P1: Q4 | Q1: Q5 | S1: Elasticité-Prix 2014 | T1: M1 | U1: M2 | V1: Q1 | W1: Q2 | X1: Q3 | Y1: Q4 | Z1: Q5 | AB1: CB | AC1: M1 | AD1: M2 | AE1: Q1-60-14 | AF1: Q2-60-14 | AG1: Q3-60-14 | AH1: Q4-60-14 | AI1: Q5-60-14 | AJ1: CB-2014
A2: G01 | B2: 0.0195875 | C2: 0.0367566 | D2: 0.0740258 | E2: 0.0620019 | F2: 0.0554708 | G2: 0.0419979 | H2: 0.01785 | J2: G01 | K2: =IF(AC2=0,0,B2/AC2) -> 0.36530713 | L2: =IF(AD2=0,0,C2/AD2) -> 0.48847987 | M2: =IF(AE2=0,0,D2/AE2) -> 0.7982111 | N2: =IF(AF2=0,0,E2/AF2) -> 0.74147677 | O2: =IF(AG2=0,0,F2/AG2) -> 0.74050471 | P2: =IF(AH2=0,0,G2/AH2) -> 0.63879992 | Q2: =IF(AI2=0,0,H2/AI2) -> 0.43448746 | S2: G01 | T2: =IF(T67=0,0,((1-B2)*(K67/T67))-1) -> -0.28246696 | U2: =IF(U67=0,0,((1-C2)*(L67/U67))-1) -> -0.45785425 | V2: =IF(V67=0,0,((1-D2)*(M67/V67))-1) -> -0.82939247 | W2: =IF(W67=0,0,((1-E2)*(N67/W67))-1) -> -0.76121982 | X2: =IF(X67=0,0,((1-F2)*(O67/X67))-1) -> -0.7683554 | Y2: =IF(Y67=0,0,((1-G2)*(P67/Y67))-1) -> -0.64089235 | Z2: =IF(Z67=0,0,((1-H2)*(Q67/Z67))-1) -> -0.30330951 | AB2: G01 | AC2: 0.053619265 | AD2: 0.075246909 | AE2: 0.092739628 | AF2: 0.083619478 | AG2: 0.074909449 | AH2: 0.065744999 | AI2: 0.041082889 | AJ2: DAM_G01
A3: G02 | B3: 0.0180563 | C3: 0.0205408 | D3: 0.0309675 | E3: 0.02887 | F3: 0.0288493 | G3: 0.0270277 | H3: 0.0147922 | J3: G02 | K3: =IF(AC3=0,0,B3/AC3) -> 0.55947195 | L3: =IF(AD3=0,0,C3/AD3) -> 0.70687058 | M3: =IF(AE3=0,0,D3/AE3) -> 1.013076 | N3: =IF(AF3=0,0,E3/AF3) -> 0.83554143 | O3: =IF(AG3=0,0,F3/AG3) -> 0.81277269 | P3: =IF(AH3=0,0,G3/AH3) -> 0.78206128 | Q3: =IF(AI3=0,0,H3/AI3) -> 0.52475543 | S3: G02 | T3: =IF(T68=0,0,((1-B3)*(K68/T68))-1) -> -0.40889506 | U3: =IF(U68=0,0,((1-C3)*(L68/U68))-1) -> -0.58274719 | V3: =IF(V68=0,0,((1-D3)*(M68/V68))-1) -> -1.0642448 | W3: =IF(W68=0,0,((1-E3)*(N68/W68))-1) -> -0.849597 | X3: =IF(X68=0,0,((1-F3)*(O68/X68))-1) -> -0.84737177 | Y3: =IF(Y68=0,0,((1-G3)*(P68/Y68))-1) -> -0.76268423 | Z3: =IF(Z68=0,0,((1-H3)*(Q68/Z68))-1) -> -0.32525271 | AB3: G02 | AC3: 0.032273826 | AD3: 0.029058785 | AE3: 0.030567796 | AF3: 0.034552446 | AG3: 0.035494918 | AH3: 0.034559568 | AI3: 0.028188751 | AJ3: DAM_G02
A4: G03 | B4: 0.0097289 | C4: 0.0269781 | D4: 0.0578651 | E4: 0.0434876 | F4: 0.0360239 | G4: 0.0256144 | H4: 0.006658 | J4: G03 | K4: =IF(AC4=0,0,B4/AC4) -> 0.29946831 | L4: =IF(AD4=0,0,C4/AD4) -> 0.47000754 | M4: =IF(AE4=0,0,D4/AE4) -> 0.91398683 | N4: =IF(AF4=0,0,E4/AF4) -> 0.78213851 | O4: =IF(AG4=0,0,F4/AG4) -> 0.72513372 | P4: =IF(AH4=0,0,G4/AH4) -> 0.5931703 | Q4: =IF(AI4=0,0,H4/AI4) -> 0.25165226 | S4: G03 | T4: =IF(T69=0,0,((1-B4)*(K69/T69))-1) -> -0.14745753 | U4: =IF(U69=0,0,((1-C4)*(L69/U69))-1) -> -0.41885098 | V4: =IF(V69=0,0,((1-D4)*(M69/V69))-1) -> -0.94317387 | W4: =IF(W69=0,0,((1-E4)*(N69/W69))-1) -> -0.79730932 | X4: =IF(X69=0,0,((1-F4)*(O69/X69))-1) -> -0.75574443 | Y4: =IF(Y69=0,0,((1-G4)*(P69/Y69))-1) -> -0.58333942 | Z4: =IF(Z69=0,0,((1-H4)*(Q69/Z69))-1) -> -0.034765247 | AB4: G03 | AC4: 0.032487244 | AD4: 0.057399292 | AE4: 0.063310649 | AF4: 0.055600893 | AG4: 0.049678975 | AH4: 0.043182202 | AI4: 0.026457144 | AJ4: DAM_G03
A5: G04 | B5: 0.0446583 | C5: 0.0887762 | D5: 0.1327872 | E5: 0.1123262 | F5: 0.1048248 | G5: 0.0926668 | H5: 0.0378701 | J5: G04 | K5: =IF(AC5=0,0,B5/AC5) -> 0.55824664 | L5: =IF(AD5=0,0,C5/AD5) -> 0.79746401 | M5: =IF(AE5=0,0,D5/AE5) -> 1.1930253 | N5: =IF(AF5=0,0,E5/AF5) -> 1.0409111 | O5: =IF(AG5=0,0,F5/AG5) -> 1.0143947 | P5: =IF(AH5=0,0,G5/AH5) -> 0.95163026 | Q5: =IF(AI5=0,0,H5/AI5) -> 0.52998655 | S5: G04 | T5: =IF(T70=0,0,((1-B5)*(K70/T70))-1) -> -0.51575054 | U5: =IF(U70=0,0,((1-C5)*(L70/U70))-1) -> -0.78383907 | V5: =IF(V70=0,0,((1-D5)*(M70/V70))-1) -> -1.1800697 | W5: =IF(W70=0,0,((1-E5)*(N70/W70))-1) -> -1.0390392 | X5: =IF(X70=0,0,((1-F5)*(O70/X70))-1) -> -1.0221307 | Y5: =IF(Y70=0,0,((1-G5)*(P70/Y70))-1) -> -0.94775032 | Z5: =IF(Z70=0,0,((1-H5)*(Q70/Z70))-1) -> -0.46821677 | AB5: G04 | AC5: 0.079997436 | AD5: 0.11132314 | AE5: 0.11130292 | AF5: 0.10791143 | AG5: 0.10333729 | AH5: 0.097376895 | AI5: 0.071454832 | AJ5: DAM_G04
A6: G05 | B6: 0.0140662 | C6: 0.0115413 | D6: 0.0158006 | E6: 0.011536 | F6: 0.0133813 | G6: 0.0152841 | H6: 0.0134499 | J6: G05 | K6: =IF(AC6=0,0,B6/AC6) -> 0.92276047 | L6: =IF(AD6=0,0,C6/AD6) -> 0.86084618 | M6: =IF(AE6=0,0,D6/AE6) -> 1.1333234 | N6: =IF(AF6=0,0,E6/AF6) -> 0.8059048 | O6: =IF(AG6=0,0,F6/AG6) -> 0.88706886 | P6: =IF(AH6=0,0,G6/AH6) -> 1.0173309 | Q6: =IF(AI6=0,0,H6/AI6) -> 0.9105316 | S6: G05 | T6: =IF(T71=0,0,((1-B6)*(K71/T71))-1) -> -0.58683942 | U6: =IF(U71=0,0,((1-C6)*(L71/U71))-1) -> -0.57777631 | V6: =IF(V71=0,0,((1-D6)*(M71/V71))-1) -> -1.2460603 | W6: =IF(W71=0,0,((1-E6)*(N71/W71))-1) -> -0.83100752 | X6: =IF(X71=0,0,((1-F6)*(O71/X71))-1) -> -0.95837665 | Y6: =IF(Y71=0,0,((1-G6)*(P71/Y71))-1) -> -0.95824551 | Z6: =IF(Z71=0,0,((1-H6)*(Q71/Z71))-1) -> -0.51706234 | AB6: G05 | AC6: 0.015243609 | AD6: 0.013406925 | AE6: 0.013941828 | AF6: 0.014314346 | AG6: 0.015084849 | AH6: 0.015023725 | AI6: 0.014771481 | AJ6: DAM_G05
A7: G06 | B7: 0.007577 | C7: 0.0274591 | D7: 0.0504545 | E7: 0.0444545 | F7: 0.0336536 | G7: 0.0262831 | H7: 0.0067484 | J7: G06 | K7: =IF(AC7=0,0,B7/AC7) -> 0.30298035 | L7: =IF(AD7=0,0,C7/AD7) -> 0.62281423 | M7: =IF(AE7=0,0,D7/AE7) -> 1.0057887 | N7: =IF(AF7=0,0,E7/AF7) -> 0.96716211 | O7: =IF(AG7=0,0,F7/AG7) -> 0.86617103 | P7: =IF(AH7=0,0,G7/AH7) -> 0.79806216 | Q7: =IF(AI7=0,0,H7/AI7) -> 0.34905292 | S7: G06 | T7: =IF(T72=0,0,((1-B7)*(K72/T72))-1) -> -0.10149238 | U7: =IF(U72=0,0,((1-C7)*(L72/U72))-1) -> -0.54799901 | V7: =IF(V72=0,0,((1-D7)*(M72/V72))-1) -> -1.0362901 | W7: =IF(W72=0,0,((1-E7)*(N72/W72))-1) -> -0.97550507 | X7: =IF(X72=0,0,((1-F7)*(O72/X72))-1) -> -0.89721754 | Y7: =IF(Y72=0,0,((1-G7)*(P72/Y72))-1) -> -0.77683411 | Z7: =IF(Z72=0,0,((1-H7)*(Q72/Z72))-1) -> -0.049851921 | AB7: G06 | AC7: 0.025008222 | AD7: 0.044088749 | AE7: 0.050164117 | AF7: 0.045963856 | AG7: 0.038853297 | AH7: 0.03293365 | AI7: 0.019333458 | AJ7: DAM_G06
A8: G07 | B8: 0.0042131 | C8: 0.0133065 | D8: 0.0244277 | E8: 0.0163645 | F8: 0.0148119 | G8: 0.0113631 | H8: 0.0039698 | J8: G07 | K8: =IF(AC8=0,0,B8/AC8) -> 0.33737773 | L8: =IF(AD8=0,0,C8/AD8) -> 0.67410848 | M8: =IF(AE8=0,0,D8/AE8) -> 1.0509162 | N8: =IF(AF8=0,0,E8/AF8) -> 0.81348823 | O8: =IF(AG8=0,0,F8/AG8) -> 0.81107432 | P8: =IF(AH8=0,0,G8/AH8) -> 0.71062404 | Q8: =IF(AI8=0,0,H8/AI8) -> 0.4027901 | S8: G07 | T8: =IF(T73=0,0,((1-B8)*(K73/T73))-1) -> 0.075318882 | U8: =IF(U73=0,0,((1-C8)*(L73/U73))-1) -> -0.48543802 | V8: =IF(V73=0,0,((1-D8)*(M73/V73))-1) -> -1.1179506 | W8: =IF(W73=0,0,((1-E8)*(N73/W73))-1) -> -0.83272953 | X8: =IF(X73=0,0,((1-F8)*(O73/X73))-1) -> -0.87144311 | Y8: =IF(Y73=0,0,((1-G8)*(P73/Y73))-1) -> -0.65842585 | Z8: =IF(Z73=0,0,((1-H8)*(Q73/Z73))-1) -> 0.19204568 | AB8: G07 | AC8: 0.012487783 | AD8: 0.019739405 | AE8: 0.023244194 | AF8: 0.020116456 | AG8: 0.018262075 | AH8: 0.015990312 | AI8: 0.0098557537 | AJ8: DAM_G07
A9: G08 | B9: 0.0222767 | C9: 0.0385646 | D9: 0.0365704 | E9: 0.0397101 | F9: 0.0347593 | G9: 0.0355561 | H9: 0.0198098 | J9: G08 | K9: =IF(AC9=0,0,B9/AC9) -> 0.87349927 | L9: =IF(AD9=0,0,C9/AD9) -> 1.157327 | M9: =IF(AE9=0,0,D9/AE9) -> 1.5378127 | N9: =IF(AF9=0,0,E9/AF9) -> 1.4378361 | O9: =IF(AG9=0,0,F9/AG9) -> 1.2555693 | P9: =IF(AH9=0,0,G9/AH9) -> 1.1706852 | Q9: =IF(AI9=0,0,H9/AI9) -> 0.74056885 | S9: G08 | T9: =IF(T74=0,0,((1-B9)*(K74/T74))-1) -> -0.67655806 | U9: =IF(U74=0,0,((1-C9)*(L74/U74))-1) -> -1.0398525 | V9: =IF(V74=0,0,((1-D9)*(M74/V74))-1) -> -1.5840519 | W9: =IF(W74=0,0,((1-E9)*(N74/W74))-1) -> -1.4319636 | X9: =IF(X74=0,0,((1-F9)*(O74/X74))-1) -> -1.2838947 | Y9: =IF(Y74=0,0,((1-G9)*(P74/Y74))-1) -> -1.1361192 | Z9: =IF(Z74=0,0,((1-H9)*(Q74/Z74))-1) -> -0.52917002 | AB9: G08 | AC9: 0.025502826 | AD9: 0.03332213 | AE9: 0.023780789 | AF9: 0.027617961 | AG9: 0.027684096 | AH9: 0.030372042 | AI9: 0.026749437 | AJ9: DAM_G08
A10: G09 | B10: 0.0050026 | C10: 0.0107084 | D10: 0.0166031 | E10: 0.0126032 | F10: 0.0094961 | G10: 0.0104614 | H10: 0.0043414 | J10: G09 | K10: =IF(AC10=0,0,B10/AC10) -> 0.50285243 | L10: =IF(AD10=0,0,C10/AD10) -> 0.55410888 | M10: =IF(AE10=0,0,D10/AE10) -> 0.74448952 | N10: =IF(AF10=0,0,E10/AF10) -> 0.73620029 | O10: =IF(AG10=0,0,F10/AG10) -> 0.65427143 | P10: =IF(AH10=0,0,G10/AH10) -> 0.82806119 | Q10: =IF(AI10=0,0,H10/AI10) -> 0.47639814 | S10: G09 | T10: =IF(T75=0,0,((1-B10)*(K75/T75))-1) -> 0.015787071 | U10: =IF(U75=0,0,((1-C10)*(L75/U75))-1) -> -0.36122616 | V10: =IF(V75=0,0,((1-D10)*(M75/V75))-1) -> -0.82046853 | W10: =IF(W75=0,0,((1-E10)*(N75/W75))-1) -> -0.7586241 | X10: =IF(X75=0,0,((1-F10)*(O75/X75))-1) -> -0.7303849 | Y10: =IF(Y75=0,0,((1-G10)*(P75/Y75))-1) -> -0.75956949 | Z10: =IF(Z75=0,0,((1-H10)*(Q75/Z75))-1) -> 0.16697096 | AB10: G09 | AC10: 0.0099484455 | AD10: 0.019325444 | AE10: 0.022301321 | AF10: 0.017119254 | AG10: 0.014514007 | AH10: 0.012633607 | AI10: 0.0091129659 | AJ10: DAM_G09
A11: G10 | B11: 0.0005867 | C11: 0.0003866 | D11: 8.64e-05 | E11: 0.0003114 | F11: 0.0002097 | G11: 0.0004595 | H11: 0.0006289 | J11: G10 | K11: =IF(AC11=0,0,B11/AC11) -> 1.7082596 | L11: =IF(AD11=0,0,C11/AD11) -> 1.6833269 | M11: =IF(AE11=0,0,D11/AE11) -> 0.84219466 | N11: =IF(AF11=0,0,E11/AF11) -> 1.3296274 | O11: =IF(AG11=0,0,F11/AG11) -> 0.95894257 | P11: =IF(AH11=0,0,G11/AH11) -> 1.47792 | Q11: =IF(AI11=0,0,H11/AI11) -> 1.5987202 | S11: G10 | T11: =IF(T76=0,0,((1-B11)*(K76/T76))-1) -> 13.454167 | U11: =IF(U76=0,0,((1-C11)*(L76/U76))-1) -> 15.122709 | V11: =IF(V76=0,0,((1-D11)*(M76/V76))-1) -> -16.69872 | W11: =IF(W76=0,0,((1-E11)*(N76/W76))-1) -> -2.7426861 | X11: =IF(X76=0,0,((1-F11)*(O76/X76))-1) -> -5.8382547 | Y11: =IF(Y76=0,0,((1-G11)*(P76/Y76))-1) -> 1.4076203 | Z11: =IF(Z76=0,0,((1-H11)*(Q76/Z76))-1) -> 13.414228 | AB11: G10 | AC11: 0.00034344896 | AD11: 0.00022966424 | AE11: 0.00010258911 | AF11: 0.00023420095 | AG11: 0.00021867837 | AH11: 0.00031090993 | AI11: 0.00039337715 | AJ11: DAM_G10
A12: G11 | B12: 0.0036468 | C12: 0.0120934 | D12: 0.0241609 | E12: 0.016708 | F12: 0.0144133 | G12: 0.0104496 | H12: 0.0027376 | J12: G11 | K12: =IF(AC12=0,0,B12/AC12) -> 0.31442948 | L12: =IF(AD12=0,0,C12/AD12) -> 0.52441587 | M12: =IF(AE12=0,0,D12/AE12) -> 0.95101405 | N12: =IF(AF12=0,0,E12/AF12) -> 0.76781004 | O12: =IF(AG12=0,0,F12/AG12) -> 0.78281139 | P12: =IF(AH12=0,0,G12/AH12) -> 0.66610422 | Q12: =IF(AI12=0,0,H12/AI12) -> 0.28224548 | S12: G11 | T12: =IF(T77=0,0,((1-B12)*(K77/T77))-1) -> 0.13067801 | U12: =IF(U77=0,0,((1-C12)*(L77/U77))-1) -> -0.36475835 | V12: =IF(V77=0,0,((1-D12)*(M77/V77))-1) -> -1.0146868 | W12: =IF(W77=0,0,((1-E12)*(N77/W77))-1) -> -0.78665113 | X12: =IF(X77=0,0,((1-F12)*(O77/X77))-1) -> -0.84306603 | Y12: =IF(Y77=0,0,((1-G12)*(P77/Y77))-1) -> -0.61298562 | Z12: =IF(Z77=0,0,((1-H12)*(Q77/Z77))-1) -> 0.32337312 | AB12: G11 | AC12: 0.011598149 | AD12: 0.023060706 | AE12: 0.025405408 | AF12: 0.021760591 | AG12: 0.018412226 | AH12: 0.015687635 | AI12: 0.009699358 | AJ12: DAM_G11
A13: G12 | B13: 0.003622 | C13: 0.0120319 | D13: 0.0226734 | E13: 0.0162 | F13: 0.0136456 | G13: 0.0097577 | H13: 0.0029403 | J13: G12 | K13: =IF(AC13=0,0,B13/AC13) -> 0.36150732 | L13: =IF(AD13=0,0,C13/AD13) -> 0.61159112 | M13: =IF(AE13=0,0,D13/AE13) -> 1.1085086 | N13: =IF(AF13=0,0,E13/AF13) -> 0.88841326 | O13: =IF(AG13=0,0,F13/AG13) -> 0.84301184 | P13: =IF(AH13=0,0,G13/AH13) -> 0.72093089 | Q13: =IF(AI13=0,0,H13/AI13) -> 0.34572717 | S13: G12 | T13: =IF(T78=0,0,((1-B13)*(K78/T78))-1) -> 0.15434817 | U13: =IF(U78=0,0,((1-C13)*(L78/U78))-1) -> -0.42236082 | V13: =IF(V78=0,0,((1-D13)*(M78/V78))-1) -> -1.1837836 | W13: =IF(W78=0,0,((1-E13)*(N78/W78))-1) -> -0.90808792 | X13: =IF(X78=0,0,((1-F13)*(O78/X78))-1) -> -0.91018547 | Y13: =IF(Y78=0,0,((1-G13)*(P78/Y78))-1) -> -0.65799438 | Z13: =IF(Z78=0,0,((1-H13)*(Q78/Z78))-1) -> 0.34514305 | AB13: G12 | AC13: 0.010019161 | AD13: 0.019673111 | AE13: 0.020453969 | AF13: 0.018234757 | AG13: 0.016186724 | AH13: 0.013534862 | AI13: 0.0085046831 | AJ13: DAM_G12
... A64: G95 | B64: -3.1e-06 | C64: -2.93e-06 | D64: -9.16e-06 | E64: 0 | F64: 3.05e-05 | G64: -2.65e-06 | H64: -5.03e-07 | J64: G95 | K64: =IF(AC64=0,0,B64/AC64) -> -0.17790433 | L64: =IF(AD64=0,0,C64/AD64) -> -0.53805905 | M64: =IF(AE64=0,0,D64/AE64) -> -1.4857561 | N64: =IF(AF64=0,0,E64/AF64) -> 0 | O64: =IF(AG64=0,0,F64/AG64) -> 1.7829457 | P64: =IF(AH64=0,0,G64/AH64) -> -0.05132772 | Q64: =IF(AI64=0,0,H64/AI64) -> -0.43525454 | S64: G95 | T64: =IF(T129=0,0,((1-B64)*(K129/T129))-1) -> 0 | U64: =IF(U129=0,0,((1-C64)*(L129/U129))-1) -> 0 | V64: =IF(V129=0,0,((1-D64)*(M129/V129))-1) -> -262.3927 | W64: =IF(W129=0,0,((1-E64)*(N129/W129))-1) -> 0 | X64: =IF(X129=0,0,((1-F64)*(O129/X129))-1) -> -64.16779 | Y64: =IF(Y129=0,0,((1-G64)*(P129/Y129))-1) -> 17.434096 | Z64: =IF(Z129=0,0,((1-H64)*(Q129/Z129))-1) -> 5113.9092 | AB64: G95 | AC64: 1.7425096e-05 | AD64: 5.445499e-06 | AE64: 6.1652109e-06 | AF64: 0 | AG64: 1.7106522e-05 | AH64: 5.1629022e-05 | AI64: 1.1556456e-06 | AJ64: DAM_G95
A66: alpha-14 | B66: M1 | C66: M2 | D66: Q1 | E66: Q2 | F66: Q3 | G66: Q4 | H66: Q5 | J66: CMIN | K66: M1 | L66: M2 | M66: Q1 | N66: Q2 | O66: Q3 | P66: Q4 | Q66: Q5 | S66: Cmoyen | T66: M1 | U66: M2 | V66: Q1 | W66: Q2 | X66: Q3 | Y66: Q4 | Z66: Q5
A67: G01 | B67: 2906.971 | C67: 2149.566 | D67: 643.0907 | E67: 1024.215 | F67: 1121.747 | G67: 1720.205 | H67: 2975.969 | J67: G01 | K67: 3352.0453 | L67: 2365.2013 | M67: 587.18467 | N67: 1008.5271 | O67: 1060.162 | P67: 1785.2153 | Q67: 3732.9165 | S67: G01 | T67: =Cmoyen!M3 -> 4580.1196 | U67: =Cmoyen!N3 -> 4202.3101 | V67: =Cmoyen!X26 -> 3186.9512 | W67: =Cmoyen!Y26 -> 3961.7883 | X67: =Cmoyen!Z26 -> 4322.803 | Y67: =Cmoyen!AA26 -> 4762.4717 | Z67: =Cmoyen!AB26 -> 5262.4286
A68: G02 | B68: 1214.453 | C68: 475.7017 | D68: -13.73634 | E68: 269.2251 | F68: 383.5015 | G68: 545.6 | H68: 1715.997 | J68: G02 | K68: 1659.5273 | L68: 691.337 | M68: -69.642367 | N68: 253.53722 | O68: 321.91651 | P68: 610.61029 | Q68: 2472.9445 | S68: G02 | T68: =Cmoyen!M4 -> 2756.8073 | U68: =Cmoyen!N4 -> 1622.8444 | V68: =Cmoyen!X27 -> 1050.4471 | W68: =Cmoyen!Y27 -> 1637.0525 | X68: =Cmoyen!Z27 -> 2048.3069 | Y68: =Cmoyen!AA27 -> 2503.4446 | Z68: =Cmoyen!AB27 -> 3610.7803
A69: G03 | B69: 1944.006 | C69: 1698.933 | D69: 187.1326 | E69: 573.9122 | F69: 787.9914 | G69: 1272.589 | H69: 2536.133 | J69: G03 | K69: 2389.0803 | L69: 1914.5683 | M69: 131.22657 | N69: 558.22432 | O69: 726.40641 | P69: 1337.5993 | Q69: 3293.0805 | S69: G03 | T69: =Cmoyen!M5 -> 2775.0373 | U69: =Cmoyen!N5 -> 3205.5752 | V69: =Cmoyen!X28 -> 2175.639 | W69: =Cmoyen!Y28 -> 2634.3021 | X69: =Cmoyen!Z28 -> 2866.8269 | Y69: =Cmoyen!AA28 -> 3128.0557 | Z69: =Cmoyen!AB28 -> 3388.9737
A70: G04 | B70: 3018.643 | C70: 1259.178 | D70: -738.297 | E70: -209.1653 | F70: -85.84038 | G70: 341.1921 | H70: 4301.972 | J70: G04 | K70: 3463.7173 | L70: 1474.8133 | M70: -794.20303 | N70: -224.85318 | O70: -147.42537 | P70: 406.20239 | Q70: 5058.9195 | S70: G04 | T70: =Cmoyen!M6 -> 6833.3242 | U70: =Cmoyen!N6 -> 6217.0576 | V70: =Cmoyen!X29 -> 3824.8694 | W70: =Cmoyen!Y29 -> 5112.711 | X70: =Cmoyen!Z29 -> 5963.2895 | Y70: =Cmoyen!AA29 -> 7053.84 | Z70: =Cmoyen!AB29 -> 9152.8605
A71: G05 | B71: 100.5766 | C71: 104.1899 | D71: -63.87506 | E71: 131.6355 | F71: 98.30963 | G71: -18.8637 | H71: 169.2875 | J71: G05 | K71: 545.65091 | L71: 319.8252 | M71: -119.78109 | N71: 115.94762 | O71: 36.724635 | P71: 46.146587 | Q71: 926.23504 | S71: G05 | T71: =Cmoyen!M7 -> 1302.0983 | U71: =Cmoyen!N7 -> 748.73581 | V71: =Cmoyen!X30 -> 479.10398 | W71: =Cmoyen!Y30 -> 678.19615 | X71: =Cmoyen!Z30 -> 870.50207 | Y71: =Cmoyen!AA30 -> 1088.2967 | Z71: =Cmoyen!AB30 -> 1892.1226
A72: G06 | B72: 1488.958 | C72: 928.7143 | D72: -9.977374 | E72: 71.51242 | F72: 300.06 | G72: 481.7597 | H72: 1612.062 | J72: G06 | K72: 1934.0323 | L72: 1144.3496 | M72: -65.883401 | N72: 55.824541 | O72: 238.47501 | P72: 546.76999 | Q72: 2369.0095 | S72: G06 | T72: =Cmoyen!M8 -> 2136.1846 | U72: =Cmoyen!N8 -> 2462.222 | V72: =Cmoyen!X31 -> 1723.8649 | W72: =Cmoyen!Y31 -> 2177.7111 | X72: =Cmoyen!Z31 -> 2242.1089 | Y72: =Cmoyen!AA31 -> 2385.6655 | Z72: =Cmoyen!AB31 -> 2476.4798
A73: G07 | B73: 706.8188 | C73: 359.2602 | D73: -40.66912 | E73: 177.7645 | F73: 199.1016 | G73: 335.1876 | H73: 753.9516 | J73: G07 | K73: 1151.8931 | L73: 574.8955 | M73: -96.575147 | N73: 162.07662 | O73: 137.51661 | P73: 400.19789 | Q73: 1510.8991 | S73: G07 | T73: =Cmoyen!M9 -> 1066.6976 | U73: =Cmoyen!N9 -> 1102.3855 | V73: =Cmoyen!X32 -> 798.77517 | W73: =Cmoyen!Y32 -> 953.093 | X73: =Cmoyen!Z32 -> 1053.8504 | Y73: =Cmoyen!AA32 -> 1158.3148 | Z73: =Cmoyen!AB32 -> 1262.4526
A74: G08 | B74: 275.5761 | C74: -292.7732 | D74: -439.5074 | E74: -572.9121 | F74: -408.2883 | G74: -375.5278 | H74: 888.9153 | J74: G08 | K74: 720.65041 | L74: -77.137902 | M74: -495.41343 | N74: -588.59998 | O74: -469.87329 | P74: -310.51751 | Q74: 1645.8628 | S74: G08 | T74: =Cmoyen!M10 -> 2178.4333 | U74: =Cmoyen!N10 -> 1860.9392 | V74: =Cmoyen!X33 -> 817.215 | W74: =Cmoyen!Y33 -> 1308.5051 | X74: =Cmoyen!Z33 -> 1597.5674 | Y74: =Cmoyen!AA33 -> 2200.1063 | Z74: =Cmoyen!AB33 -> 3426.4144
A75: G09 | B75: 422.4705 | C75: 481.2346 | D75: 195.8172 | E75: 213.9642 | F75: 289.5689 | G75: 157.3483 | H75: 611.2052 | J75: G09 | K75: 867.54481 | L75: 696.8699 | M75: 139.91117 | N75: 198.27632 | O75: 227.98391 | P75: 222.35859 | Q75: 1368.1527 | S75: G09 | T75: =Cmoyen!M11 -> 849.78915 | U75: =Cmoyen!N11 -> 1079.267 | V75: =Cmoyen!X34 -> 766.37381 | W75: =Cmoyen!Y34 -> 811.08928 | X75: =Cmoyen!Z34 -> 837.56045 | Y75: =Cmoyen!AA34 -> 915.16007 | Z75: =Cmoyen!AB34 -> 1167.3067
A76: G10 | B76: -20.78107 | C76: -8.764707 | D76: 0.5566046 | E76: -3.655258 | F76: 0.5168849 | G76: -10.76127 | H76: -30.17424 | J76: G10 | K76: 424.29324 | L76: 206.87059 | M76: -55.349423 | N76: -19.343137 | O76: -61.06811 | P76: 54.249017 | Q76: 726.7733 | S76: G10 | T76: =Cmoyen!M12 -> 29.337167 | U76: =Cmoyen!N12 -> 12.826047 | V76: =Cmoyen!X35 -> 3.5254237 | W76: =Cmoyen!Y35 -> 11.096154 | X76: =Cmoyen!Z35 -> 12.619283 | Y76: =Cmoyen!AA35 -> 22.521861 | Z76: =Cmoyen!AB35 -> 50.388841
A77: G11 | B77: 679.1948 | C77: 612.4882 | D77: 42.76633 | E77: 239.386 | F77: 230.7682 | G77: 379.433 | H77: 891.7504 | J77: G11 | K77: 1124.2691 | L77: 828.1235 | M77: -13.139697 | N77: 223.69812 | O77: 169.18321 | P77: 444.44329 | Q77: 1648.6979 | S77: G11 | T77: =Cmoyen!M13 -> 990.70568 | U77: =Cmoyen!N13 -> 1287.87 | V77: =Cmoyen!X36 -> 873.04422 | W77: =Cmoyen!Y36 -> 1030.9901 | X77: =Cmoyen!Z36 -> 1062.5151 | Y77: =Cmoyen!AA36 -> 1136.3894 | Z77: =Cmoyen!AB36 -> 1242.4194
A78: G12 | B78: 546.4423 | C78: 426.7361 | D78: -76.2706 | E78: 96.40201 | F78: 146.6403 | G78: 273.6118 | H78: 712.7592 | J78: G12 | K78: 991.51661 | L78: 642.3714 | M78: -132.17663 | N78: 80.714131 | O78: 85.055305 | P78: 338.62209 | Q78: 1469.7067 | S78: G12 | T78: =Cmoyen!M14 -> 855.82961 | U78: =Cmoyen!N14 -> 1098.6832 | V78: =Cmoyen!X37 -> 702.89047 | W78: =Cmoyen!Y37 -> 863.94043 | X78: =Cmoyen!Z37 -> 934.08801 | Y78: =Cmoyen!AA37 -> 980.44562 | Z78: =Cmoyen!AB37 -> 1089.39
... A129: G95 | B129: 1.752837 | C129: 0.4679539 | D129: 0.5267247 | E129: 0 | F129: -0.7740541 | G129: 3.931776 | H129: 0.2123995 | J129: G95 | K129: 446.82715 | L129: 216.10325 | M129: -55.379303 | N129: -15.687879 | O129: -62.359049 | P129: 68.942063 | Q129: 757.15994 | S129: G95 | T129: =Cmoyen!M65 -> 0 | U129: =Cmoyen!N65 -> 0 | V129: =Cmoyen!X88 -> 0.21186441 | W129: =Cmoyen!Y88 -> 0 | X129: =Cmoyen!Z88 -> 0.98716683 | Y129: =Cmoyen!AA88 -> 3.739931 | Z129: =Cmoyen!AB88 -> 0.14803006

Sheet TOTAL-20-pdts
A1: beta | B1: 2007 | C1: 2014 | E1: CB | F1: 2007 | G1: 2014 | I1: Elasticité-revenu | J1: 2007 | K1: 2014 | M1: Elasticité-Prix | N1: 2007 | O1: 2014
A2: A00 | B2: 0.0897521 | C2: 0.052092 | E2: A00 | F2: 0.14516761 | G2: 0.13018789 | I2: A00 | J2: =B2/F2 -> 0.61826534 | K2: =C2/G2 -> 0.40012939 | M2: A00 | N2: =((1-B2)*(J24/N24))-1 -> -0.65922937 | O2: =((1-C2)*(K24/O24))-1 -> -0.43917364
A3: B05 | B3: 0.0123094 | C3: 0.0131777 | E3: B05 | F3: 0.014020363 | G3: 0.01406124 | I3: B05 | J3: =B3/F3 -> 0.87796584 | K3: =C3/G3 -> 0.93716484 | M3: B05 | N3: =((1-B3)*(J25/N25))-1 -> -0.9547666 | O3: =((1-C3)*(K25/O25))-1 -> -1.0131318
A4: C00 | B4: 0.0002209 | C4: 6.31e-05 | E4: C00 | F4: 0.0007061479 | G4: 0.00060134906 | I4: C00 | J4: =B4/F4 -> 0.31282399 | K4: =C4/G4 -> 0.10493074 | M4: C00 | N4: =((1-B4)*(J26/N26))-1 -> -1.8262868 | O4: =((1-C4)*(K26/O26))-1 -> -1.8853369
A5: D01 | B5: 0.1128563 | C5: 0.1114682 | E5: D01 | F5: 0.25791695 | G5: 0.22724891 | I5: D01 | J5: =B5/F5 -> 0.43756838 | K5: =C5/G5 -> 0.49051148 | M5: D01 | N5: =((1-B5)*(J27/N27))-1 -> -0.50471887 | O5: =((1-C5)*(K27/O27))-1 -> -0.55148952
A6: D02 | B6: 0.0448868 | C6: 0.0510683 | E6: D02 | F6: 0.039309202 | G6: 0.037308712 | I6: D02 | J6: =B6/F6 -> 1.1418904 | K6: =C6/G6 -> 1.3688036 | M6: D02 | N6: =((1-B6)*(J28/N28))-1 -> -1.1614936 | O6: =((1-C6)*(K28/O28))-1 -> -1.3772024
A7: D03 | B7: 0.0288466 | C7: 0.0450162 | E7: D03 | F7: 0.042089274 | G7: 0.048785153 | I7: D03 | J7: =B7/F7 -> 0.68536701 | K7: =C7/G7 -> 0.92274384 | M7: D03 | N7: =((1-B7)*(J29/N29))-1 -> -0.71910734 | O7: =((1-C7)*(K29/O29))-1 -> -0.94718055
A8: D04 | B8: 0.1367028 | C8: 0.0885994 | E8: D04 | F8: 0.055765281 | G8: 0.036314489 | I8: D04 | J8: =B8/F8 -> 2.4513963 | K8: =C8/G8 -> 2.439781 | M8: D04 | N8: =((1-B8)*(J30/N30))-1 -> -2.2695337 | O8: =((1-C8)*(K30/O30))-1 -> -2.3390876
A9: D05 | B9: 0.018061 | C9: 0.0165391 | E9: D05 | F9: 0.011763422 | G9: 0.0098940891 | I9: D05 | J9: =B9/F9 -> 1.5353525 | K9: =C9/G9 -> 1.6716142 | M9: D05 | N9: =((1-B9)*(J31/N31))-1 -> -1.6149074 | O9: =((1-C9)*(K31/O31))-1 -> -1.7669256
A10: D23 | B10: 0.0855924 | C10: 0.0398977 | E10: D23 | F10: 0.050511425 | G10: 0.03550734 | I10: D23 | J10: =B10/F10 -> 1.6945157 | K10: =C10/G10 -> 1.1236465 | M10: D23 | N10: =((1-B10)*(J32/N32))-1 -> -1.6544205 | O10: =((1-C10)*(K32/O32))-1 -> -1.147663
A11: E00 | B11: 0.0140526 | C11: 0.0156978 | E11: E00 | F11: 0.036224333 | G11: 0.038705328 | I11: E00 | J11: =B11/F11 -> 0.38793261 | K11: =C11/G11 -> 0.40557207 | M11: E00 | N11: =((1-B11)*(J33/N33))-1 -> -0.42562787 | O11: =((1-C11)*(K33/O33))-1 -> -0.44213124
A12: F45 | B12: 0.0329717 | C12: 0.0292507 | E12: F45 | F12: 0.027781658 | G12: 0.022434735 | I12: F45 | J12: =B12/F12 -> 1.1868154 | K12: =C12/G12 -> 1.303813 | M12: F45 | N12: =((1-B12)*(J34/N34))-1 -> -1.2178608 | O12: =((1-C12)*(K34/O34))-1 -> -1.3412552
A13: G00 | B13: 0.0359023 | C13: 0.022819 | E13: G00 | F13: 0.011009713 | G13: 0.012202197 | I13: G00 | J13: =B13/F13 -> 3.2609659 | K13: =C13/G13 -> 1.8700731 | M13: G00 | N13: =((1-B13)*(J35/N35))-1 -> -3.2733947 | O13: =((1-C13)*(K35/O35))-1 -> -1.9359625
... A21: OP0 | B21: 0.0577988 | C21: 0.082465 | E21: OP0 | F21: 0.03851358 | G21: 0.04285002 | I21: OP0 | J21: =B21/F21 -> 1.5007382 | K21: =C21/G21 -> 1.9245032 | M21: OP0 | N21: =((1-B21)*(J43/N43))-1 -> -1.4979457 | O21: =((1-C21)*(K43/O43))-1 -> -1.8711912
A23: alpha | B23: 2007 | C23: 2014 | I23: CMIN | J23: 2007 | K23: 2014 | M23: Cmoyen | N23: 2007 | O23: 2014
A24: A00 | B24: 3152.445 | C24: 5862.502 | I24: A00 | J24: 3091.6383 | K24: 5782.1293 | M24: A00 | N24: =Cmoyen!AF3 -> 8258.2154 | O24: =Cmoyen!AG3 -> 9772.9475
A25: B05 | B25: 97.33369 | C25: 66.32634 | I25: B05 | J25: 36.527007 | K25: -14.046406 | M25: B05 | N25: =Cmoyen!AF4 -> 797.58275 | O25: =Cmoyen!AG4 -> 1055.5495
A26: C00 | B26: 27.60662 | C26: 40.40427 | I26: C00 | J26: -33.200063 | K26: -39.968476 | M26: C00 | N26: =Cmoyen!AF5 -> 40.170955 | O26: =Cmoyen!AG5 -> 45.142086
A27: D01 | B27: 8252.132 | C27: 8691.429 | I27: D01 | J27: 8191.3253 | K27: 8611.0563 | M27: D01 | N27: =Cmoyen!AF6 -> 14672.238 | O27: =Cmoyen!AG6 -> 17059.127
A28: D02 | B28: -317.2973 | C28: -1032.908 | I28: D02 | J28: -378.10398 | K28: -1113.2807 | M28: D02 | N28: =Cmoyen!AF7 -> 2236.2004 | O28: =Cmoyen!AG7 -> 2800.6914
A29: D03 | B29: 753.3397 | C29: 282.9266 | I29: D03 | J29: 692.53302 | K29: 202.55385 | M29: D03 | N29: =Cmoyen!AF8 -> 2394.3516 | O29: =Cmoyen!AG8 -> 3662.2051
A30: D04 | B30: -4604.329 | C30: -3924.923 | I30: D04 | J30: -4665.1357 | K30: -4005.2957 | M30: D04 | N30: =Cmoyen!AF9 -> 3172.3448 | O30: =Cmoyen!AG9 -> 2726.057
A31: D05 | B31: -358.2525 | C31: -498.8251 | I31: D05 | J31: -419.05918 | K31: -579.19785 | M31: D05 | N31: =Cmoyen!AF10 -> 669.19114 | O31: =Cmoyen!AG10 -> 742.72972
A32: D23 | B32: -1995.667 | C32: -329.5738 | I32: D23 | J32: -2056.4737 | K32: -409.94655 | M32: D23 | N32: =Cmoyen!AF11 -> 2873.4663 | O32: =Cmoyen!AG11 -> 2665.4659
A33: E00 | B33: 1261.291 | C33: 1727.129 | I33: E00 | J33: 1200.4843 | K33: 1646.7563 | M33: E00 | N33: =Cmoyen!AF12 -> 2060.71 | O33: =Cmoyen!AG12 -> 2905.5325
A34: F45 | B34: -295.2462 | C34: -511.6632 | I34: F45 | J34: -356.05288 | K34: -592.03595 | M34: F45 | N34: =Cmoyen!AF13 -> 1580.4278 | O34: =Cmoyen!AG13 -> 1684.1312
A35: G00 | B35: -1416.077 | C35: -796.9845 | I35: G00 | J35: -1476.8837 | K35: -877.35725 | M35: G00 | N35: =Cmoyen!AF14 -> 626.31454 | O35: =Cmoyen!AG14 -> 915.99482
... A43: OP0 | B43: -1097.087 | C43: -2973.823 | I43: OP0 | J43: -1157.8937 | K43: -3054.1957 | M43: OP0 | N43: =Cmoyen!AF22 -> 2190.9394 | O43: =Cmoyen!AG22 -> 3216.6663

Sheet TOTAL-60-pdts
B1: beta-07 | C1: alpha-07 | F1: beta-14 | G1: alpha-14 | J1: CB-2007 | K1: Cmin-2007 | L1: Cmoyen-2007 | O1: CB-2014 | P1: Cmin-2014 | Q1: Cmoyen-2014 | T1: Elasticité-revenu-2007 | U1: Elasticité-Prix-2007 | X1: Elasticité-revenu-2014 | Y1: Elasticité-Prix-2014
A2: G01 | B2: 0.0210704 | C2: 2989.878 | E2: G01 | F2: 0.0213151 | G2: 2847.791 | I2: G01 | J2: 0.073628189 | K2: 4125.0406 | L2: =Cmoyen!AJ3 -> 4188.5201 | N2: G01 | O2: 0.059251236 | P2: 3276.121 | Q2: =Cmoyen!AL3 -> 4447.8744 | S2: G01 | T2: =B2/J2 -> 0.286173 | U2: =((1-B2)*(K2/L2))-1 -> -0.035906658 | W2: G01 | X2: =F2/O2 -> 0.35974102 | Y2: =((1-F2)*(P2/Q2))-1 -> -0.27914102
A3: G02 | B3: 0.0218978 | C3: 594.3209 | E3: G02 | F3: 0.0193959 | G3: 903.8701 | I3: G02 | J3: 0.032345104 | K3: 1729.4835 | L3: =Cmoyen!AJ4 -> 1840.0306 | N3: G02 | O3: 0.031436609 | P3: 1332.2001 | Q3: =Cmoyen!AL4 -> 2359.8848 | S3: G02 | T3: =B3/J3 -> 0.67700508 | U3: =((1-B3)*(K3/L3))-1 -> -0.08066114 | W3: G02 | X3: =F3/O3 -> 0.61698448 | Y3: =((1-F3)*(P3/Q3))-1 -> -0.44643021
A4: G03 | B4: 0.0112735 | C4: 1455.317 | E4: G03 | F4: 0.0105711 | G4: 2132.188 | I4: G03 | J4: 0.036855852 | K4: 2590.4796 | L4: =Cmoyen!AJ5 -> 2096.6355 | N4: G03 | O4: 0.038974494 | P4: 2560.518 | Q4: =Cmoyen!AL5 -> 2925.7391 | S4: G03 | T4: =B4/J4 -> 0.30588087 | U4: =((1-B4)*(K4/L4))-1 -> 0.22161235 | W4: G03 | X4: =F4/O4 -> 0.27123123 | Y4: =((1-F4)*(P4/Q4))-1 -> -0.13408186
A5: G04 | B5: 0.0634646 | C5: 2205.371 | E5: G04 | F5: 0.0487742 | G5: 2956.231 | I5: G04 | J5: 0.10223191 | K5: 3340.5336 | L5: =Cmoyen!AJ6 -> 5815.7128 | N5: G04 | O5: 0.088154843 | P5: 3384.561 | Q5: =Cmoyen!AL6 -> 6617.6116 | S5: G04 | T5: =B5/J5 -> 0.62079053 | U5: =((1-B5)*(K5/L5))-1 -> -0.46205597 | W5: G04 | X5: =F5/O5 -> 0.55327874 | Y5: =((1-F5)*(P5/Q5))-1 -> -0.51349793
A6: G05 | B6: 0.0132582 | C6: 104.8367 | E6: G05 | F6: 0.0139988 | G6: 57.54517 | I6: G05 | J6: 0.015101128 | K6: 1239.9993 | L6: =Cmoyen!AJ7 -> 859.06471 | N6: G05 | O6: 0.014765325 | P6: 485.87521 | Q6: =Cmoyen!AL7 -> 1108.4041 | S6: G05 | T6: =B6/J6 -> 0.8779609 | U6: =((1-B6)*(K6/L6))-1 -> 0.42429217 | W6: G05 | X6: =F6/O6 -> 0.94808612 | Y6: =((1-F6)*(P6/Q6))-1 -> -0.5677808
A7: G06 | B7: 0.0126459 | C7: 1508.491 | E7: G06 | F7: 0.0090289 | G7: 1572.525 | I7: G06 | J7: 0.039162968 | K7: 2643.6536 | L7: =Cmoyen!AJ8 -> 2227.8815 | N7: G06 | O7: 0.029976909 | P7: 2000.855 | Q7: =Cmoyen!AL8 -> 2250.3079 | S7: G06 | T7: =B7/J7 -> 0.32290454 | U7: =((1-B7)*(K7/L7))-1 -> 0.17161629 | W7: G06 | X7: =F7/O7 -> 0.30119517 | Y7: =((1-F7)*(P7/Q7))-1 -> -0.1188808
A8: G07 | B8: 0.0048958 | C8: 546.9978 | E8: G07 | F8: 0.0050353 | G8: 701.2007 | I8: G07 | J8: 0.01451125 | K8: 1682.1604 | L8: =Cmoyen!AJ9 -> 825.50807 | N8: G07 | O8: 0.01437615 | P8: 1129.5307 | Q8: =Cmoyen!AL9 -> 1079.1895 | S8: G07 | T8: =B8/J8 -> 0.33737961 | U8: =((1-B8)*(K8/L8))-1 -> 1.0277511 | W8: G07 | X8: =F8/O8 -> 0.35025372 | Y8: =((1-F8)*(P8/Q8))-1 -> 0.041377104
A9: G08 | B9: 0.0201052 | C9: 330.4513 | E9: G08 | F9: 0.0236555 | G9: 291.5272 | I9: G08 | J9: 0.025914074 | K9: 1465.6139 | L9: =Cmoyen!AJ10 -> 1474.1856 | N9: G08 | O9: 0.027539021 | P9: 719.85724 | Q9: =Cmoyen!AL10 -> 2067.3004 | S9: G08 | T9: =B9/J9 -> 0.77584097 | U9: =((1-B9)*(K9/L9))-1 -> -0.025802854 | W9: G08 | X9: =F9/O9 -> 0.85898116 | Y9: =((1-F9)*(P9/Q9))-1 -> -0.66002588
A10: G09 | B10: 0.0051161 | C10: 668.8648 | E10: G09 | F10: 0.005039 | G10: 551.8441 | I10: G09 | J10: 0.016873811 | K10: 1804.0274 | L10: =Cmoyen!AJ11 -> 959.9081 | N10: G09 | O10: 0.012390273 | P10: 980.17414 | Q10: =Cmoyen!AL11 -> 930.11359 | S10: G09 | T10: =B10/J10 -> 0.30319767 | U10: =((1-B10)*(K10/L10))-1 -> 0.86976005 | W10: G09 | X10: =F10/O10 -> 0.40668998 | Y10: =((1-F10)*(P10/Q10))-1 -> 0.048511763
A11: G10 | B11: 0.0006939 | C11: -18.69872 | E11: G10 | F11: 0.0005611 | G11: -18.56092 | I11: G10 | J11: 0.00036522949 | K11: 1116.4639 | L11: =Cmoyen!AJ12 -> 20.776975 | N11: G10 | O11: 0.00031381872 | P11: 409.76912 | Q11: =Cmoyen!AL12 -> 23.557758 | S11: G10 | T11: =B11/J11 -> 1.8999013 | U11: =((1-B11)*(K11/L11))-1 -> 52.698344 | W11: G10 | X11: =F11/O11 -> 1.7879749 | Y11: =((1-F11)*(P11/Q11))-1 -> 16.384473
A12: G11 | B12: 0.0038916 | C12: 633.9666 | E12: G11 | F12: 0.003967 | G12: 796.9309 | I12: G11 | J12: 0.015035864 | K12: 1769.1292 | L12: =Cmoyen!AJ13 -> 855.35202 | N12: G11 | O12: 0.014583069 | P12: 1225.2609 | Q12: =Cmoyen!AL13 -> 1094.7225 | S12: G11 | T12: =B12/J12 -> 0.25882117 | U12: =((1-B12)*(K12/L12))-1 -> 1.0602564 | W12: G11 | X12: =F12/O12 -> 0.27202778 | Y12: =((1-F12)*(P12/Q12))-1 -> 0.11480337
A13: G12 | B13: 0.0032322 | C13: 404.0031 | E13: G12 | F13: 0.004033 | G13: 638.0866 | I13: G12 | J13: 0.010333968 | K13: 1539.1657 | L13: =Cmoyen!AJ14 -> 587.87312 | N13: G12 | O13: 0.012533109 | P13: 1066.4166 | Q13: =Cmoyen!AL14 -> 940.83596 | S13: G12 | T13: =B13/J13 -> 0.31277433 | U13: =((1-B13)*(K13/L13))-1 -> 1.6097312 | W13: G12 | X13: =F13/O13 -> 0.32178768 | Y13: =((1-F13)*(P13/Q13))-1 -> 0.12890644
... A49: G76 | B49: 0.0459087 | C49: -1104.792 | E49: G76 | F49: 0.0021011 | G49: -38.65047 | I49: G76 | J49: 0.026488011 | K49: 30.370606 | L49: =Cmoyen!AJ50 -> 1506.8355 | N49: G76 | O49: 0.0015862517 | P49: 389.67957 | Q49: =Cmoyen!AL50 -> 119.07682 | S49: G76 | T49: =B49/J49 -> 1.7331879 | U49: =((1-B49)*(K49/L49))-1 -> -0.98077008 | W49: G76 | X49: =F49/O49 -> 1.3245691 | Y49: =((1-F49)*(P49/Q49))-1 -> 2.2656299
E50: G77 | F50: 0.0039424 | G50: -203.6866 | I50: G81 | J50: 0.0013314534 | K50: 1135.1626 | L50: =Cmoyen!AJ51 -> 75.742991 | N50: G77 | O50: 0.0012289998 | P50: 224.64344 | Q50: =Cmoyen!AL51 -> 92.25861 | W50: G77 | X50: =F50/O50 -> 3.2078118 | Y50: =((1-F50)*(P50/Q50))-1 -> 1.4253325
E51: G81 | F51: 0.003637 | G51: -184.4069 | I51: G82 | J51: 8.067423e-05 | K51: 1135.1626 | L51: =Cmoyen!AJ52 -> 4.5893515 | N51: G81 | O51: 0.001180441 | P51: 243.92314 | Q51: =Cmoyen!AL52 -> 88.6134 | W51: G81 | X51: =F51/O51 -> 3.0810518 | Y51: =((1-F51)*(P51/Q51))-1 -> 1.742655
E52: G82 | F52: 0.0006099 | G52: -29.14958 | I52: G83 | J52: 0.00029003394 | K52: 1135.1626 | L52: =Cmoyen!AJ53 -> 16.499292 | N52: G82 | O52: 0.00022155328 | P52: 399.18046 | Q52: =Cmoyen!AL53 -> 16.631572 | W52: G82 | X52: =F52/O52 -> 2.7528367 | Y52: =((1-F52)*(P52/Q52))-1 -> 22.986729
E53: G83 | F53: 0.0014877 | G53: -64.9417 | I53: G84 | J53: 0.00012925301 | K53: 1135.1626 | L53: =Cmoyen!AJ54 -> 7.3528745 | N53: G83 | O53: 0.00062258356 | P53: 363.38834 | Q53: =Cmoyen!AL54 -> 46.73613 | W53: G83 | X53: =F53/O53 -> 2.3895588 | Y53: =((1-F53)*(P53/Q53))-1 -> 6.7637519
E54: G84 | F54: 0.0003924 | G54: -13.75102 | I54: G85 | J54: 0.018230218 | K54: 1135.1626 | L54: =Cmoyen!AJ55 -> 1037.0707 | N54: G84 | O54: 0.0002091953 | P54: 414.57902 | Q54: =Cmoyen!AL55 -> 15.703882 | W54: G84 | X54: =F54/O54 -> 1.8757591 | Y54: =((1-F54)*(P54/Q54))-1 -> 25.389419
E55: G85 | F55: 0.0441316 | G55: -1525.326 | I55: G86 | J55: 3.4475103e-05 | K55: 1135.1626 | L55: =Cmoyen!AJ56 -> 1.9612008 | N55: G85 | O55: 0.023812397 | P55: -1096.996 | Q55: =Cmoyen!AL56 -> 1787.5501 | W55: G85 | X55: =F55/O55 -> 1.8533036 | Y55: =((1-F55)*(P55/Q55))-1 -> -1.5866039
E56: G86 | F56: 0.0006876 | G56: 5.173323 | I56: G87 | J56: 0.017891137 | K56: 1135.1626 | L56: =Cmoyen!AJ57 -> 1017.7812 | N56: G86 | O56: 0.00075655344 | P56: 433.50336 | Q56: =Cmoyen!AL57 -> 56.792987 | W56: G86 | X56: =F56/O56 -> 0.90885847 | Y56: =((1-F56)*(P56/Q56))-1 -> 6.6277954
E57: G87 | F57: 0.0366687 | G57: -1155.601 | I57: G88 | J57: 0.00012213148 | K57: 1135.1626 | L57: =Cmoyen!AJ58 -> 6.9477485 | N57: G87 | O57: 0.021274621 | P57: -727.27096 | Q57: =Cmoyen!AL58 -> 1597.0442 | W57: G87 | X57: =F57/O57 -> 1.7235888 | Y57: =((1-F57)*(P57/Q57))-1 -> -1.4386872
E58: G88 | F58: 0.0005725 | G58: -5.982793 | I58: G89 | J58: 0.020418697 | K58: 1135.1626 | L58: =Cmoyen!AJ59 -> 1161.5677 | N58: G88 | O58: 0.00049276421 | P58: 422.34724 | Q58: =Cmoyen!AL59 -> 36.990845 | W58: G88 | X58: =F58/O58 -> 1.1618133 | Y58: =((1-F58)*(P58/Q58))-1 -> 10.411079
E59: G89 | F59: 0.0052243 | G59: 693.4741 | I59: G91 | J59: 0.006694022 | K59: 1135.1626 | L59: =Cmoyen!AJ60 -> 380.80586 | N59: G89 | O59: 0.014462224 | P59: 1121.8041 | Q59: =Cmoyen!AL60 -> 1085.6509 | W59: G89 | X59: =F59/O59 -> 0.36123765 | Y59: =((1-F59)*(P59/Q59))-1 -> 0.027902706
E60: G91 | F60: 0.0236103 | G60: -931.171 | I60: G92 | J60: 0.015466084 | K60: 1135.1626 | L60: =Cmoyen!AJ61 -> 879.82611 | N60: G91 | O60: 0.011205953 | P60: -502.84096 | Q60: =Cmoyen!AL61 -> 841.20897 | W60: G91 | X60: =F60/O60 -> 2.1069426 | Y60: =((1-F60)*(P60/Q60))-1 -> -1.5836466
E61: G92 | F61: 0.0431807 | G61: -1871.682 | I61: G93 | J61: 0.0039225772 | K61: 1135.1626 | L61: =Cmoyen!AJ62 -> 223.14543 | N61: G92 | O61: 0.018247541 | P61: -1443.352 | Q61: =Cmoyen!AL62 -> 1369.8073 | W61: G92 | X61: =F61/O61 -> 2.3663845 | Y61: =((1-F61)*(P61/Q61))-1 -> -2.0081908
E62: G93 | F62: 0.0039901 | G62: -49.85609 | I62: G94 | J62: 0.0027464336 | K62: 1135.1626 | L62: =Cmoyen!AJ63 -> 156.23761 | N62: G93 | O62: 0.0033259101 | P62: 378.47395 | Q62: =Cmoyen!AL63 -> 249.66957 | W62: G93 | X62: =F62/O62 -> 1.1997017 | Y62: =((1-F62)*(P62/Q62))-1 -> 0.5098508
E63: G94 | F63: 0.0041603 | G63: -133.9291 | K63: 1135.1626 | L63: =Cmoyen!AJ64 -> 0 | N63: G94 | O63: 0.0023761827 | P63: 294.40094 | Q63: =Cmoyen!AL64 -> 178.37539 | W63: G94 | X63: =F63/O63 -> 1.7508334 | Y63: =((1-F63)*(P63/Q63))-1 -> 0.64359073
E64: G95 | F64: -8.66e-07 | G64: 1.1389 | K64: 1135.1626 | L64: =Cmoyen!AJ65 -> 0 | N64: G95 | O64: 1.4305535e-05 | P64: 429.46894 | Q64: =Cmoyen!AL65 -> 1.0738885 | W64: G95 | X64: =F64/O64 -> -0.060536009 | Y64: =((1-F64)*(P64/Q64))-1 -> 398.91982

Sheet Cmoyen
B2: 2007 | C2: M1 | D2: M2 | E2: 2014 | F2: M1 | G2: M2 | I2: 2007 | J2: M1 | K2: M2 | L2: 2014 | M2: M1 | N2: M2 | Q2: Q1-20-07 | R2: Q2-20-07 | S2: Q3-20-07 | T2: Q4-20-07 | U2: Q5-20-07 | X2: Q1-20-14 | Y2: Q2-20-14 | Z2: Q3-20-14 | AA2: Q4-20-14 | AB2: Q5-20-14 | AF2: total-20-07 | AG2: total-20-14 | AJ2: total-60-07 | AL2: total-60-14
B3: A00 | C3: 8903.7381 | D3: 7273.3084 | E3: A00 | F3: 9140.8204 | G3: 10946.736 | I3: G01 | J3: 4115.9292 | K3: 4299.2758 | L3: DAM_G01 | M3: 4580.1196 | N3: 4202.3101 | P3: DAMA00 | Q3: 3073.4509 | R3: 5261.3341 | S3: 7264.2987 | T3: 9755.9059 | U3: 16333.404 | W3: DAMA00 | X3: 7499.5859 | Y3: 8813.7856 | Z3: 9826.3904 | AA3: 10854.282 | AB3: 11961.545 | AE3: DAMA00 | AF3: 8258.2154 | AG3: 9772.9475 | AI3: G01 | AJ3: 4188.5201 | AK3: G01 | AL3: 4447.8744
B4: B05 | C4: 999.09308 | D4: 490.12816 | E4: B05 | F4: 1234.2746 | G4: 723.67721 | I4: G02 | J4: 2271.4177 | K4: 1181.8412 | L4: DAM_G02 | M4: 2756.8073 | N4: 1622.8444 | P4: DAMB05 | Q4: 259.93889 | R4: 444.3664 | S4: 623.63664 | T4: 907.19373 | U4: 1799.0147 | W4: DAMB05 | X4: 497.13735 | Y4: 747.9141 | Z4: 905.90974 | AA4: 1186.3092 | AB4: 1966.5698 | AE4: DAMB05 | AF4: 797.58275 | AG4: 1055.5495 | AI4: G02 | AJ4: 1840.0306 | AK4: G02 | AL4: 2359.8848
B5: C00 | C5: 36.639876 | D5: 45.558503 | E5: C00 | F5: 33.453998 | G5: 66.845549 | I5: G03 | J5: 1953.0087 | K5: 2315.7743 | L5: DAM_G03 | M5: 2775.0373 | N5: 3205.5752 | P5: DAMC00 | Q5: 20.26138 | R5: 32.050804 | S5: 40.190871 | T5: 48.591316 | U5: 60.967972 | W5: DAMC00 | X5: 47.704923 | Y5: 47.074967 | Z5: 45.947808 | AA5: 46.927215 | AB5: 37.910476 | AE5: DAMC00 | AF5: 40.170955 | AG5: 45.142086 | AI5: G03 | AJ5: 2096.6355 | AK5: G03 | AL5: 2925.7391
B6: D01 | C6: 14805.197 | D6: 14469.376 | E6: D01 | F6: 17615.792 | G6: 16025.464 | I6: G04 | J6: 6288.0628 | K6: 5095.0243 | L6: DAM_G04 | M6: 6833.3242 | N6: 6217.0576 | P6: DAMD01 | Q6: 6558.1514 | R6: 10613.166 | S6: 13693.826 | T6: 17718.93 | U6: 25344.363 | W6: DAMD01 | X6: 11210.893 | Y6: 14441.441 | Z6: 16859.371 | AA6: 19590.147 | AB6: 23435.148 | AE6: DAMD01 | AF6: 14672.238 | AG6: 17059.127 | AI6: G04 | AJ6: 5815.7128 | AK6: G04 | AL6: 6617.6116
B7: D02 | C7: 2635.0914 | D7: 1627.5919 | E7: D02 | F7: 3196.4211 | G7: 2065.8658 | I7: G05 | J7: 1076.1085 | K7: 527.90987 | L7: DAM_G05 | M7: 1302.0983 | N7: 748.73581 | P7: DAMD02 | Q7: 492.80694 | R7: 969.35768 | S7: 1513.7152 | T7: 2477.4505 | U7: 5890.0111 | W7: DAMD02 | X7: 1149.4578 | Y7: 1699.7091 | Z7: 2408.5301 | AA7: 3238.3469 | AB7: 5586.6618 | AE7: DAMD02 | AF7: 2236.2004 | AG7: 2800.6914 | AI7: G05 | AJ7: 859.06471 | AK7: G05 | AL7: 1108.4041
B8: D03 | C8: 2823.4891 | D8: 1739.5947 | E8: D03 | F8: 4159.6633 | G8: 2738.4814 | I8: G06 | J8: 2232.0408 | K8: 2221.5354 | L8: DAM_G06 | M8: 2136.1846 | N8: 2462.222 | P8: DAMD03 | Q8: 771.24545 | R8: 1443.3091 | S8: 2019.1094 | T8: 2810.9826 | U8: 5055.0703 | W8: DAMD03 | X8: 1781.5128 | Y8: 2520.7195 | Z8: 3136.5308 | AA8: 4165.8321 | AB8: 6795.7605 | AE8: DAMD03 | AF8: 2394.3516 | AG8: 3662.2051 | AI8: G06 | AJ8: 2227.8815 | AK8: G06 | AL8: 2250.3079
B9: D04 | C9: 3992.0106 | D9: 1921.7387 | E9: D04 | F9: 3404.9316 | G9: 1465.4633 | I9: G07 | J9: 856.57384 | K9: 778.10944 | L9: DAM_G07 | M9: 1066.6976 | N9: 1102.3855 | P9: DAMD04 | Q9: 463.09525 | R9: 854.39989 | S9: 1406.1362 | T9: 2228.4645 | U9: 11211.413 | W9: DAMD04 | X9: 665.94005 | Y9: 1042.5148 | Z9: 1437.9657 | AA9: 2546.0558 | AB9: 8054.9648 | AE9: DAMD04 | AF9: 3172.3448 | AG9: 2726.057 | AI9: G07 | AJ9: 825.50807 | AK9: G07 | AL9: 1079.1895
B10: D05 | C10: 800.99902 | D10: 468.08512 | E10: D05 | F10: 891.37963 | G10: 466.7036 | I10: G08 | J10: 1578.0893 | K10: 1315.6545 | L10: DAM_G08 | M10: 2178.4333 | N10: 1860.9392 | P10: DAMD05 | Q10: 118.14339 | R10: 227.83415 | S10: 364.71874 | T10: 605.12473 | U10: 2087.1961 | W10: DAMD05 | X10: 170.6804 | Y10: 291.14045 | Z10: 453.75389 | AA10: 808.21123 | AB10: 2020.6359 | AE10: DAMD05 | AF10: 669.19114 | AG10: 742.72972 | AI10: G08 | AJ10: 1474.1856 | AK10: G08 | AL10: 2067.3004
B11: D23 | C11: 3327.6159 | D11: 2180.5471 | E11: D23 | F11: 2946.5769 | G11: 2143.4745 | I11: G09 | J11: 815.14416 | K11: 1180.7818 | L11: DAM_G09 | M11: 849.78915 | N11: 1079.267 | P11: DAMD23 | Q11: 964.24832 | R11: 1427.0875 | S11: 1840.5744 | T11: 2430.7236 | U11: 7899.3666 | W11: DAMD23 | X11: 1380.1072 | Y11: 1698.7574 | Z11: 2019.5291 | AA11: 2834.9966 | AB11: 5462.1524 | AE11: DAMD23 | AF11: 2873.4663 | AG11: 2665.4659 | AI11: G09 | AJ11: 959.9081 | AK11: G09 | AL11: 930.11359
B12: E00 | C12: 2182.9144 | D12: 1874.2565 | E12: E00 | F12: 3446.7652 | G12: 1900.5243 | I12: G10 | J12: 30.296062 | K12: 6.2532189 | L12: DAM_G10 | M12: 29.337167 | N12: 12.826047 | P12: DAME00 | Q12: 1134.8438 | R12: 1629.8409 | S12: 1950.614 | T12: 2351.0524 | U12: 3300.8768 | W12: DAME00 | X12: 1972.8099 | Y12: 2512.7765 | Z12: 2886.283 | AA12: 3266.8508 | AB12: 3927.1987 | AE12: DAME00 | AF12: 2060.71 | AG12: 2905.5325 | AI12: G10 | AJ12: 20.776975 | AK12: G10 | AL12: 23.557758
B13: F45 | C13: 1566.3146 | D13: 1601.961 | E13: F45 | F13: 1705.9965 | G13: 1643.5299 | I13: G11 | J13: 772.29911 | K13: 982.0701 | L13: DAM_G11 | M13: 990.70568 | N13: 1287.87 | P13: DAMF45 | Q13: 347.32592 | R13: 655.66527 | S13: 997.67225 | T13: 1603.154 | U13: 4418.2531 | W13: DAMF45 | X13: 409.77281 | Y13: 809.34667 | Z13: 1301.4761 | AA13: 2022.9155 | AB13: 3939.5533 | AE13: DAMF45 | AF13: 1580.4278 | AG13: 1684.1312 | AI13: G11 | AJ13: 855.35202 | AK13: G11 | AL13: 1094.7225
B14: G00 | C14: 802.50325 | D14: 357.49443 | E14: G00 | F14: 1064.4604 | G14: 640.31098 | I14: G12 | J14: 536.19831 | K14: 666.71602 | L14: DAM_G12 | M14: 855.82961 | N14: 1098.6832 | P14: DAMG00 | Q14: 35.284959 | R14: 79.121741 | S14: 167.73817 | T14: 317.26859 | U14: 2603.4298 | W14: DAMG00 | X14: 150.01209 | Y14: 253.28746 | Z14: 469.30411 | AA14: 1097.6228 | AB14: 2651.8746 | AE14: DAMG00 | AF14: 626.31454 | AG14: 915.99482 | AI14: G12 | AJ14: 587.87312 | AK14: G12 | AL14: 940.83596
... B22: OP0 | C22: 2767.3952 | D22: 1311.4114 | E22: OP0 | F22: 4079.2138 | G22: 1615.013 | I22: G23 | J22: 41.21519 | K22: 33.791845 | L22: DAM_G23 | M22: 60.490751 | N22: 52.112844 | P22: DAMOP0 | Q22: 430.4411 | R22: 907.51312 | S22: 1388.3668 | T22: 2095.7701 | U22: 6301.8111 | W22: DAMOP0 | X22: 932.63295 | Y22: 1561.3084 | Z22: 2101.6139 | AA22: 3013.0007 | AB22: 8598.0296 | AE22: DAMOP0 | AF22: 2190.9394 | AG22: 3216.6663 | AI22: G23 | AJ22: 38.276126 | AK22: G23 | AL22: 57.558222
I23: G24 | J23: 177.49672 | K23: 138.60193 | L23: DAM_G24 | M23: 334.88424 | N23: 243.30197 | AI23: G24 | AJ23: 162.09742 | AK23: G24 | AL23: 302.82758
I24: G25 | J24: 73.440225 | K24: 38.733548 | L24: DAM_G25 | M24: 53.920694 | N24: 18.15814 | AI24: G25 | AJ24: 59.699094 | AK24: G25 | AL24: 41.40268
I25: G26 | J25: 75.590483 | K25: 39.562947 | L25: DAM_G26 | M25: 74.472563 | N25: 58.080501 | P25: 2007 | Q25: Q1-60-07 | R25: Q2-60-07 | S25: Q3-60-07 | T25: Q4-60-07 | U25: Q5-60-07 | W25: 2014 | X25: Q1-60-14 | Y25: Q2-60-14 | Z25: Q3-60-14 | AA25: Q4-60-14 | AB25: Q5-60-14 | AI25: G26 | AJ25: 61.326395 | AK25: G26 | AL25: 68.734828
I26: G27 | J26: 129.79301 | K26: 31.01073 | L26: DAM_G27 | M26: 153.40008 | N26: 32.573023 | P26: G01 | Q26: 2991.0707 | R26: 3831.8327 | S26: 4148.5281 | T26: 4529.4128 | U26: 4912.2646 | W26: G01 | X26: 3186.9512 | Y26: 3961.7883 | Z26: 4322.803 | AA26: 4762.4717 | AB26: 5262.4286 | AI26: G27 | AJ26: 90.682951 | AK26: G27 | AL26: 111.10683
I27: G28 | J27: 426.34435 | K27: 259.92704 | L27: DAM_G28 | M27: 497.71784 | N27: 327.63542 | P27: G02 | Q27: 694.07871 | R27: 1122.4111 | S27: 1492.3873 | T27: 1936.3641 | U27: 3206.9607 | W27: G02 | X27: 1050.4471 | Y27: 1637.0525 | Z27: 2048.3069 | AA27: 2503.4446 | AB27: 3610.7803 | AI27: G28 | AJ27: 360.4561 | AK27: G28 | AL27: 438.18367
I28: G31 | J28: 7931.2923 | K28: 2511.6724 | L28: DAM_G31 | M28: 14042.131 | N28: 4974.6537 | P28: G03 | Q28: 1327.5456 | R28: 1830.0981 | S28: 2062.477 | T28: 2307.3186 | U28: 2599.9564 | W28: G03 | X28: 2175.639 | Y28: 2634.3021 | Z28: 2866.8269 | AA28: 3128.0557 | AB28: 3388.9737 | AI28: G31 | AJ28: 5785.5464 | AK28: G31 | AL28: 10868.23
I29: G32 | J29: 1566.3146 | K29: 1601.961 | L29: DAM_G32 | M29: 1705.9965 | N29: 1643.5299 | P29: G04 | Q29: 2669.5572 | R29: 4007.041 | S29: 4880.8206 | T29: 6263.3868 | U29: 9294.7911 | W29: G04 | X29: 3824.8694 | Y29: 5112.711 | Z29: 5963.2895 | AA29: 7053.84 | AB29: 9152.8605 | AI29: G32 | AJ29: 1580.4278 | AK29: G32 | AL29: 1684.1312
I30: G33 | J30: 4528.0525 | K30: 3887.7986 | L30: DAM_G33 | M30: 4867.1806 | N30: 4547.1026 | P30: G05 | Q30: 358.88283 | R30: 492.58005 | S30: 679.32823 | T30: 817.73146 | U30: 1580.8532 | W30: G05 | X30: 479.10398 | Y30: 678.19615 | Z30: 870.50207 | AA30: 1088.2967 | AB30: 1892.1226 | AI30: G33 | AJ30: 4274.562 | AK30: G33 | AL30: 4755.1433
I31: G34 | J31: 0 | K31: 0.012875536 | L31: DAM_G34 | M31: 0.78362235 | N31: 3.1610018 | P31: G06 | Q31: 1426.9463 | R31: 1996.3049 | S31: 2191.9621 | T31: 2426.7802 | U31: 2737.8592 | W31: G06 | X31: 1723.8649 | Y31: 2177.7111 | Z31: 2242.1089 | AA31: 2385.6655 | AB31: 2476.4798 | AI31: G34 | AJ31: 0.005097706 | AK31: G34 | AL31: 1.6157796
I32: G41 | J32: 803.58908 | K32: 415.15165 | L32: DAM_G41 | M32: 786.01881 | N32: 452.54707 | P32: G07 | Q32: 491.7424 | R32: 753.6436 | S32: 818.39752 | T32: 916.41216 | U32: 1008.892 | W32: G07 | X32: 798.77517 | Y32: 953.093 | Z32: 1053.8504 | AA32: 1158.3148 | AB32: 1262.4526 | AI32: G41 | AJ32: 649.79822 | AK32: G41 | AL32: 669.29326
I33: G42 | J33: 227.17932 | K33: 231.201 | L33: DAM_G42 | M33: 305.73463 | N33: 292.68347 | P33: G08 | Q33: 474.11717 | R33: 882.06516 | S33: 1136.3961 | T33: 1609.5725 | U33: 2627.7687 | W33: G08 | X33: 817.215 | Y33: 1308.5051 | Z33: 1597.5674 | AA33: 2200.1063 | AB33: 3426.4144 | AI33: G42 | AJ33: 228.77159 | AK33: G42 | AL33: 301.16632
I34: G43 | J34: 515.28434 | K34: 245.68956 | L34: DAM_G43 | M34: 482.41209 | N34: 281.00302 | P34: G09 | Q34: 825.80859 | R34: 947.11746 | S34: 967.39023 | T34: 978.61456 | U34: 1029.4992 | W34: G09 | X34: 766.37381 | Y34: 811.08928 | Z34: 837.56045 | AA34: 915.16007 | AB34: 1167.3067 | AI34: G43 | AJ34: 408.54588 | AK34: G43 | AL34: 411.91261
I35: G44 | J35: 34.526957 | K35: 28.312947 | L35: DAM_G44 | M35: 66.936859 | N35: 99.993292 | P35: G10 | Q35: 2.1735242 | R35: 5.7876106 | S35: 9.6768782 | T35: 14.813627 | U35: 55.460993 | W35: G10 | X35: 3.5254237 | Y35: 11.096154 | Z35: 12.619283 | AA35: 22.521861 | AB35: 50.388841 | AI35: G44 | AJ35: 32.066695 | AK35: G44 | AL35: 78.507646
I36: G45 | J36: 2.2191749 | K36: 2.6895565 | L36: DAM_G45 | M36: 3.2081888 | N36: 5.7580322 | P36: G11 | Q36: 630.81753 | R36: 787.05632 | S36: 831.11379 | T36: 933.20842 | U36: 993.1593 | W36: G11 | X36: 873.04422 | Y36: 1030.9901 | Z36: 1062.5151 | AA36: 1136.3894 | AB36: 1242.4194 | AI36: G45 | AJ36: 2.4054092 | AK36: G45 | AL36: 4.1007138
I37: G46 | J37: 731.99883 | K37: 631.24106 | L37: DAM_G46 | M37: 892.91108 | N37: 775.7542 | P37: G12 | Q37: 429.47764 | R37: 522.16331 | S37: 572.45733 | T37: 641.37341 | U37: 696.87943 | W37: G12 | X37: 702.89047 | Y37: 863.94043 | Z37: 934.08801 | AA37: 980.44562 | AB37: 1089.39 | AI37: G46 | AJ37: 692.10663 | AK37: G46 | AL37: 851.9025
... I63: G94 | J63: 242.70066 | K63: 24.316524 | L63: DAM_G93 | M63: 235.54961 | N63: 275.88873 | P63: G52 | Q63: 699.93202 | R63: 1302.1673 | S63: 1851.6951 | T63: 2499.688 | U63: 5137.2984 | W63: G52 | X63: 1385.5831 | Y63: 2381.4038 | Z63: 3094.2547 | AA63: 4471.1343 | AB63: 9221.2478 | AI63: G94 | AJ63: 156.23761 | AK63: G93 | AL63: 249.66957
P64: G53 | Q64: 105.90519 | R64: 127.53258 | S64: 171.18964 | T64: 253.25919 | U64: 373.89798 | W64: G53 | X64: 1.0389831 | Y64: 1.1357249 | Z64: 1.3030602 | AA64: 0.83803222 | AB64: 10.068094 | AK64: G94 | AL64: 178.37539
P65: G61 | Q65: 257.61449 | R65: 557.98954 | S65: 895.59373 | T65: 2054.2358 | U65: 12175.786 | W65: G61 | X65: 374.98922 | Y65: 849.2054 | Z65: 1344.0853 | AA65: 2372.8654 | AB65: 10326.849 | AK65: G95 | AL65: 1.0738885
P66: G62 | Q66: 471.2737 | R66: 686.58488 | S66: 908.83662 | T66: 1191.5184 | U66: 1618.2291 | W66: G62 | X66: 697.23653 | Y66: 1078.414 | Z66: 1339.3581 | AA66: 1526.6971 | AB66: 1857.6143
P67: G63 | Q67: 347.78265 | R67: 643.40869 | S67: 935.23122 | T67: 1404.4569 | U67: 3662.5357 | W67: G63 | X67: 486.0139 | Y67: 812.84379 | Z67: 1088.0963 | AA67: 1573.3018 | AB67: 3312.0149
P68: G71 | Q68: 135.57156 | R68: 215.29847 | S68: 244.7841 | T68: 322.24115 | U68: 667.11675 | W68: G71 | X68: 67.903178 | Y68: 107.99149 | Z68: 176.6693 | AA68: 312.21663 | AB68: 852.22526
P69: G72 | Q69: 51.768336 | R69: 33.589702 | S69: 51.657185 | T69: 51.273881 | U69: 161.71086 | W69: G72 | X69: 23.408898 | Y69: 51.866494 | Z69: 60.274992 | AA69: 86.974568 | AB69: 162.65953
P70: G73 | Q70: 12.784436 | R70: 31.497989 | S70: 79.354486 | T70: 118.22311 | U70: 644.57938 | W70: G73 | X70: 12.108475 | Y70: 33.117604 | Z70: 58.062389 | AA70: 97.348274 | AB70: 380.31455
P71: G74 | Q71: 29.264758 | R71: 92.065165 | S71: 130.17068 | T71: 179.59519 | U71: 780.0611 | W71: G74 | X71: 51.609746 | Y71: 143.70525 | Z71: 228.77124 | AA71: 458.07854 | AB71: 2388.4441
P72: G75 | Q72: 9.4722719 | R72: 12.573612 | S72: 16.179431 | T72: 8.0895124 | U72: 25.695581 | W72: G75 | X72: 820.86557 | Y72: 1083.4826 | Z72: 1450.6736 | AA72: 1972.5812 | AB72: 5330.9419
P73: G76 | Q73: 527.77728 | R73: 703.6782 | S73: 953.04303 | T73: 1103.2946 | U73: 3392.4119 | W73: G76 | X73: 40.016667 | Y73: 45.707286 | Z73: 66.135132 | AA73: 132.68503 | AB73: 232.61833
P74: G81 | Q74: 3.7423971 | R74: 11.965406 | S74: 11.26477 | T74: 41.215097 | U74: 239.33279 | W74: G77 | X74: 6.2580508 | Y74: 7.4519231 | Z74: 21.648569 | AA74: 55.742232 | AB74: 268.48121
P75: G82 | Q75: 1.5849732 | R75: 0.72888174 | S75: 1.9897885 | T75: 1.4442218 | U75: 13.552646 | W75: G81 | X75: 2.9730932 | Y75: 6.4785503 | Z75: 28.536032 | AA75: 57.134925 | AB75: 251.71931
P76: G83 | Q76: 0.31932021 | R76: 5.7272727 | S76: 3.8030635 | T76: 9.7875752 | U76: 48.6503 | W76: G82 | X76: 1.1466102 | Y76: 10.508136 | Z76: 6.7502468 | AA76: 6.6041427 | AB76: 43.501754
P77: G84 | Q77: 3.4150268 | R77: 4.4312148 | S77: 6.5929978 | T77: 5.6947228 | U77: 13.658483 | W77: G83 | X77: 4.3271186 | Y77: 9.1176036 | Z77: 23.014808 | AA77: 39.329689 | AB77: 114.97563
... P86: G94 | Q86: 19.992844 | R86: 48.095736 | S86: 79.608315 | T86: 162.1817 | U86: 365.13148 | W86: G93 | X86: 114.11186 | Y86: 144.93121 | Z86: 170.68279 | AA86: 220.61335 | AB86: 464.69324
W87: G94 | X87: 13.952966 | Y87: 30.701183 | Z87: 61.23692 | AA87: 110.4672 | AB87: 492.51355
W88: G95 | X88: 0.21186441 | Y88: 0 | Z88: 0.98716683 | AA88: 3.739931 | AB88: 0.14803006

Sheet Synthèse-20
B2: Elasticité-revenu 2007 | D2: National | F2: Milieu Urbain | G2: Milieu Rural | I2: Quintile 1 | J2: Quintile 2 | K2: Quintile 3 | L2: Quintile 4 | M2: Quintile 5 | O2: Elasticité-Prix 2007 | Q2: National | S2: Milieu Urbain | T2: Milieu Rural | V2: Quintile 1 | W2: Quintile 2 | X2: Quintile 3 | Y2: Quintile 4 | Z2: Quintile 5 | AB2: tot-rev-2007 | AC2: Moy-rev-2007_mil | AD2: Moy-rev-2007_qui | AE2: tot-prix- 2007 | AF2: Moy-prix- 2007_mil | AG2: Moy-prix- 2007_qui
B4: A00 | D4: 0.61826534 | F4: 0.60469571 | G4: 0.86485086 | I4: 1.0594818 | J4: 1.0043047 | K4: 0.76665567 | L4: 0.8744419 | M4: 0.50513122 | O4: A00 | Q4: -0.65922937 | S4: -0.6378944 | T4: -0.93109298 | V4: -1.0635157 | W4: -1.0236482 | X4: -0.84829327 | Y4: -0.92918623 | Z4: -0.46800237 | AB4: =D4 -> 0.61826534 | AC4: =AVERAGE(F4:G4) -> 0.73477329 | AD4: =AVERAGE(I4:M4) -> 0.84200306 | AE4: =Q4 -> -0.65922937 | AF4: =AVERAGE(S4:T4) -> -0.78449369 | AG4: =AVERAGE(V4:Z4) -> -0.86652916
B5: B05 | D5: 0.87796584 | F5: 0.79672414 | G5: 0.90588147 | I5: 1.2082265 | J5: 0.91454487 | K5: 1.0165672 | L5: 0.91256775 | M5: 0.80714419 | O5: B05 | Q5: -0.9547666 | S5: -0.80650356 | T5: -1.7090431 | V5: -1.4068859 | W5: -1.1973496 | X5: -1.6986777 | Y5: -1.3728091 | Z5: -0.15907545 | AB5: =D5 -> 0.87796584 | AC5: =AVERAGE(F5:G5) -> 0.85130281 | AD5: =AVERAGE(I5:M5) -> 0.97181011 | AE5: =Q5 -> -0.9547666 | AF5: =AVERAGE(S5:T5) -> -1.2577733 | AG5: =AVERAGE(V5:Z5) -> -1.1669596
B6: C00 | D6: 0.31282399 | F6: 0.35494691 | G6: 0.53344062 | I6: 0.90076311 | J6: 0.8008729 | K6: 0.65372805 | L6: 0.58068732 | M6: 0.21217624 | O6: C00 | Q6: -1.8262868 | S6: -0.55686678 | T6: -9.2478947 | V6: -3.5359134 | W6: -4.7544032 | X6: -11.391573 | Y6: -9.2650108 | Z6: 19.183367 | AB6: =D6 -> 0.31282399 | AC6: =AVERAGE(F6:G6) -> 0.44419376 | AD6: =AVERAGE(I6:M6) -> 0.62964552 | AE6: =Q6 -> -1.8262868 | AF6: =AVERAGE(S6:T6) -> -4.9023807 | AG6: =AVERAGE(V6:Z6) -> -1.9527066
B7: D01 | D7: 0.43756838 | F7: 0.44734105 | G7: 0.66142194 | I7: 0.95310351 | J7: 0.92861148 | K7: 0.59394059 | L7: 0.78101543 | M7: 0.32079717 | O7: D01 | Q7: -0.50471887 | S7: -0.50357252 | T7: -0.75721682 | V7: -0.97417384 | W7: -0.95913487 | X7: -0.69528037 | Y7: -0.84897587 | Z7: -0.31861566 | AB7: =D7 -> 0.43756838 | AC7: =AVERAGE(F7:G7) -> 0.5543815 | AD7: =AVERAGE(I7:M7) -> 0.71549364 | AE7: =Q7 -> -0.50471887 | AF7: =AVERAGE(S7:T7) -> -0.63039467 | AG7: =AVERAGE(V7:Z7) -> -0.75923612
B8: D02 | D8: 1.1418904 | F8: 1.1283871 | G8: 1.1208592 | I8: 1.4951245 | J8: 1.5885187 | K8: 1.2502422 | L8: 1.3739846 | M8: 0.92753509 | O8: D02 | Q8: -1.1614936 | S8: -1.1252485 | T8: -1.3496387 | V8: -1.5798406 | W8: -1.6842183 | X8: -1.5122862 | Y8: -1.5141049 | Z8: -0.73800221 | AB8: =D8 -> 1.1418904 | AC8: =AVERAGE(F8:G8) -> 1.1246232 | AD8: =AVERAGE(I8:M8) -> 1.327081 | AE8: =Q8 -> -1.1614936 | AF8: =AVERAGE(S8:T8) -> -1.2374436 | AG8: =AVERAGE(V8:Z8) -> -1.4056905
B9: D03 | D9: 0.68536701 | F9: 0.6264359 | G9: 0.87446462 | I9: 1.1507789 | J9: 0.80882062 | K9: 1.1343109 | L9: 1.0577608 | M9: 0.51212139 | O9: D03 | Q9: -0.71910734 | S9: -0.63905515 | T9: -1.0992216 | V9: -1.2096503 | W9: -0.90050697 | X9: -1.3299005 | Y9: -1.1978416 | Z9: -0.29225831 | AB9: =D9 -> 0.68536701 | AC9: =AVERAGE(F9:G9) -> 0.75045026 | AD9: =AVERAGE(I9:M9) -> 0.93275853 | AE9: =Q9 -> -0.71910734 | AF9: =AVERAGE(S9:T9) -> -0.8691384 | AG9: =AVERAGE(V9:Z9) -> -0.98603156
B10: D04 | D10: 2.4513963 | F10: 2.3757601 | G10: 2.2444593 | I10: 1.3373422 | J10: 1.2700428 | K10: 1.7316479 | L10: 1.4080487 | M10: 2.1603917 | O10: D04 | Q10: -2.2695337 | S10: -2.1784965 | T10: -2.3074986 | V10: -1.4377822 | W10: -1.4040662 | X10: -1.9807798 | Y10: -1.5668546 | Z10: -1.862326 | AB10: =D10 -> 2.4513963 | AC10: =AVERAGE(F10:G10) -> 2.3101097 | AD10: =AVERAGE(I10:M10) -> 1.5814947 | AE10: =Q10 -> -2.2695337 | AF10: =AVERAGE(S10:T10) -> -2.2429975 | AG10: =AVERAGE(V10:Z10) -> -1.6503618
B11: D05 | D11: 1.5353525 | F11: 1.5265996 | G11: 1.4186744 | I11: 1.3555845 | J11: 1.5692898 | K11: 1.5340399 | L11: 1.6085943 | M11: 1.1701574 | O11: D05 | Q11: -1.6149074 | S11: -1.5258499 | T11: -2.2479886 | V11: -1.8010186 | W11: -2.1131271 | X11: -2.6959749 | Y11: -2.2854663 | Z11: -0.61084769 | AB11: =D11 -> 1.5353525 | AC11: =AVERAGE(F11:G11) -> 1.472637 | AD11: =AVERAGE(I11:M11) -> 1.4475332 | AE11: =Q11 -> -1.6149074 | AF11: =AVERAGE(S11:T11) -> -1.8869193 | AG11: =AVERAGE(V11:Z11) -> -1.9012869
B12: D23 | D12: 1.6945157 | F12: 1.7702043 | G12: 1.3733701 | I12: 0.7483696 | J12: 0.75027971 | K12: 0.62101114 | L12: 0.89022998 | M12: 1.900521 | O12: D23 | Q12: -1.6544205 | S12: -1.7030854 | T12: -1.5173539 | V12: -0.81134677 | W12: -0.84460294 | X12: -0.85940123 | Y12: -1.0616508 | Z12: -1.6658523 | AB12: =D12 -> 1.6945157 | AC12: =AVERAGE(F12:G12) -> 1.5717872 | AD12: =AVERAGE(I12:M12) -> 0.98208228 | AE12: =Q12 -> -1.6544205 | AF12: =AVERAGE(S12:T12) -> -1.6102196 | AG12: =AVERAGE(V12:Z12) -> -1.0485708
B13: E00 | D13: 0.38793261 | F13: 0.38571931 | G13: 0.5106725 | I13: 0.7078317 | J13: 0.6434147 | K13: 0.48770699 | L13: 0.61225276 | M13: 0.38028638 | O13: E00 | Q13: -0.42562787 | S13: -0.39694833 | T13: -0.72870622 | V13: -0.76542553 | W13: -0.73049058 | X13: -0.71542339 | Y13: -0.79671555 | Z13: -0.031262916 | AB13: =D13 -> 0.38793261 | AC13: =AVERAGE(F13:G13) -> 0.44819591 | AD13: =AVERAGE(I13:M13) -> 0.56629851 | AE13: =Q13 -> -0.42562787 | AF13: =AVERAGE(S13:T13) -> -0.56282727 | AG13: =AVERAGE(V13:Z13) -> -0.60786359
B14: F45 | D14: 1.1868154 | F14: 1.3112558 | G14: 1.4765662 | I14: 1.6711537 | J14: 2.2300531 | K14: 1.2623007 | L14: 0.67152646 | M14: 0.87165062 | O14: F45 | Q14: -1.2178608 | S14: -1.3060886 | T14: -1.6851956 | V14: -1.7994724 | W14: -2.3574664 | X14: -1.6750633 | Y14: -0.9360088 | Z14: -0.61547878 | AB14: =D14 -> 1.1868154 | AC14: =AVERAGE(F14:G14) -> 1.393911 | AD14: =AVERAGE(I14:M14) -> 1.3413369 | AE14: =Q14 -> -1.2178608 | AF14: =AVERAGE(S14:T14) -> -1.4956421 | AG14: =AVERAGE(V14:Z14) -> -1.4766979
B15: G00 | D15: 3.2609659 | F15: 3.1345558 | G15: 3.037674 | I15: 1.5272769 | J15: 2.0564493 | K15: 1.2022577 | L15: 1.8433186 | M15: 2.5699361 | O15: G00 | Q15: -3.2733947 | S15: -3.061588 | T15: -4.0703434 | V15: -3.0359568 | W15: -3.6454687 | X15: -3.7637503 | Y15: -3.1531767 | Z15: -2.0594184 | AB15: =D15 -> 3.2609659 | AC15: =AVERAGE(F15:G15) -> 3.0861149 | AD15: =AVERAGE(I15:M15) -> 1.8398477 | AE15: =Q15 -> -3.2733947 | AF15: =AVERAGE(S15:T15) -> -3.5659657 | AG15: =AVERAGE(V15:Z15) -> -3.1315542
... B23: OP0 | D23: 1.5007382 | F23: 1.4112976 | G23: 1.4666599 | I23: 1.3202003 | J23: 1.0095392 | K23: 2.0659569 | L23: 1.3238973 | M23: 1.3529573 | O23: OP0 | Q23: -1.4979457 | S23: -1.3893299 | T23: -1.7355895 | V23: -1.4308825 | W23: -1.1449405 | X23: -1.2367871 | Y23: -1.5015167 | Z23: -1.1546702 | AB23: =D23 -> 1.5007382 | AC23: =AVERAGE(F23:G23) -> 1.4389788 | AD23: =AVERAGE(I23:M23) -> 1.4145102 | AE23: =Q23 -> -1.4979457 | AF23: =AVERAGE(S23:T23) -> -1.5624597 | AG23: =AVERAGE(V23:Z23) -> -1.2937594
B26: Elasticité-revenu 2014 | D26: National | F26: Milieu Urbain | G26: Milieu Rural | I26: Quintile 1 | J26: Quintile 2 | K26: Quintile 3 | L26: Quintile 4 | M26: Quintile 5 | O26: Elasticité-Prix 2014 | Q26: National | S26: Milieu Urbain | T26: Milieu Rural | V26: Quintile 1 | W26: Quintile 2 | X26: Quintile 3 | Y26: Quintile 4 | Z26: Quintile 5 | AB26: tot-rev-2014 | AC26: Moy-rev-2014_mil | AD26: Moy-rev-2014_qui | AE26: tot-prix- 2014 | AF26: Moy-prix- 2014_mil | AG26: Moy-prix- 2014_qui
B28: A00 | D28: 0.40012939 | F28: 0.43941571 | G28: 0.68726763 | I28: 1.0081283 | J28: 0.92102559 | K28: 0.93601863 | L28: 0.7847426 | M28: 0.44912121 | O28: A00 | Q28: -0.43917364 | S28: -0.46925147 | T28: -0.76764886 | V28: -1.0159987 | W28: -0.9571373 | X28: -0.96999894 | Y28: -0.83774863 | Z28: -0.43986601 | AB28: =D28 -> 0.40012939 | AC28: =AVERAGE(F28:G28) -> 0.56334167 | AD28: =AVERAGE(I28:M28) -> 0.81980727 | AE28: =Q28 -> -0.43917364 | AF28: =AVERAGE(S28:T28) -> -0.61845016 | AG28: =AVERAGE(V28:Z28) -> -0.84414992
B29: B05 | D29: 0.93716484 | F29: 0.91298027 | G29: 0.87564473 | I29: 1.0302135 | J29: 0.84754111 | K29: 0.93151282 | L29: 1.0645746 | M29: 0.89581221 | O29: B05 | Q29: -1.0131318 | S29: -0.94078405 | T29: -1.5381681 | V29: -1.2070165 | W29: -1.1760003 | X29: -1.2419467 | Y29: -1.3734577 | Z29: -0.70906684 | AB29: =D29 -> 0.93716484 | AC29: =AVERAGE(F29:G29) -> 0.8943125 | AD29: =AVERAGE(I29:M29) -> 0.95393086 | AE29: =Q29 -> -1.0131318 | AF29: =AVERAGE(S29:T29) -> -1.2394761 | AG29: =AVERAGE(V29:Z29) -> -1.1414976
B30: C00 | D30: 0.10493074 | F30: 0.14988081 | G30: 0.49977364 | I30: 0.70487045 | J30: 0.80695521 | K30: 0.6035612 | L30: 0.55729799 | M30: 0.19943148 | O30: C00 | Q30: -1.8853369 | S30: -1.1464155 | T30: -7.7351474 | V30: -2.5757508 | W30: -6.056691 | X30: -6.7855923 | Y30: -8.5095617 | Z30: 9.6770588 | AB30: =D30 -> 0.10493074 | AC30: =AVERAGE(F30:G30) -> 0.32482722 | AD30: =AVERAGE(I30:M30) -> 0.57442327 | AE30: =Q30 -> -1.8853369 | AF30: =AVERAGE(S30:T30) -> -4.4407815 | AG30: =AVERAGE(V30:Z30) -> -2.8501074
B31: D01 | D31: 0.49051148 | F31: 0.49934654 | G31: 0.67609162 | I31: 0.94815138 | J31: 0.87102785 | K31: 0.8483727 | L31: 0.75780866 | M31: 0.50813638 | O31: D01 | Q31: -0.55148952 | S31: -0.55260077 | T31: -0.76327063 | V31: -0.96855613 | W31: -0.91556335 | X31: -0.89547843 | Y31: -0.81688994 | Z31: -0.53479219 | AB31: =D31 -> 0.49051148 | AC31: =AVERAGE(F31:G31) -> 0.58771908 | AD31: =AVERAGE(I31:M31) -> 0.78669939 | AE31: =Q31 -> -0.55148952 | AF31: =AVERAGE(S31:T31) -> -0.6579357 | AG31: =AVERAGE(V31:Z31) -> -0.82625601
B32: D02 | D32: 1.3688036 | F32: 1.3992968 | G32: 1.2880911 | I32: 1.6131836 | J32: 1.5097089 | K32: 1.2173575 | L32: 1.2576494 | M32: 1.4575589 | O32: D02 | Q32: -1.3772024 | S32: -1.3882729 | T32: -1.4974515 | V32: -1.6567292 | W32: -1.6224516 | X32: -1.3199136 | Y32: -1.3545694 | Z32: -1.3681163 | AB32: =D32 -> 1.3688036 | AC32: =AVERAGE(F32:G32) -> 1.3436939 | AD32: =AVERAGE(I32:M32) -> 1.4110917 | AE32: =Q32 -> -1.3772024 | AF32: =AVERAGE(S32:T32) -> -1.4428622 | AG32: =AVERAGE(V32:Z32) -> -1.464356
B33: D03 | D33: 0.92274384 | F33: 0.8938189 | G33: 1.0997427 | I33: 1.2205015 | J33: 1.1264975 | K33: 1.0895546 | L33: 1.1435966 | M33: 0.83214508 | O33: D03 | Q33: -0.94718055 | S33: -0.90610565 | T33: -1.2615479 | V33: -1.2549474 | W33: -1.21218 | X33: -1.1704938 | Y33: -1.2197807 | Z33: -0.78593367 | AB33: =D33 -> 0.92274384 | AC33: =AVERAGE(F33:G33) -> 0.99678078 | AD33: =AVERAGE(I33:M33) -> 1.0824591 | AE33: =Q33 -> -0.94718055 | AF33: =AVERAGE(S33:T33) -> -1.0838268 | AG33: =AVERAGE(V33:Z33) -> -1.1286671
B34: D04 | D34: 2.439781 | F34: 2.3605374 | G34: 2.3144919 | I34: 1.1481887 | J34: 1.8717413 | K34: 1.4716277 | L34: 1.7825806 | M34: 1.9652021 | O34: D04 | Q34: -2.3390876 | S34: -2.2413891 | T34: -2.5448232 | V34: -1.2765565 | W34: -2.0668026 | X34: -1.6470233 | Y34: -1.878242 | Z34: -1.8161916 | AB34: =D34 -> 2.439781 | AC34: =AVERAGE(F34:G34) -> 2.3375146 | AD34: =AVERAGE(I34:M34) -> 1.6478681 | AE34: =Q34 -> -2.3390876 | AF34: =AVERAGE(S34:T34) -> -2.3931061 | AG34: =AVERAGE(V34:Z34) -> -1.7369632
B35: D05 | D35: 1.6716142 | F35: 1.6027839 | G35: 1.9366787 | I35: 1.8144895 | J35: 1.2806437 | K35: 1.2370681 | L35: 1.5930688 | M35: 1.1697722 | O35: D05 | Q35: -1.7669256 | S35: -1.6294804 | T35: -2.9416329 | V35: -2.3267504 | W35: -2.1218688 | X35: -1.8557282 | Y35: -2.0385284 | Z35: -0.98471783 | AB35: =D35 -> 1.6716142 | AC35: =AVERAGE(F35:G35) -> 1.7697313 | AD35: =AVERAGE(I35:M35) -> 1.4190085 | AE35: =Q35 -> -1.7669256 | AF35: =AVERAGE(S35:T35) -> -2.2855566 | AG35: =AVERAGE(V35:Z35) -> -1.8655187
B36: D23 | D36: 1.1236465 | F36: 1.1492443 | G36: 1.2253802 | I36: 0.7958992 | J36: 1.1013455 | K36: 1.2372241 | L36: 1.3914532 | M36: 1.01196 | O36: D23 | Q36: -1.147663 | S36: -1.1541921 | T36: -1.4299289 | V36: -0.86469977 | W36: -1.2379255 | X36: -1.3631172 | Y36: -1.4981911 | Z36: -0.9456121 | AB36: =D36 -> 1.1236465 | AC36: =AVERAGE(F36:G36) -> 1.1873123 | AD36: =AVERAGE(I36:M36) -> 1.1075764 | AE36: =Q36 -> -1.147663 | AF36: =AVERAGE(S36:T36) -> -1.2920605 | AG36: =AVERAGE(V36:Z36) -> -1.1819091
B37: E00 | D37: 0.40557207 | F37: 0.33935849 | G37: 0.40911001 | I37: 0.56419093 | J37: 0.55677895 | K37: 0.62716771 | L37: 0.51664714 | M37: 0.43526639 | O37: E00 | Q37: -0.44213124 | S37: -0.35794383 | T37: -0.66841785 | V37: -0.62105727 | W37: -0.66459743 | X37: -0.73341825 | Y37: -0.63844029 | Z37: -0.34787286 | AB37: =D37 -> 0.40557207 | AC37: =AVERAGE(F37:G37) -> 0.37423425 | AD37: =AVERAGE(I37:M37) -> 0.54001022 | AE37: =Q37 -> -0.44213124 | AF37: =AVERAGE(S37:T37) -> -0.51318084 | AG37: =AVERAGE(V37:Z37) -> -0.60107722
B38: F45 | D38: 1.303813 | F38: 1.2938645 | G38: 2.177485 | I38: 1.929453 | J38: 1.9540441 | K38: 1.9035969 | L38: 1.5996144 | M38: 0.86265025 | O38: F45 | Q38: -1.3412552 | S38: -1.3053063 | T38: -2.377605 | V38: -2.1232328 | W38: -2.2207943 | X38: -2.0783226 | Y38: -1.7534853 | Z38: -0.7731724 | AB38: =D38 -> 1.303813 | AC38: =AVERAGE(F38:G38) -> 1.7356748 | AD38: =AVERAGE(I38:M38) -> 1.6498717 | AE38: =Q38 -> -1.3412552 | AF38: =AVERAGE(S38:T38) -> -1.8414557 | AG38: =AVERAGE(V38:Z38) -> -1.7898015
B39: G00 | D39: 1.8700731 | F39: 1.7969774 | G39: 2.5575422 | I39: 2.6253203 | J39: 2.525217 | K39: 2.729942 | L39: 2.4549828 | M39: 1.1079869 | O39: G00 | Q39: -1.9359625 | S39: -1.8097463 | T39: -3.2454699 | V39: -3.1974184 | W39: -3.4704182 | X39: -3.2885067 | Y39: -2.7366304 | Z39: -0.96747661 | AB39: =D39 -> 1.8700731 | AC39: =AVERAGE(F39:G39) -> 2.1772598 | AD39: =AVERAGE(I39:M39) -> 2.2886898 | AE39: =Q39 -> -1.9359625 | AF39: =AVERAGE(S39:T39) -> -2.5276081 | AG39: =AVERAGE(V39:Z39) -> -2.7320901
... B47: OP0 | D47: 1.9245032 | F47: 1.8280613 | G47: 1.6947389 | I47: 1.3759452 | J47: 1.2817967 | K47: 1.1785491 | L47: 1.1449787 | M47: 1.6479335 | O47: OP0 | Q47: -1.8711912 | S47: -1.7632311 | T47: -1.945646 | V47: -1.4555749 | W47: -1.423029 | X47: -1.3015678 | Y47: -1.2576663 | Z47: -1.544013 | AB47: =D47 -> 1.9245032 | AC47: =AVERAGE(F47:G47) -> 1.7614001 | AD47: =AVERAGE(I47:M47) -> 1.3258407 | AE47: =Q47 -> -1.8711912 | AF47: =AVERAGE(S47:T47) -> -1.8544386 | AG47: =AVERAGE(V47:Z47) -> -1.3963702
B50: Variation Elasticité-revenu 2014/2007 | D50: National | F50: Milieu Urbain | G50: Milieu Rural | I50: Quintile 1 | J50: Quintile 2 | K50: Quintile 3 | L50: Quintile 4 | M50: Quintile 5 | O50: Variation Elasticité-Prix 2014/2007 | Q50: National | S50: Milieu Urbain | T50: Milieu Rural | V50: Quintile 1 | W50: Quintile 2 | X50: Quintile 3 | Y50: Quintile 4 | Z50: Quintile 5 | AB50: tot-rev-14/07 | AC50: Moy-rev-14/07_mil | AD50: Moy-rev-14/07_qui | AE50: tot-prix- 14/07 | AF50: Moy-prix- 14/07_mil | AG50: Moy-prix- 14/07_qui
B52: A00 | D52: =D28/D4-1 -> -0.3528193 | F52: =F28/F4-1 -> -0.27332756 | G52: =G28/G4-1 -> -0.20533393 | I52: =I28/I4-1 -> -0.048470354 | J52: =J28/J4-1 -> -0.082922194 | K52: =K28/K4-1 -> 0.22091138 | L52: =L28/L4-1 -> -0.10257892 | M52: =M28/M4-1 -> -0.1108821 | O52: A00 | Q52: =Q28/Q4-1 -> -0.33380753 | S52: =S28/S4-1 -> -0.26437437 | T52: =T28/T4-1 -> -0.17554006 | V52: =V28/V4-1 -> -0.044679188 | W52: =W28/W4-1 -> -0.064974348 | X52: =X28/X4-1 -> 0.14347122 | Y52: =Y28/Y4-1 -> -0.098406101 | Z52: =Z28/Z4-1 -> -0.060120111 | AB52: =AB28/AB4-1 -> -0.3528193 | AC52: =AC28/AC4-1 -> -0.23331226 | AD52: =AD28/AD4-1 -> -0.026360703 | AE52: =AE28/AE4-1 -> -0.33380753 | AF52: =AF28/AF4-1 -> -0.21165693 | AG52: =AG28/AG4-1 -> -0.025826292
B53: B05 | D53: =D29/D5-1 -> 0.067427459 | F53: =F29/F5-1 -> 0.14591767 | G53: =G29/G5-1 -> -0.033378261 | I53: =I29/I5-1 -> -0.14733413 | J53: =J29/J5-1 -> -0.073264593 | K53: =K29/K5-1 -> -0.083668225 | L53: =L29/L5-1 -> 0.1665705 | M53: =M29/M5-1 -> 0.109854 | O53: B05 | Q53: =Q29/Q5-1 -> 0.061130377 | S53: =S29/S5-1 -> 0.16649707 | T53: =T29/T5-1 -> -0.099982843 | V53: =V29/V5-1 -> -0.1420651 | W53: =W29/W5-1 -> -0.017830457 | X53: =X29/X5-1 -> -0.26887442 | Y53: =Y29/Y5-1 -> 0.00047245209 | Z53: =Z29/Z5-1 -> 3.4574247 | AB53: =AB29/AB5-1 -> 0.067427459 | AC53: =AC29/AC5-1 -> 0.050522201 | AD53: =AD29/AD5-1 -> -0.018397884 | AE53: =AE29/AE5-1 -> 0.061130377 | AF53: =AF29/AF5-1 -> -0.014547337 | AG53: =AG29/AG5-1 -> -0.021819041
B54: C00 | D54: =D30/D6-1 -> -0.6645694 | F54: =F30/F6-1 -> -0.57773738 | G54: =G30/G6-1 -> -0.063112894 | I54: =I30/I6-1 -> -0.21747412 | J54: =J30/J6-1 -> 0.0075946106 | K54: =K30/K6-1 -> -0.076739623 | L54: =L30/L6-1 -> -0.040278706 | M54: =M30/M6-1 -> -0.060066849 | O54: C00 | Q54: =Q30/Q6-1 -> 0.032333426 | S54: =S30/S6-1 -> 1.0586889 | T54: =T30/T6-1 -> -0.16357747 | V54: =V30/V6-1 -> -0.27154584 | W54: =W30/W6-1 -> 0.27391194 | X54: =X30/X6-1 -> -0.40433229 | Y54: =Y30/Y6-1 -> -0.081537848 | Z54: =Z30/Z6-1 -> -0.49554953 | AB54: =AB30/AB6-1 -> -0.6645694 | AC54: =AC30/AC6-1 -> -0.26872628 | AD54: =AD30/AD6-1 -> -0.087703723 | AE54: =AE30/AE6-1 -> 0.032333426 | AF54: =AF30/AF6-1 -> -0.094158186 | AG54: =AG30/AG6-1 -> 0.45956767
B55: D01 | D55: =D31/D7-1 -> 0.12099389 | F55: =F31/F7-1 -> 0.11625467 | G55: =G31/G7-1 -> 0.022179001 | I55: =I31/I7-1 -> -0.0051957965 | J55: =J31/J7-1 -> -0.062010468 | K55: =K31/K7-1 -> 0.42837974 | L55: =L31/L7-1 -> -0.029713586 | M55: =M31/M7-1 -> 0.58398023 | O55: D01 | Q55: =Q31/Q7-1 -> 0.092666729 | S55: =S31/S7-1 -> 0.097360843 | T55: =T31/T7-1 -> 0.0079948156 | V55: =V31/V7-1 -> -0.005766637 | W55: =W31/W7-1 -> -0.045427946 | X55: =X31/X7-1 -> 0.2879386 | Y55: =Y31/Y7-1 -> -0.037793691 | Z55: =Z31/Z7-1 -> 0.67848682 | AB55: =AB31/AB7-1 -> 0.12099389 | AC55: =AC31/AC7-1 -> 0.060134732 | AD55: =AD31/AD7-1 -> 0.099519763 | AE55: =AE31/AE7-1 -> 0.092666729 | AF55: =AF31/AF7-1 -> 0.043688547 | AG55: =AG31/AG7-1 -> 0.088272781
B56: D02 | D56: =D32/D8-1 -> 0.19871715 | F56: =F32/F8-1 -> 0.24008579 | G56: =G32/G8-1 -> 0.14919972 | I56: =I32/I8-1 -> 0.078962684 | J56: =J32/J8-1 -> -0.04961214 | K56: =K32/K8-1 -> -0.026302603 | L56: =L32/L8-1 -> -0.084669928 | M56: =M32/M8-1 -> 0.57143259 | O56: D02 | Q56: =Q32/Q8-1 -> 0.18571668 | S56: =S32/S8-1 -> 0.23374786 | T56: =T32/T8-1 -> 0.10952029 | V56: =V32/V8-1 -> 0.048668577 | W56: =W32/W8-1 -> -0.036673797 | X56: =X32/X8-1 -> -0.12720653 | Y56: =Y32/Y8-1 -> -0.10536625 | Z56: =Z32/Z8-1 -> 0.85381053 | AB56: =AB32/AB8-1 -> 0.19871715 | AC56: =AC32/AC8-1 -> 0.19479484 | AD56: =AD32/AD8-1 -> 0.063304834 | AE56: =AE32/AE8-1 -> 0.18571668 | AF56: =AF32/AF8-1 -> 0.16600241 | AG56: =AG32/AG8-1 -> 0.041734327
B57: D03 | D57: =D33/D9-1 -> 0.34634995 | F57: =F33/F9-1 -> 0.42683219 | G57: =G33/G9-1 -> 0.25761823 | I57: =I33/I9-1 -> 0.060587284 | J57: =J33/J9-1 -> 0.39276561 | K57: =K33/K9-1 -> -0.039456809 | L57: =L33/L9-1 -> 0.081148634 | M57: =M33/M9-1 -> 0.62489812 | O57: D03 | Q57: =Q33/Q9-1 -> 0.31716157 | S57: =S33/S9-1 -> 0.41788334 | T57: =T33/T9-1 -> 0.14767383 | V57: =V33/V9-1 -> 0.037446415 | W57: =W33/W9-1 -> 0.34610846 | X57: =X33/X9-1 -> -0.11986368 | Y57: =Y33/Y9-1 -> 0.018315455 | Z57: =Z33/Z9-1 -> 1.6891748 | AB57: =AB33/AB9-1 -> 0.34634995 | AC57: =AC33/AC9-1 -> 0.32824363 | AD57: =AD33/AD9-1 -> 0.16049229 | AE57: =AE33/AE9-1 -> 0.31716157 | AF57: =AF33/AF9-1 -> 0.24701289 | AG57: =AG33/AG9-1 -> 0.14465617
B58: D04 | D58: =D34/D10-1 -> -0.0047382223 | F58: =F34/F10-1 -> -0.0064075238 | G58: =G34/G10-1 -> 0.031202403 | I58: =I34/I10-1 -> -0.14143991 | J58: =J34/J10-1 -> 0.4737624 | K58: =K34/K10-1 -> -0.15015767 | L58: =L34/L10-1 -> 0.26599353 | M58: =M34/M10-1 -> -0.090349159 | O58: D04 | Q58: =Q34/Q10-1 -> 0.030646761 | S58: =S34/S10-1 -> 0.028869712 | T58: =T34/T10-1 -> 0.10284931 | V58: =V34/V10-1 -> -0.11213499 | W58: =W34/W10-1 -> 0.4720122 | X58: =X34/X10-1 -> -0.1684975 | Y58: =Y34/Y10-1 -> 0.19873406 | Z58: =Z34/Z10-1 -> -0.024772462 | AB58: =AB34/AB10-1 -> -0.0047382223 | AC58: =AC34/AC10-1 -> 0.011863026 | AD58: =AD34/AD10-1 -> 0.04196878 | AE58: =AE34/AE10-1 -> 0.030646761 | AF58: =AF34/AF10-1 -> 0.066923212 | AG58: =AG34/AG10-1 -> 0.052474221
B59: D05 | D59: =D35/D11-1 -> 0.088749473 | F59: =F35/F11-1 -> 0.04990456 | G59: =G35/G11-1 -> 0.36513256 | I59: =I35/I11-1 -> 0.33852931 | J59: =J35/J11-1 -> -0.18393421 | K59: =K35/K11-1 -> -0.19358807 | L59: =L35/L11-1 -> -0.009651614 | M59: =M35/M11-1 -> -0.00032921886 | O59: D05 | Q59: =Q35/Q11-1 -> 0.094134338 | S59: =S35/S11-1 -> 0.067916535 | T59: =T35/T11-1 -> 0.30856217 | V59: =V35/V11-1 -> 0.29190807 | W59: =W35/W11-1 -> 0.0041368644 | X59: =X35/X11-1 -> -0.3116671 | Y59: =Y35/Y11-1 -> -0.10804706 | Z59: =Z35/Z11-1 -> 0.61205132 | AB59: =AB35/AB11-1 -> 0.088749473 | AC59: =AC35/AC11-1 -> 0.20174303 | AD59: =AD35/AD11-1 -> -0.019705746 | AE59: =AE35/AE11-1 -> 0.094134338 | AF59: =AF35/AF11-1 -> 0.21126359 | AG59: =AG35/AG11-1 -> -0.018812612
B60: D23 | D60: =D36/D12-1 -> -0.3368922 | F60: =F36/F12-1 -> -0.35078436 | G60: =G36/G12-1 -> -0.10775673 | I60: =I36/I12-1 -> 0.063510865 | J60: =J36/J12-1 -> 0.46791319 | K60: =K36/K12-1 -> 0.99227362 | L60: =L36/L12-1 -> 0.56302661 | M60: =M36/M12-1 -> -0.46753546 | O60: D23 | Q60: =Q36/Q12-1 -> -0.30630514 | S60: =S36/S12-1 -> -0.32229347 | T60: =T36/T12-1 -> -0.057616752 | V60: =V36/V12-1 -> 0.065758558 | W60: =W36/W12-1 -> 0.46568926 | X60: =X36/X12-1 -> 0.5861243 | Y60: =Y36/Y12-1 -> 0.41119011 | Z60: =Z36/Z12-1 -> -0.43235537 | AB60: =AB36/AB12-1 -> -0.3368922 | AC60: =AC36/AC12-1 -> -0.24461004 | AD60: =AD36/AD12-1 -> 0.1277837 | AE60: =AE36/AE12-1 -> -0.30630514 | AF60: =AF36/AF12-1 -> -0.19758742 | AG60: =AG36/AG12-1 -> 0.12716196
B61: E00 | D61: =D37/D13-1 -> 0.045470422 | F61: =F37/F13-1 -> -0.12019315 | G61: =G37/G13-1 -> -0.19887989 | I61: =I37/I13-1 -> -0.20293069 | J61: =J37/J13-1 -> -0.13464995 | K61: =K37/K13-1 -> 0.28595184 | L61: =L37/L13-1 -> -0.15615384 | M61: =M37/M13-1 -> 0.14457528 | O61: E00 | Q61: =Q37/Q13-1 -> 0.038774181 | S61: =S37/S13-1 -> -0.098260888 | T61: =T37/T13-1 -> -0.082733433 | V61: =V37/V13-1 -> -0.18861176 | W61: =W37/W13-1 -> -0.090203969 | X61: =X37/X13-1 -> 0.02515274 | Y61: =Y37/Y13-1 -> -0.19865968 | Z61: =Z37/Z13-1 -> 10.127332 | AB61: =AB37/AB13-1 -> 0.045470422 | AC61: =AC37/AC13-1 -> -0.16502082 | AD61: =AD37/AD13-1 -> -0.046421252 | AE61: =AE37/AE13-1 -> 0.038774181 | AF61: =AF37/AF13-1 -> -0.088209001 | AG61: =AG37/AG13-1 -> -0.011164304
B62: F45 | D62: =D38/D14-1 -> 0.098581162 | F62: =F38/F14-1 -> -0.013263035 | G62: =G38/G14-1 -> 0.47469518 | I62: =I38/I14-1 -> 0.15456347 | J62: =J38/J14-1 -> -0.12376791 | K62: =K38/K14-1 -> 0.50803752 | L62: =L38/L14-1 -> 1.3820572 | M62: =M38/M14-1 -> -0.010325657 | O62: F45 | Q62: =Q38/Q14-1 -> 0.10132061 | S62: =S38/S14-1 -> -0.00059891182 | T62: =T38/T14-1 -> 0.41087778 | V62: =V38/V14-1 -> 0.17991962 | W62: =W38/W14-1 -> -0.05797413 | X62: =X38/X14-1 -> 0.24074275 | Y62: =Y38/Y14-1 -> 0.87336411 | Z62: =Z38/Z14-1 -> 0.25621293 | AB62: =AB38/AB14-1 -> 0.098581162 | AC62: =AC38/AC14-1 -> 0.24518338 | AD62: =AD38/AD14-1 -> 0.23002037 | AE62: =AE38/AE14-1 -> 0.10132061 | AF62: =AF38/AF14-1 -> 0.23121414 | AG62: =AG38/AG14-1 -> 0.21202952
B63: G00 | D63: =D39/D15-1 -> -0.42652787 | F63: =F39/F15-1 -> -0.42672024 | G63: =G39/G15-1 -> -0.15805904 | I63: =I39/I15-1 -> 0.71895498 | J63: =J39/J15-1 -> 0.22795006 | K63: =K39/K15-1 -> 1.2706796 | L63: =L39/L15-1 -> 0.33182774 | M63: =M39/M15-1 -> -0.56886596 | O63: G00 | Q63: =Q39/Q15-1 -> -0.40857651 | S63: =S39/S15-1 -> -0.4088864 | T63: =T39/T15-1 -> -0.20265451 | V63: =V39/V15-1 -> 0.053183113 | W63: =W39/W15-1 -> -0.048018648 | X63: =X39/X15-1 -> -0.12626862 | Y63: =Y39/Y15-1 -> -0.13210368 | Z63: =Z39/Z15-1 -> -0.53021853 | AB63: =AB39/AB15-1 -> -0.42652787 | AC63: =AC39/AC15-1 -> -0.29449815 | AD63: =AD39/AD15-1 -> 0.24395612 | AE63: =AE39/AE15-1 -> -0.40857651 | AF63: =AF39/AF15-1 -> -0.29118552 | AG63: =AG39/AG15-1 -> -0.12756097
... B71: OP0 | D71: =D47/D23-1 -> 0.28237104 | F71: =F47/F23-1 -> 0.29530529 | G71: =G47/G23-1 -> 0.15550915 | I71: =I47/I23-1 -> 0.042224563 | J71: =J47/J23-1 -> 0.2696849 | K71: =K47/K23-1 -> -0.4295384 | L71: =L47/L23-1 -> -0.13514536 | M71: =M47/M23-1 -> 0.21802334 | O71: OP0 | Q71: =Q47/Q23-1 -> 0.24917162 | S71: =S47/S23-1 -> 0.26912339 | T71: =T47/T23-1 -> 0.12102891 | V71: =V47/V23-1 -> 0.017256723 | W71: =W47/W23-1 -> 0.24288465 | X71: =X47/X23-1 -> 0.052378188 | Y71: =Y47/Y23-1 -> -0.16240274 | Z71: =Z47/Z23-1 -> 0.33718967 | AB71: =AB47/AB23-1 -> 0.28237104 | AC71: =AC47/AC23-1 -> 0.22406262 | AD71: =AD47/AD23-1 -> -0.062685694 | AE71: =AE47/AE23-1 -> 0.24917162 | AF71: =AF47/AF23-1 -> 0.18687128 | AG71: =AG47/AG23-1 -> 0.079312105

Sheet Synthèse-60
B2: Elasticité-revenu 2007 | C2: Milieu Urbain | D2: Milieu Rural | E2: Quintile 1 | F2: Quintile 2 | G2: Quintile 3 | H2: Quintile 4 | I2: Quintile 5 | K2: Elasticité-Prix 2007 | L2: Milieu Urbain | M2: Milieu Rural | N2: Quintile 1 | O2: Quintile 2 | P2: Quintile 3 | Q2: Quintile 4 | R2: Quintile 5
B4: G01 | C4: 0.29891619 | D4: 0.45614943 | E4: 0.80344403 | F4: 0.81076652 | G4: 0.77423129 | H4: 0.66247003 | I4: 0.32521352 | K4: G01 | L4: 0.034785149 | M4: -0.40851501 | N4: -0.84206145 | O4: -0.83376801 | P4: -0.80038434 | Q4: -0.65149517 | R4: 0.22125846
B5: G02 | C5: 0.59546444 | D5: 0.80568398 | E5: 1.0235349 | F5: 1.1137533 | G5: 0.84743054 | H5: 0.80169306 | I5: 0.5405861 | K5: G02 | L5: 0.02350758 | M5: -0.54123327 | N5: -1.1117996 | O5: -1.1323451 | P5: -0.87971109 | Q5: -0.73656943 | R5: 0.30362711
B6: G03 | C6: 0.31269045 | D6: 0.60997196 | E6: 0.95972233 | F6: 0.99678347 | G6: 0.87863885 | H6: 0.80661268 | I6: 0.25849365 | K6: G03 | L6: 0.41891883 | M6: -0.48697093 | N6: -1.0072317 | O6: -1.0106001 | P6: -0.90357254 | Q6: -0.75415213 | R6: 0.79853211
B7: G04 | C7: 0.58936227 | D7: 0.95359603 | E7: 1.03195 | F7: 1.147645 | G7: 1.1527621 | H7: 0.99849025 | I7: 0.53480866 | K7: G04 | L7: -0.39425179 | M7: -0.90215709 | N7: -1.0494462 | O7: -1.134034 | P7: -1.1407437 | Q7: -0.97872266 | R7: -0.2727138
B8: G05 | C8: 0.79672229 | D8: 0.90588528 | E8: 0.90924878 | F8: 0.68396292 | G8: 0.81859974 | H8: 0.79912442 | I8: 0.80723397 | K8: G05 | L8: 0.53493309 | M8: -0.29869044 | N8: -1.0853139 | O8: -0.73997014 | P8: -0.88314248 | Q8: -0.63121097 | R8: 0.92646252
B9: G06 | C9: 0.29135356 | D9: 0.66763854 | E9: 1.0434813 | F9: 0.97172687 | G9: 0.95743946 | H9: 0.87822895 | I9: 0.29702477 | K9: G06 | L9: 0.34697665 | M9: -0.53778923 | N9: -1.0826533 | O9: -0.98575698 | P9: -0.97808213 | Q9: -0.82713245 | R9: 0.70441026
B10: G07 | C10: 0.30043915 | D10: 0.64974666 | E10: 0.85168512 | F10: 0.91655754 | G10: 0.91605225 | H10: 0.72899064 | I10: 0.35605862 | K10: G07 | L10: 1.3886353 | M10: -0.24141939 | N10: -0.9813548 | O10: -0.95247102 | P10: -0.968923 | Q10: -0.58036338 | R10: 2.3865239
B11: G08 | C11: 0.75371663 | D11: 1.1722626 | E11: 1.4667909 | F11: 1.515512 | G11: 1.2436673 | H11: 1.1115554 | I11: 0.60912714 | K11: G08 | L11: 0.14703017 | M11: -0.92813828 | N11: -1.5837274 | O11: -1.5246309 | P11: -1.2722533 | Q11: -1.023211 | R11: 0.42588639
B12: G09 | C12: 0.40796649 | D12: 0.44341527 | E12: 0.86699336 | F12: 0.88231311 | G12: 0.63321431 | H12: 0.73034553 | I12: 0.50918648 | K12: G09 | L12: 1.3647913 | M12: -0.17846266 | N12: -0.94566499 | O12: -0.91226993 | P12: -0.6820038 | Q12: -0.59170928 | R12: 2.1738799
B13: G10 | C13: 1.6492917 | D13: 0.94757217 | E13: 3.0435244 | F13: 0.98947822 | G13: 1.5380999 | H13: 0.86530395 | I13: 1.3847732 | K13: G10 | L13: 46.336445 | M13: 50.963266 | N13: -32.298107 | O13: -5.5408237 | P13: -5.9620374 | Q13: 8.6465939 | R13: 48.684165
B14: G11 | C14: 0.28828687 | D14: 0.49642423 | E14: 0.85594296 | F14: 0.86300563 | G14: 0.67596322 | H14: 0.70618906 | I14: 0.26856503 | K14: G11 | L14: 1.5867304 | M14: -0.17517982 | N14: -0.95772975 | O14: -0.89848435 | P14: -0.73099271 | Q14: -0.56050034 | R14: 2.520365
B15: G12 | C15: 0.35487166 | D15: 0.53339468 | E15: 0.89405974 | F15: 1.1195783 | G15: 0.82939494 | H15: 0.66785942 | I15: 0.35760701 | K15: G12 | L15: 2.3487078 | M15: -0.054237699 | N15: -1.0414845 | O15: -1.1672071 | P15: -0.90524481 | Q15: -0.45241602 | R15: 3.6188627
... B51: G76 | C51: 1.5290113 | D51: 0.92870646 | E51: 0.92889775 | F51: 1.063885 | G51: 1.1742778 | H51: 1.3184659 | I51: 1.5813436 | K51: G76 | L51: -0.85803831 | M51: -0.32848301 | N51: -1.0484127 | O51: -1.0991697 | P51: -1.2136001 | Q51: -1.1856692 | R51: -0.77456884
B54: Elasticité-revenu 2014 | C54: Milieu Urbain | D54: Milieu Rural | E54: Quintile 1 | F54: Quintile 2 | G54: Quintile 3 | H54: Quintile 4 | I54: Quintile 5 | K54: Elasticité-Prix 2014 | L54: Milieu Urbain | M54: Milieu Rural | N54: Quintile 1 | O54: Quintile 2 | P54: Quintile 3 | Q54: Quintile 4 | R54: Quintile 5
B56: G01 | C56: 0.36530713 | D56: 0.48847987 | E56: 0.7982111 | F56: 0.74147677 | G56: 0.74050471 | H56: 0.63879992 | I56: 0.43448746 | K56: G01 | L56: -0.28246696 | M56: -0.45785425 | N56: -0.82939247 | O56: -0.76121982 | P56: -0.7683554 | Q56: -0.64089235 | R56: -0.30330951
B57: G02 | C57: 0.55947195 | D57: 0.70687058 | E57: 1.013076 | F57: 0.83554143 | G57: 0.81277269 | H57: 0.78206128 | I57: 0.52475543 | K57: G02 | L57: -0.40889506 | M57: -0.58274719 | N57: -1.0642448 | O57: -0.849597 | P57: -0.84737177 | Q57: -0.76268423 | R57: -0.32525271
B58: G03 | C58: 0.29946831 | D58: 0.47000754 | E58: 0.91398683 | F58: 0.78213851 | G58: 0.72513372 | H58: 0.5931703 | I58: 0.25165226 | K58: G03 | L58: -0.14745753 | M58: -0.41885098 | N58: -0.94317387 | O58: -0.79730932 | P58: -0.75574443 | Q58: -0.58333942 | R58: -0.034765247
B59: G04 | C59: 0.55824664 | D59: 0.79746401 | E59: 1.1930253 | F59: 1.0409111 | G59: 1.0143947 | H59: 0.95163026 | I59: 0.52998655 | K59: G04 | L59: -0.51575054 | M59: -0.78383907 | N59: -1.1800697 | O59: -1.0390392 | P59: -1.0221307 | Q59: -0.94775032 | R59: -0.46821677
B60: G05 | C60: 0.92276047 | D60: 0.86084618 | E60: 1.1333234 | F60: 0.8059048 | G60: 0.88706886 | H60: 1.0173309 | I60: 0.9105316 | K60: G05 | L60: -0.58683942 | M60: -0.57777631 | N60: -1.2460603 | O60: -0.83100752 | P60: -0.95837665 | Q60: -0.95824551 | R60: -0.51706234
B61: G06 | C61: 0.30298035 | D61: 0.62281423 | E61: 1.0057887 | F61: 0.96716211 | G61: 0.86617103 | H61: 0.79806216 | I61: 0.34905292 | K61: G06 | L61: -0.10149238 | M61: -0.54799901 | N61: -1.0362901 | O61: -0.97550507 | P61: -0.89721754 | Q61: -0.77683411 | R61: -0.049851921
B62: G07 | C62: 0.33737773 | D62: 0.67410848 | E62: 1.0509162 | F62: 0.81348823 | G62: 0.81107432 | H62: 0.71062404 | I62: 0.4027901 | K62: G07 | L62: 0.075318882 | M62: -0.48543802 | N62: -1.1179506 | O62: -0.83272953 | P62: -0.87144311 | Q62: -0.65842585 | R62: 0.19204568
B63: G08 | C63: 0.87349927 | D63: 1.157327 | E63: 1.5378127 | F63: 1.4378361 | G63: 1.2555693 | H63: 1.1706852 | I63: 0.74056885 | K63: G08 | L63: -0.67655806 | M63: -1.0398525 | N63: -1.5840519 | O63: -1.4319636 | P63: -1.2838947 | Q63: -1.1361192 | R63: -0.52917002
B64: G09 | C64: 0.50285243 | D64: 0.55410888 | E64: 0.74448952 | F64: 0.73620029 | G64: 0.65427143 | H64: 0.82806119 | I64: 0.47639814 | K64: G09 | L64: 0.015787071 | M64: -0.36122616 | N64: -0.82046853 | O64: -0.7586241 | P64: -0.7303849 | Q64: -0.75956949 | R64: 0.16697096
B65: G10 | C65: 1.7082596 | D65: 1.6833269 | E65: 0.84219466 | F65: 1.3296274 | G65: 0.95894257 | H65: 1.47792 | I65: 1.5987202 | K65: G10 | L65: 13.454167 | M65: 15.122709 | N65: -16.69872 | O65: -2.7426861 | P65: -5.8382547 | Q65: 1.4076203 | R65: 13.414228
B66: G11 | C66: 0.31442948 | D66: 0.52441587 | E66: 0.95101405 | F66: 0.76781004 | G66: 0.78281139 | H66: 0.66610422 | I66: 0.28224548 | K66: G11 | L66: 0.13067801 | M66: -0.36475835 | N66: -1.0146868 | O66: -0.78665113 | P66: -0.84306603 | Q66: -0.61298562 | R66: 0.32337312
B67: G12 | C67: 0.36150732 | D67: 0.61159112 | E67: 1.1085086 | F67: 0.88841326 | G67: 0.84301184 | H67: 0.72093089 | I67: 0.34572717 | K67: G12 | L67: 0.15434817 | M67: -0.42236082 | N67: -1.1837836 | O67: -0.90808792 | P67: -0.91018547 | Q67: -0.65799438 | R67: 0.34514305
... B109: G88 | C109: 0.91772632 | D109: 2.371671 | E109: 1.4017971 | F109: 2.2095987 | G109: 2.2336125 | H109: 2.9077043 | I109: 0.66800792 | K109: G88 | L109: 8.0843972 | M109: 13.109751 | N109: -10.881836 | O109: -4.1479136 | P109: -6.0945274 | Q109: -1.8426239 | R109: 10.635648

Sheet Result-Corresp_20-60
B2: Elasticité-revenu 2007 | D2: National-2007 | E2: Milieu-2007- Urbain | F2: Milieu-2007- Rural | G2: Q2007- 1 | H2: Q2007- 2 | I2: Q2007- 3 | J2: Q2007- 4 | K2: Q2007- 5 | M2: Elasticité-Prix 2007 | O2: National-2007 | P2: Milieu-2007- Urbain | Q2: Milieu-2007- Rural | R2: Q2007- 1 | S2: Q2007- 2 | T2: Q2007- 3 | U2: Q2007- 4 | V2: Q2007- 5 | Z2: Elasticité-revenu-2007 | AA2: Elasticité-Prix-2007
Y3: enqres | Z3: elrev | AA3: elpri | AB3: ncn | AC3: enq
B5: A00 | C5: G06 | D5: 0.32290454 | E5: 0.29135356 | F5: 0.66763854 | G5: 1.0434813 | H5: 0.97172687 | I5: 0.95743946 | J5: 0.87822895 | K5: 0.29702477 | M5: A00 | N5: G06 | O5: 0.17161629 | P5: 0.34697665 | Q5: -0.53778923 | R5: -1.0826533 | S5: -0.98575698 | T5: -0.97808213 | U5: -0.82713245 | V5: 0.70441026 | Y5: G06 | Z5: 0.32290454 | AA5: 0.17161629 | AB5: A00 | AC5: G06 | AD5: =IF(Y5=AC5,0,1) -> 0
B6: A00 | C6: G08 | D6: 0.77584097 | E6: 0.75371663 | F6: 1.1722626 | G6: 1.4667909 | H6: 1.515512 | I6: 1.2436673 | J6: 1.1115554 | K6: 0.60912714 | M6: A00 | N6: G08 | O6: -0.025802854 | P6: 0.14703017 | Q6: -0.92813828 | R6: -1.5837274 | S6: -1.5246309 | T6: -1.2722533 | U6: -1.023211 | V6: 0.42588639 | Y6: G08 | Z6: 0.77584097 | AA6: -0.025802854 | AB6: A00 | AC6: G08 | AD6: =IF(Y6=AC6,0,1) -> 0
B8: B05 | C8: G05 | D8: 0.8779609 | E8: 0.79672229 | F8: 0.90588528 | G8: 0.90924878 | H8: 0.68396292 | I8: 0.81859974 | J8: 0.79912442 | K8: 0.80723397 | M8: B05 | N8: G05 | O8: 0.42429217 | P8: 0.53493309 | Q8: -0.29869044 | R8: -1.0853139 | S8: -0.73997014 | T8: -0.88314248 | U8: -0.63121097 | V8: 0.92646252 | Y8: G05 | Z8: 0.8779609 | AA8: 0.42429217 | AB8: B05 | AC8: G05 | AD8: =IF(Y8=AC8,0,1) -> 0
B10: D01 | C10: G01 | D10: 0.286173 | E10: 0.29891619 | F10: 0.45614943 | G10: 0.80344403 | H10: 0.81076652 | I10: 0.77423129 | J10: 0.66247003 | K10: 0.32521352 | M10: D01 | N10: G01 | O10: -0.035906658 | P10: 0.034785149 | Q10: -0.40851501 | R10: -0.84206145 | S10: -0.83376801 | T10: -0.80038434 | U10: -0.65149517 | V10: 0.22125846 | Y10: G01 | Z10: 0.286173 | AA10: -0.035906658 | AB10: D01 | AC10: G01 | AD10: =IF(Y10=AC10,0,1) -> 0
B11: D01 | C11: G02 | D11: 0.67700508 | E11: 0.59546444 | F11: 0.80568398 | G11: 1.0235349 | H11: 1.1137533 | I11: 0.84743054 | J11: 0.80169306 | K11: 0.5405861 | M11: D01 | N11: G02 | O11: -0.08066114 | P11: 0.02350758 | Q11: -0.54123327 | R11: -1.1117996 | S11: -1.1323451 | T11: -0.87971109 | U11: -0.73656943 | V11: 0.30362711 | Y11: G02 | Z11: 0.67700508 | AA11: -0.08066114 | AB11: D01 | AC11: G02 | AD11: =IF(Y11=AC11,0,1) -> 0
B12: D01 | C12: G03 | D12: 0.30588087 | E12: 0.31269045 | F12: 0.60997196 | G12: 0.95972233 | H12: 0.99678347 | I12: 0.87863885 | J12: 0.80661268 | K12: 0.25849365 | M12: D01 | N12: G03 | O12: 0.22161235 | P12: 0.41891883 | Q12: -0.48697093 | R12: -1.0072317 | S12: -1.0106001 | T12: -0.90357254 | U12: -0.75415213 | V12: 0.79853211 | Y12: G03 | Z12: 0.30588087 | AA12: 0.22161235 | AB12: D01 | AC12: G03 | AD12: =IF(Y12=AC12,0,1) -> 0
B13: D01 | C13: G04 | D13: 0.62079053 | E13: 0.58936227 | F13: 0.95359603 | G13: 1.03195 | H13: 1.147645 | I13: 1.1527621 | J13: 0.99849025 | K13: 0.53480866 | M13: D01 | N13: G04 | O13: -0.46205597 | P13: -0.39425179 | Q13: -0.90215709 | R13: -1.0494462 | S13: -1.134034 | T13: -1.1407437 | U13: -0.97872266 | V13: -0.2727138 | Y13: G04 | Z13: 0.62079053 | AA13: -0.46205597 | AB13: D01 | AC13: G04 | AD13: =IF(Y13=AC13,0,1) -> 0
B14: D01 | C14: G07 | D14: 0.33737961 | E14: 0.30043915 | F14: 0.64974666 | G14: 0.85168512 | H14: 0.91655754 | I14: 0.91605225 | J14: 0.72899064 | K14: 0.35605862 | M14: D01 | N14: G07 | O14: 1.0277511 | P14: 1.3886353 | Q14: -0.24141939 | R14: -0.9813548 | S14: -0.95247102 | T14: -0.968923 | U14: -0.58036338 | V14: 2.3865239 | Y14: G07 | Z14: 0.33737961 | AA14: 1.0277511 | AB14: D01 | AC14: G07 | AD14: =IF(Y14=AC14,0,1) -> 0
B15: D01 | C15: G09 | D15: 0.30319767 | E15: 0.40796649 | F15: 0.44341527 | G15: 0.86699336 | H15: 0.88231311 | I15: 0.63321431 | J15: 0.73034553 | K15: 0.50918648 | M15: D01 | N15: G09 | O15: 0.86976005 | P15: 1.3647913 | Q15: -0.17846266 | R15: -0.94566499 | S15: -0.91226993 | T15: -0.6820038 | U15: -0.59170928 | V15: 2.1738799 | Y15: G09 | Z15: 0.30319767 | AA15: 0.86976005 | AB15: D01 | AC15: G09 | AD15: =IF(Y15=AC15,0,1) -> 0
B16: D01 | C16: G10 | D16: 1.8999013 | E16: 1.6492917 | F16: 0.94757217 | G16: 3.0435244 | H16: 0.98947822 | I16: 1.5380999 | J16: 0.86530395 | K16: 1.3847732 | M16: D01 | N16: G10 | O16: 52.698344 | P16: 46.336445 | Q16: 50.963266 | R16: -32.298107 | S16: -5.5408237 | T16: -5.9620374 | U16: 8.6465939 | V16: 48.684165 | Y16: G10 | Z16: 1.8999013 | AA16: 52.698344 | AB16: D01 | AC16: G10 | AD16: =IF(Y16=AC16,0,1) -> 0
B17: D01 | C17: G11 | D17: 0.25882117 | E17: 0.28828687 | F17: 0.49642423 | G17: 0.85594296 | H17: 0.86300563 | I17: 0.67596322 | J17: 0.70618906 | K17: 0.26856503 | M17: D01 | N17: G11 | O17: 1.0602564 | P17: 1.5867304 | Q17: -0.17517982 | R17: -0.95772975 | S17: -0.89848435 | T17: -0.73099271 | U17: -0.56050034 | V17: 2.520365 | Y17: G11 | Z17: 0.25882117 | AA17: 1.0602564 | AB17: D01 | AC17: G11 | AD17: =IF(Y17=AC17,0,1) -> 0
B18: D01 | C18: G12 | D18: 0.31277433 | E18: 0.35487166 | F18: 0.53339468 | G18: 0.89405974 | H18: 1.1195783 | I18: 0.82939494 | J18: 0.66785942 | K18: 0.35760701 | M18: D01 | N18: G12 | O18: 1.6097312 | P18: 2.3487078 | Q18: -0.054237699 | R18: -1.0414845 | S18: -1.1672071 | T18: -0.90524481 | U18: -0.45241602 | V18: 3.6188627 | Y18: G12 | Z18: 0.31277433 | AA18: 1.6097312 | AB18: D01 | AC18: G12 | AD18: =IF(Y18=AC18,0,1) -> 0
... B59: OP0 | C59: G74 | D59: 2.2584477 | E59: 2.1337508 | F59: 1.1517164 | G59: 1.86411 | H59: 1.7562953 | I59: 2.3936647 | J59: 1.4123889 | K59: 1.6961797 | M59: OP0 | N59: G74 | O59: 1.6708974 | P59: 1.5916533 | Q59: 1.273937 | R59: -4.0306218 | S59: -2.0376922 | T59: -2.7103825 | U59: -0.62936313 | V59: 1.829451 | Y59: G74 | Z59: 2.2584477 | AA59: 1.6708974 | AB59: OP0 | AC59: G74 | AD59: =IF(Y59=AC59,0,1) -> 0
B62: Elasticité-revenu 2014 | D62: National-2014 | E62: Milieu-2014- Urbain | F62: Milieu-2014- Rural | G62: Q2014- 1 | H62: Q2014- 2 | I62: Q2014- 3 | J62: Q2014- 4 | K62: Q2014- 5 | M62: Elasticité-Prix 2014 | O62: National-2014 | P62: Milieu-2014- Urbain | Q62: Milieu-2014- Rural | R62: Q2014- 1 | S62: Q2014- 2 | T62: Q2014- 3 | U62: Q2014- 4 | V62: Q2014- 5 | Z62: Elasticité-revenu-2014 | AA62: Elasticité-Prix-2014
Y63: enqres | Z63: elrev | AA63: elpri | AB63: ncn | AC63: enq
B65: A00 | C65: G06 | D65: 0.30119517 | E65: 0.30298035 | F65: 0.62281423 | G65: 1.0057887 | H65: 0.96716211 | I65: 0.86617103 | J65: 0.79806216 | K65: 0.34905292 | M65: A00 | N65: G06 | O65: -0.1188808 | P65: -0.10149238 | Q65: -0.54799901 | R65: -1.0362901 | S65: -0.97550507 | T65: -0.89721754 | U65: -0.77683411 | V65: -0.049851921 | Y65: G06 | Z65: 0.30119517 | AA65: -0.1188808 | AB65: A00 | AC65: G06 | AD65: =IF(Y65=AC65,0,1) -> 0
B66: A00 | C66: G08 | D66: 0.85898116 | E66: 0.87349927 | F66: 1.157327 | G66: 1.5378127 | H66: 1.4378361 | I66: 1.2555693 | J66: 1.1706852 | K66: 0.74056885 | M66: A00 | N66: G08 | O66: -0.66002588 | P66: -0.67655806 | Q66: -1.0398525 | R66: -1.5840519 | S66: -1.4319636 | T66: -1.2838947 | U66: -1.1361192 | V66: -0.52917002 | Y66: G08 | Z66: 0.85898116 | AA66: -0.66002588 | AB66: A00 | AC66: G08 | AD66: =IF(Y66=AC66,0,1) -> 0
B68: B05 | C68: G05 | D68: 0.94808612 | E68: 0.92276047 | F68: 0.86084618 | G68: 1.1333234 | H68: 0.8059048 | I68: 0.88706886 | J68: 1.0173309 | K68: 0.9105316 | M68: B05 | N68: G05 | O68: -0.5677808 | P68: -0.58683942 | Q68: -0.57777631 | R68: -1.2460603 | S68: -0.83100752 | T68: -0.95837665 | U68: -0.95824551 | V68: -0.51706234 | Y68: G05 | Z68: 0.94808612 | AA68: -0.5677808 | AB68: B05 | AC68: G05 | AD68: =IF(Y68=AC68,0,1) -> 0
B70: D01 | C70: G01 | D70: 0.35974102 | E70: 0.36530713 | F70: 0.48847987 | G70: 0.7982111 | H70: 0.74147677 | I70: 0.74050471 | J70: 0.63879992 | K70: 0.43448746 | M70: D01 | N70: G01 | O70: -0.27914102 | P70: -0.28246696 | Q70: -0.45785425 | R70: -0.82939247 | S70: -0.76121982 | T70: -0.7683554 | U70: -0.64089235 | V70: -0.30330951 | Y70: G01 | Z70: 0.35974102 | AA70: -0.27914102 | AB70: D01 | AC70: G01 | AD70: =IF(Y70=AC70,0,1) -> 0
B71: D01 | C71: G02 | D71: 0.61698448 | E71: 0.55947195 | F71: 0.70687058 | G71: 1.013076 | H71: 0.83554143 | I71: 0.81277269 | J71: 0.78206128 | K71: 0.52475543 | M71: D01 | N71: G02 | O71: -0.44643021 | P71: -0.40889506 | Q71: -0.58274719 | R71: -1.0642448 | S71: -0.849597 | T71: -0.84737177 | U71: -0.76268423 | V71: -0.32525271 | Y71: G02 | Z71: 0.61698448 | AA71: -0.44643021 | AB71: D01 | AC71: G02 | AD71: =IF(Y71=AC71,0,1) -> 0
B72: D01 | C72: G03 | D72: 0.27123123 | E72: 0.29946831 | F72: 0.47000754 | G72: 0.91398683 | H72: 0.78213851 | I72: 0.72513372 | J72: 0.5931703 | K72: 0.25165226 | M72: D01 | N72: G03 | O72: -0.13408186 | P72: -0.14745753 | Q72: -0.41885098 | R72: -0.94317387 | S72: -0.79730932 | T72: -0.75574443 | U72: -0.58333942 | V72: -0.034765247 | Y72: G03 | Z72: 0.27123123 | AA72: -0.13408186 | AB72: D01 | AC72: G03 | AD72: =IF(Y72=AC72,0,1) -> 0
B73: D01 | C73: G04 | D73: 0.55327874 | E73: 0.55824664 | F73: 0.79746401 | G73: 1.1930253 | H73: 1.0409111 | I73: 1.0143947 | J73: 0.95163026 | K73: 0.52998655 | M73: D01 | N73: G04 | O73: -0.51349793 | P73: -0.51575054 | Q73: -0.78383907 | R73: -1.1800697 | S73: -1.0390392 | T73: -1.0221307 | U73: -0.94775032 | V73: -0.46821677 | Y73: G04 | Z73: 0.55327874 | AA73: -0.51349793 | AB73: D01 | AC73: G04 | AD73: =IF(Y73=AC73,0,1) -> 0
B74: D01 | C74: G07 | D74: 0.35025372 | E74: 0.33737773 | F74: 0.67410848 | G74: 1.0509162 | H74: 0.81348823 | I74: 0.81107432 | J74: 0.71062404 | K74: 0.4027901 | M74: D01 | N74: G07 | O74: 0.041377104 | P74: 0.075318882 | Q74: -0.48543802 | R74: -1.1179506 | S74: -0.83272953 | T74: -0.87144311 | U74: -0.65842585 | V74: 0.19204568 | Y74: G07 | Z74: 0.35025372 | AA74: 0.041377104 | AB74: D01 | AC74: G07 | AD74: =IF(Y74=AC74,0,1) -> 0
B75: D01 | C75: G09 | D75: 0.40668998 | E75: 0.50285243 | F75: 0.55410888 | G75: 0.74448952 | H75: 0.73620029 | I75: 0.65427143 | J75: 0.82806119 | K75: 0.47639814 | M75: D01 | N75: G09 | O75: 0.048511763 | P75: 0.015787071 | Q75: -0.36122616 | R75: -0.82046853 | S75: -0.7586241 | T75: -0.7303849 | U75: -0.75956949 | V75: 0.16697096 | Y75: G09 | Z75: 0.40668998 | AA75: 0.048511763 | AB75: D01 | AC75: G09 | AD75: =IF(Y75=AC75,0,1) -> 0
B76: D01 | C76: G10 | D76: 1.7879749 | E76: 1.7082596 | F76: 1.6833269 | G76: 0.84219466 | H76: 1.3296274 | I76: 0.95894257 | J76: 1.47792 | K76: 1.5987202 | M76: D01 | N76: G10 | O76: 16.384473 | P76: 13.454167 | Q76: 15.122709 | R76: -16.69872 | S76: -2.7426861 | T76: -5.8382547 | U76: 1.4076203 | V76: 13.414228 | Y76: G10 | Z76: 1.7879749 | AA76: 16.384473 | AB76: D01 | AC76: G10 | AD76: =IF(Y76=AC76,0,1) -> 0
B77: D01 | C77: G11 | D77: 0.27202778 | E77: 0.31442948 | F77: 0.52441587 | G77: 0.95101405 | H77: 0.76781004 | I77: 0.78281139 | J77: 0.66610422 | K77: 0.28224548 | M77: D01 | N77: G11 | O77: 0.11480337 | P77: 0.13067801 | Q77: -0.36475835 | R77: -1.0146868 | S77: -0.78665113 | T77: -0.84306603 | U77: -0.61298562 | V77: 0.32337312 | Y77: G11 | Z77: 0.27202778 | AA77: 0.11480337 | AB77: D01 | AC77: G11 | AD77: =IF(Y77=AC77,0,1) -> 0
B78: D01 | C78: G12 | D78: 0.32178768 | E78: 0.36150732 | F78: 0.61159112 | G78: 1.1085086 | H78: 0.88841326 | I78: 0.84301184 | J78: 0.72093089 | K78: 0.34572717 | M78: D01 | N78: G12 | O78: 0.12890644 | P78: 0.15434817 | Q78: -0.42236082 | R78: -1.1837836 | S78: -0.90808792 | T78: -0.91018547 | U78: -0.65799438 | V78: 0.34514305 | Y78: G12 | Z78: 0.32178768 | AA78: 0.12890644 | AB78: D01 | AC78: G12 | AD78: =IF(Y78=AC78,0,1) -> 0
... B119: OP0 | C119: G74 | D119: 3.2095542 | E119: 2.9853147 | F119: 3.2064219 | G119: 1.4642773 | H119: 1.5066361 | I119: 1.8921865 | J119: 1.5695436 | K119: 2.4040476 | M119: OP0 | N119: G74 | O119: -2.6343983 | P119: -2.5213041 | Q119: -2.5151607 | R119: -2.5441397 | S119: -1.6129959 | T119: -2.1526762 | U119: -1.4233731 | V119: -2.0383933 | Y119: G74 | Z119: 3.2095542 | AA119: -2.6343983 | AB119: OP0 | AC119: G74 | AD119: =IF(Y119=AC119,0,1) -> 0

Sheet Res global
B2: Elas-revenu 2007 | D2: National | E2: URB | F2: RUR | G2: Q1 | H2: Q2 | I2: Q3 | J2: Q4 | K2: Q5 | M2: Elas-Prix 2007 | O2: National | P2: URB | Q2: RUR | R2: Q1 | S2: Q2 | T2: Q3 | U2: Q4 | V2: Q5 | X2: Elas-revenu 2007 | Y2: National | Z2: M URB | AA2: M RUR | AB2: Q- 1 | AC2: Q- 2 | AD2: Q- 3 | AE2: Q- 4 | AF2: Q- 5 | AI2: Elas-Prix 2007 | AJ2: National | AK2: M URB | AL2: M RUR | AM2: Q- 1 | AN2: Q- 2 | AO2: Q- 3 | AP2: Q- 4 | AQ2: Q- 5
B4: =X4 -> A00 | D4: =Y4 -> 0.61826534 | E4: =Z4 -> 0.60469571 | F4: =AA4 -> 0.86485086 | G4: =AB4 -> 1.0594818 | H4: =AC4 -> 1.0043047 | I4: =AD4 -> 0.76665567 | J4: =AE4 -> 0.8744419 | K4: =AF4 -> 0.50513122 | M4: =AI4 -> A00 | O4: =AJ4 -> -0.65922937 | P4: =AK4 -> -0.6378944 | Q4: =AL4 -> -0.93109298 | R4: =AM4 -> -1.0635157 | S4: =AN4 -> -1.0236482 | T4: =AO4 -> -0.84829327 | U4: =AP4 -> -0.92918623 | V4: =AQ4 -> -0.46800237 | X4: A00 | Y4: 0.61826534 | Z4: 0.60469571 | AA4: 0.86485086 | AB4: 1.0594818 | AC4: 1.0043047 | AD4: 0.76665567 | AE4: 0.8744419 | AF4: 0.50513122 | AI4: A00 | AJ4: -0.65922937 | AK4: -0.6378944 | AL4: -0.93109298 | AM4: -1.0635157 | AN4: -1.0236482 | AO4: -0.84829327 | AP4: -0.92918623 | AQ4: -0.46800237
B5: A00 | C5: G06 | D5: 0.32290454 | E5: 0.29135356 | F5: 0.66763854 | G5: 1.0434813 | H5: 0.97172687 | I5: 0.95743946 | J5: 0.87822895 | K5: 0.29702477 | M5: A00 | N5: G06 | O5: 0.17161629 | P5: 0.34697665 | Q5: -0.53778923 | R5: -1.0826533 | S5: -0.98575698 | T5: -0.97808213 | U5: -0.82713245 | V5: 0.70441026
B6: A00 | C6: G08 | D6: 0.77584097 | E6: 0.75371663 | F6: 1.1722626 | G6: 1.4667909 | H6: 1.515512 | I6: 1.2436673 | J6: 1.1115554 | K6: 0.60912714 | M6: A00 | N6: G08 | O6: -0.025802854 | P6: 0.14703017 | Q6: -0.92813828 | R6: -1.5837274 | S6: -1.5246309 | T6: -1.2722533 | U6: -1.023211 | V6: 0.42588639
B7: =X7 -> B05 | D7: =Y7 -> 0.87796584 | E7: =Z7 -> 0.79672414 | F7: =AA7 -> 0.90588147 | G7: =AB7 -> 1.2082265 | H7: =AC7 -> 0.91454487 | I7: =AD7 -> 1.0165672 | J7: =AE7 -> 0.91256775 | K7: =AF7 -> 0.80714419 | M7: =AI7 -> B05 | O7: =AJ7 -> -0.9547666 | P7: =AK7 -> -0.80650356 | Q7: =AL7 -> -1.7090431 | R7: =AM7 -> -1.4068859 | S7: =AN7 -> -1.1973496 | T7: =AO7 -> -1.6986777 | U7: =AP7 -> -1.3728091 | V7: =AQ7 -> -0.15907545 | X7: B05 | Y7: 0.87796584 | Z7: 0.79672414 | AA7: 0.90588147 | AB7: 1.2082265 | AC7: 0.91454487 | AD7: 1.0165672 | AE7: 0.91256775 | AF7: 0.80714419 | AI7: B05 | AJ7: -0.9547666 | AK7: -0.80650356 | AL7: -1.7090431 | AM7: -1.4068859 | AN7: -1.1973496 | AO7: -1.6986777 | AP7: -1.3728091 | AQ7: -0.15907545
B8: B05 | C8: G05 | D8: 0.8779609 | E8: 0.79672229 | F8: 0.90588528 | G8: 0.90924878 | H8: 0.68396292 | I8: 0.81859974 | J8: 0.79912442 | K8: 0.80723397 | M8: B05 | N8: G05 | O8: 0.42429217 | P8: 0.53493309 | Q8: -0.29869044 | R8: -1.0853139 | S8: -0.73997014 | T8: -0.88314248 | U8: -0.63121097 | V8: 0.92646252
B9: =X9 -> C00 | D9: =Y9 -> 0.31282399 | E9: =Z9 -> 0.35494691 | F9: =AA9 -> 0.53344062 | G9: =AB9 -> 0.90076311 | H9: =AC9 -> 0.8008729 | I9: =AD9 -> 0.65372805 | J9: =AE9 -> 0.58068732 | K9: =AF9 -> 0.21217624 | M9: =AI9 -> C00 | O9: =AJ9 -> -1.8262868 | P9: =AK9 -> -0.55686678 | Q9: =AL9 -> -9.2478947 | R9: =AM9 -> -3.5359134 | S9: =AN9 -> -4.7544032 | T9: =AO9 -> -11.391573 | U9: =AP9 -> -9.2650108 | V9: =AQ9 -> 19.183367 | X9: C00 | Y9: 0.31282399 | Z9: 0.35494691 | AA9: 0.53344062 | AB9: 0.90076311 | AC9: 0.8008729 | AD9: 0.65372805 | AE9: 0.58068732 | AF9: 0.21217624 | AI9: C00 | AJ9: -1.8262868 | AK9: -0.55686678 | AL9: -9.2478947 | AM9: -3.5359134 | AN9: -4.7544032 | AO9: -11.391573 | AP9: -9.2650108 | AQ9: 19.183367
B10: =X10 -> D01 | D10: =Y10 -> 0.43756838 | E10: =Z10 -> 0.44734105 | F10: =AA10 -> 0.66142194 | G10: =AB10 -> 0.95310351 | H10: =AC10 -> 0.92861148 | I10: =AD10 -> 0.59394059 | J10: =AE10 -> 0.78101543 | K10: =AF10 -> 0.32079717 | M10: =AI10 -> D01 | O10: =AJ10 -> -0.50471887 | P10: =AK10 -> -0.50357252 | Q10: =AL10 -> -0.75721682 | R10: =AM10 -> -0.97417384 | S10: =AN10 -> -0.95913487 | T10: =AO10 -> -0.69528037 | U10: =AP10 -> -0.84897587 | V10: =AQ10 -> -0.31861566 | X10: D01 | Y10: 0.43756838 | Z10: 0.44734105 | AA10: 0.66142194 | AB10: 0.95310351 | AC10: 0.92861148 | AD10: 0.59394059 | AE10: 0.78101543 | AF10: 0.32079717 | AI10: D01 | AJ10: -0.50471887 | AK10: -0.50357252 | AL10: -0.75721682 | AM10: -0.97417384 | AN10: -0.95913487 | AO10: -0.69528037 | AP10: -0.84897587 | AQ10: -0.31861566
B11: D01 | C11: G01 | D11: 0.286173 | E11: 0.29891619 | F11: 0.45614943 | G11: 0.80344403 | H11: 0.81076652 | I11: 0.77423129 | J11: 0.66247003 | K11: 0.32521352 | M11: D01 | N11: G01 | O11: -0.035906658 | P11: 0.034785149 | Q11: -0.40851501 | R11: -0.84206145 | S11: -0.83376801 | T11: -0.80038434 | U11: -0.65149517 | V11: 0.22125846
B12: D01 | C12: G02 | D12: 0.67700508 | E12: 0.59546444 | F12: 0.80568398 | G12: 1.0235349 | H12: 1.1137533 | I12: 0.84743054 | J12: 0.80169306 | K12: 0.5405861 | M12: D01 | N12: G02 | O12: -0.08066114 | P12: 0.02350758 | Q12: -0.54123327 | R12: -1.1117996 | S12: -1.1323451 | T12: -0.87971109 | U12: -0.73656943 | V12: 0.30362711
B13: D01 | C13: G03 | D13: 0.30588087 | E13: 0.31269045 | F13: 0.60997196 | G13: 0.95972233 | H13: 0.99678347 | I13: 0.87863885 | J13: 0.80661268 | K13: 0.25849365 | M13: D01 | N13: G03 | O13: 0.22161235 | P13: 0.41891883 | Q13: -0.48697093 | R13: -1.0072317 | S13: -1.0106001 | T13: -0.90357254 | U13: -0.75415213 | V13: 0.79853211
B14: D01 | C14: G04 | D14: 0.62079053 | E14: 0.58936227 | F14: 0.95359603 | G14: 1.03195 | H14: 1.147645 | I14: 1.1527621 | J14: 0.99849025 | K14: 0.53480866 | M14: D01 | N14: G04 | O14: -0.46205597 | P14: -0.39425179 | Q14: -0.90215709 | R14: -1.0494462 | S14: -1.134034 | T14: -1.1407437 | U14: -0.97872266 | V14: -0.2727138
B15: D01 | C15: G07 | D15: 0.33737961 | E15: 0.30043915 | F15: 0.64974666 | G15: 0.85168512 | H15: 0.91655754 | I15: 0.91605225 | J15: 0.72899064 | K15: 0.35605862 | M15: D01 | N15: G07 | O15: 1.0277511 | P15: 1.3886353 | Q15: -0.24141939 | R15: -0.9813548 | S15: -0.95247102 | T15: -0.968923 | U15: -0.58036338 | V15: 2.3865239
B16: D01 | C16: G09 | D16: 0.30319767 | E16: 0.40796649 | F16: 0.44341527 | G16: 0.86699336 | H16: 0.88231311 | I16: 0.63321431 | J16: 0.73034553 | K16: 0.50918648 | M16: D01 | N16: G09 | O16: 0.86976005 | P16: 1.3647913 | Q16: -0.17846266 | R16: -0.94566499 | S16: -0.91226993 | T16: -0.6820038 | U16: -0.59170928 | V16: 2.1738799
B17: D01 | C17: G10 | D17: 1.8999013 | E17: 1.6492917 | F17: 0.94757217 | G17: 3.0435244 | H17: 0.98947822 | I17: 1.5380999 | J17: 0.86530395 | K17: 1.3847732 | M17: D01 | N17: G10 | O17: 52.698344 | P17: 46.336445 | Q17: 50.963266 | R17: -32.298107 | S17: -5.5408237 | T17: -5.9620374 | U17: 8.6465939 | V17: 48.684165
B18: D01 | C18: G11 | D18: 0.25882117 | E18: 0.28828687 | F18: 0.49642423 | G18: 0.85594296 | H18: 0.86300563 | I18: 0.67596322 | J18: 0.70618906 | K18: 0.26856503 | M18: D01 | N18: G11 | O18: 1.0602564 | P18: 1.5867304 | Q18: -0.17517982 | R18: -0.95772975 | S18: -0.89848435 | T18: -0.73099271 | U18: -0.56050034 | V18: 2.520365
B19: D01 | C19: G12 | D19: 0.31277433 | E19: 0.35487166 | F19: 0.53339468 | G19: 0.89405974 | H19: 1.1195783 | I19: 0.82939494 | J19: 0.66785942 | K19: 0.35760701 | M19: D01 | N19: G12 | O19: 1.6097312 | P19: 2.3487078 | Q19: -0.054237699 | R19: -1.0414845 | S19: -1.1672071 | T19: -0.90524481 | U19: -0.45241602 | V19: 3.6188627
B20: D01 | C20: G13 | D20: 1.6656286 | E20: 1.4690389 | F20: 1.838552 | G20: 2.2875789 | H20: 1.5425068 | I20: 0.78620627 | J20: 1.2147697 | K20: 1.2351589 | M20: D01 | N20: G13 | O20: 4.6926213 | P20: 4.5571061 | Q20: 2.095343 | R20: -4.9692007 | S20: -2.007503 | T20: -1.2937805 | U20: -0.27633582 | V20: 4.9551761
B21: =X21 -> D02 | D21: =Y21 -> 1.1418904 | E21: =Z21 -> 1.1283871 | F21: =AA21 -> 1.1208592 | G21: =AB21 -> 1.4951245 | H21: =AC21 -> 1.5885187 | I21: =AD21 -> 1.2502422 | J21: =AE21 -> 1.3739846 | K21: =AF21 -> 0.92753509 | M21: =AI21 -> D02 | O21: =AJ21 -> -1.1614936 | P21: =AK21 -> -1.1252485 | Q21: =AL21 -> -1.3496387 | R21: =AM21 -> -1.5798406 | S21: =AN21 -> -1.6842183 | T21: =AO21 -> -1.5122862 | U21: =AP21 -> -1.5141049 | V21: =AQ21 -> -0.73800221 | X21: D02 | Y21: 1.1418904 | Z21: 1.1283871 | AA21: 1.1208592 | AB21: 1.4951245 | AC21: 1.5885187 | AD21: 1.2502422 | AE21: 1.3739846 | AF21: 0.92753509 | AI21: D02 | AJ21: -1.1614936 | AK21: -1.1252485 | AL21: -1.3496387 | AM21: -1.5798406 | AN21: -1.6842183 | AO21: -1.5122862 | AP21: -1.5141049 | AQ21: -0.73800221
B22: D02 | C22: G21 | D22: 1.226792 | E22: 1.2175484 | F22: 1.06232 | G22: 1.4553668 | H22: 1.456649 | I22: 1.0964462 | J22: 1.1540251 | K22: 1.0272684 | M22: D02 | N22: G21 | O22: 0.22821303 | P22: 0.3389318 | Q22: -0.46567642 | R22: -1.7664923 | S22: -1.5213751 | T22: -1.1750434 | U22: -0.95698864 | V22: 0.66215571
B23: D02 | C23: G22 | D23: 0.76226492 | E23: 0.78280331 | F23: 0.74665054 | G23: 1.1210442 | H23: 1.0837143 | I23: 1.1024287 | J23: 0.91838228 | K23: 0.99203305 | M23: D02 | N23: G22 | O23: 2.6263392 | P23: 3.113839 | Q23: 0.42685845 | R23: -1.4851588 | S23: -1.1788307 | T23: -1.2323274 | U23: -0.49582593 | V23: 4.7639043
B24: D02 | C24: G23 | D24: 0.65022936 | E24: 0.65210328 | F24: 0.8366482 | G24: 1.232998 | H24: 1.3443676 | I24: 1.247135 | J24: 1.0096389 | K24: 0.35771622 | M24: D02 | N24: G23 | O24: 28.993825 | P24: 34.63279 | Q24: 8.7644317 | R24: -5.9663506 | S24: -2.5294652 | T24: -2.7163083 | U24: 2.9464527 | V24: 37.512895
B25: D02 | C25: G24 | D25: 0.73600409 | E25: 0.71218435 | F25: 1.0382529 | G25: 1.0522529 | H25: 1.1410341 | I25: 1.1748052 | J25: 1.157369 | K25: 0.60692784 | M25: D02 | N25: G24 | O25: 6.2517149 | P25: 7.4680778 | Q25: 1.2964691 | R25: -2.1683529 | S25: -1.2637272 | T25: -1.497289 | U25: -0.36924672 | V25: 9.3724988
B26: D02 | C26: G25 | D26: 3.0277544 | E26: 3.1858443 | F26: 1.2954752 | G26: 1.6437107 | H26: 0.93463932 | I26: 2.4428705 | J26: 1.0549343 | K26: 3.0333376 | M26: D02 | N26: G25 | O26: 15.93297 | P26: 16.561632 | Q26: 7.0768729 | R26: -6.1084173 | S26: -1.8921638 | T26: -3.6668104 | U26: 2.1333577 | V26: 16.665628
B27: D02 | C27: G26 | D27: 0.57503025 | E27: 0.49600592 | F27: 0.68894591 | G27: 1.3709994 | H27: 1.1922324 | I27: 1.4155464 | J27: 0.69328093 | K27: 0.57937887 | M27: D02 | N27: G26 | O27: 17.923416 | P27: 18.739476 | Q27: 7.5117032 | R27: -4.0111926 | S27: -1.9569514 | T27: -2.2808003 | U27: 0.8258438 | V27: 31.838036
B28: D02 | C28: G27 | D28: 1.5930854 | E28: 1.3003201 | F28: 2.4432315 | G28: 1.0028729 | H28: 1.0133237 | I28: 1.7778183 | J28: 1.1998219 | K28: 1.0148415 | M28: D02 | N28: G27 | O28: 10.894545 | P28: 9.8807869 | Q28: 8.0101202 | R28: -8.159867 | S28: -2.7606886 | T28: -2.9422195 | U28: 0.64132557 | V28: 10.352949
B29: D02 | C29: G28 | D29: 0.91409779 | E29: 0.87573585 | F29: 0.99200805 | G29: 0.98526244 | H29: 1.1513008 | I29: 1.2547095 | J29: 0.94194096 | K29: 0.80994059 | M29: D02 | N29: G28 | O29: 2.2163988 | P29: 2.5165753 | Q29: 0.24955811 | R29: -1.5062086 | S29: -1.2703698 | T29: -1.3946289 | U29: -0.52532967 | V29: 3.3209133
B30: =X30 -> D03 | D30: =Y30 -> 0.68536701 | E30: =Z30 -> 0.6264359 | F30: =AA30 -> 0.87446462 | G30: =AB30 -> 1.1507789 | H30: =AC30 -> 0.80882062 | I30: =AD30 -> 1.1343109 | J30: =AE30 -> 1.0577608 | K30: =AF30 -> 0.51212139 | M30: =AI30 -> D03 | O30: =AJ30 -> -0.71910734 | P30: =AK30 -> -0.63905515 | Q30: =AL30 -> -1.0992216 | R30: =AM30 -> -1.2096503 | S30: =AN30 -> -0.90050697 | T30: =AO30 -> -1.3299005 | U30: =AP30 -> -1.1978416 | V30: =AQ30 -> -0.29225831 | X30: D03 | Y30: 0.68536701 | Z30: 0.6264359 | AA30: 0.87446462 | AB30: 1.1507789 | AC30: 0.80882062 | AD30: 1.1343109 | AE30: 1.0577608 | AF30: 0.51212139 | AI30: D03 | AJ30: -0.71910734 | AK30: -0.63905515 | AL30: -1.0992216 | AM30: -1.2096503 | AN30: -0.90050697 | AO30: -1.3299005 | AP30: -1.1978416 | AQ30: -0.29225831
B31: D03 | C31: G51 | D31: 0.74455208 | E31: 0.61122995 | F31: 0.8228406 | G31: 1.2215837 | H31: 1.0569994 | I31: 0.89639419 | J31: 0.91100416 | K31: 0.73284321 | M31: D03 | N31: G51 | O31: 0.095614468 | P31: 0.19020669 | Q31: -0.31872896 | R31: -1.3352118 | S31: -1.0838765 | T31: -0.93453266 | U31: -0.81210852 | V31: 0.52444091
B32: =X32 -> D04 | D32: =Y32 -> 2.4513963 | E32: =Z32 -> 2.3757601 | F32: =AA32 -> 2.2444593 | G32: =AB32 -> 1.3373422 | H32: =AC32 -> 1.2700428 | I32: =AD32 -> 1.7316479 | J32: =AE32 -> 1.4080487 | K32: =AF32 -> 2.1603917 | M32: =AI32 -> D04 | O32: =AJ32 -> -2.2695337 | P32: =AK32 -> -2.1784965 | Q32: =AL32 -> -2.3074986 | R32: =AM32 -> -1.4377822 | S32: =AN32 -> -1.4040662 | T32: =AO32 -> -1.9807798 | U32: =AP32 -> -1.5668546 | V32: =AQ32 -> -1.862326 | X32: D04 | Y32: 2.4513963 | Z32: 2.3757601 | AA32: 2.2444593 | AB32: 1.3373422 | AC32: 1.2700428 | AD32: 1.7316479 | AE32: 1.4080487 | AF32: 2.1603917 | AI32: D04 | AJ32: -2.2695337 | AK32: -2.1784965 | AL32: -2.3074986 | AM32: -1.4377822 | AN32: -1.4040662 | AO32: -1.9807798 | AP32: -1.5668546 | AQ32: -1.862326
B33: D04 | C33: G42 | D33: 0.70307498 | E33: 0.77456011 | F33: 0.882663 | G33: 1.2887196 | H33: 1.0482265 | I33: 1.1719869 | J33: 0.98415893 | K33: 0.60209548 | M33: D04 | N33: G42 | O33: 4.2440581 | P33: 5.6117295 | Q33: 0.51441469 | R33: -1.9097146 | S33: -1.242531 | T33: -1.391191 | U33: -0.4019535 | V33: 6.5742559
B34: D04 | C34: G43 | D34: 1.006398 | E34: 0.88407466 | F34: 1.3394694 | G34: 1.109174 | H34: 1.003757 | I34: 1.0618704 | J34: 0.6626753 | K34: 0.80691054 | M34: D04 | N34: G43 | O34: 1.7521131 | P34: 1.9189601 | Q34: -0.025490597 | R34: -1.7018435 | S34: -1.1575604 | T34: -1.1930704 | U34: -0.30316136 | V34: 2.4991267
B35: D04 | C35: G44 | D35: 0.98370264 | E35: 1.0271908 | F35: 1.1195022 | G35: 0.89116056 | H35: 1.7371021 | I35: 0.96856325 | J35: 1.0566721 | K35: 0.74276286 | M35: D04 | N35: G44 | O35: 34.396766 | P35: 41.087344 | Q35: 10.338758 | R35: -5.9735428 | S35: -3.2797217 | T35: -3.1637299 | U35: 3.8954057 | V35: 41.007104
B36: D04 | C36: G71 | D36: 1.2520198 | E36: 1.3383395 | F36: 0.88665796 | G36: 0.86859941 | H36: 0.4324207 | I36: 0.66294006 | J36: 0.84559274 | K36: 1.3149443 | M36: D04 | N36: G71 | O36: 1.9836648 | P36: 2.3037205 | Q36: 0.28741772 | R36: -1.3361012 | S36: -0.55597327 | T36: -0.83848908 | U36: -0.41115769 | V36: 2.8178473
B37: =X37 -> D05 | D37: =Y37 -> 1.5353525 | E37: =Z37 -> 1.5265996 | F37: =AA37 -> 1.4186744 | G37: =AB37 -> 1.3555845 | H37: =AC37 -> 1.5692898 | I37: =AD37 -> 1.5340399 | J37: =AE37 -> 1.6085943 | K37: =AF37 -> 1.1701574 | M37: =AI37 -> D05 | O37: =AJ37 -> -1.6149074 | P37: =AK37 -> -1.5258499 | Q37: =AL37 -> -2.2479886 | R37: =AM37 -> -1.8010186 | S37: =AN37 -> -2.1131271 | T37: =AO37 -> -2.6959749 | U37: =AP37 -> -2.2854663 | V37: =AQ37 -> -0.61084769 | X37: D05 | Y37: 1.5353525 | Z37: 1.5265996 | AA37: 1.4186744 | AB37: 1.3555845 | AC37: 1.5692898 | AD37: 1.5340399 | AE37: 1.6085943 | AF37: 1.1701574 | AI37: D05 | AJ37: -1.6149074 | AK37: -1.5258499 | AL37: -2.2479886 | AM37: -1.8010186 | AN37: -2.1131271 | AO37: -2.6959749 | AP37: -2.2854663 | AQ37: -0.61084769
B38: D05 | C38: G41 | D38: 1.5152345 | E38: 1.4150548 | F38: 1.7915197 | G38: 1.1778722 | H38: 1.5891846 | I38: 1.6860213 | J38: 1.7387867 | K38: 1.0887555 | M38: D05 | N38: G41 | O38: 0.21039626 | P38: 0.3712296 | Q38: -1.0093469 | R38: -1.7841744 | S38: -1.6962072 | T38: -1.8117271 | U38: -1.486278 | V38: 0.64795691
B39: D05 | C39: G46 | D39: 0.58376275 | E39: 0.58859621 | F39: 0.7827198 | G39: 1.028306 | H39: 0.88769007 | I39: 0.91739542 | J39: 1.0385664 | K39: 0.61120586 | M39: D05 | N39: G46 | O39: 1.0417888 | P39: 1.3831922 | Q39: -0.27670948 | R39: -1.1913483 | S39: -0.9388627 | T39: -0.98570874 | U39: -0.84655774 | V39: 2.107291
B40: =X40 -> D23 | D40: =Y40 -> 1.6945157 | E40: =Z40 -> 1.7702043 | F40: =AA40 -> 1.3733701 | G40: =AB40 -> 0.7483696 | H40: =AC40 -> 0.75027971 | I40: =AD40 -> 0.62101114 | J40: =AE40 -> 0.89022998 | K40: =AF40 -> 1.900521 | M40: =AI40 -> D23 | O40: =AJ40 -> -1.6544205 | P40: =AK40 -> -1.7030854 | Q40: =AL40 -> -1.5173539 | R40: =AM40 -> -0.81134677 | S40: =AN40 -> -0.84460294 | T40: =AO40 -> -0.85940123 | U40: =AP40 -> -1.0616508 | V40: =AQ40 -> -1.6658523 | X40: D23 | Y40: 1.6945157 | Z40: 1.7702043 | AA40: 1.3733701 | AB40: 0.7483696 | AC40: 0.75027971 | AD40: 0.62101114 | AE40: 0.89022998 | AF40: 1.900521 | AI40: D23 | AJ40: -1.6544205 | AK40: -1.7030854 | AL40: -1.5173539 | AM40: -0.81134677 | AN40: -0.84460294 | AO40: -0.85940123 | AP40: -1.0616508 | AQ40: -1.6658523
B41: =X41 -> E00 | D41: =Y41 -> 0.38793261 | E41: =Z41 -> 0.38571931 | F41: =AA41 -> 0.5106725 | G41: =AB41 -> 0.7078317 | H41: =AC41 -> 0.6434147 | I41: =AD41 -> 0.48770699 | J41: =AE41 -> 0.61225276 | K41: =AF41 -> 0.38028638 | M41: =AI41 -> E00 | O41: =AJ41 -> -0.42562787 | P41: =AK41 -> -0.39694833 | Q41: =AL41 -> -0.72870622 | R41: =AM41 -> -0.76542553 | S41: =AN41 -> -0.73049058 | T41: =AO41 -> -0.71542339 | U41: =AP41 -> -0.79671555 | V41: =AQ41 -> -0.031262916 | X41: E00 | Y41: 0.38793261 | Z41: 0.38571931 | AA41: 0.5106725 | AB41: 0.7078317 | AC41: 0.6434147 | AD41: 0.48770699 | AE41: 0.61225276 | AF41: 0.38028638 | AI41: E00 | AJ41: -0.42562787 | AK41: -0.39694833 | AL41: -0.72870622 | AM41: -0.76542553 | AN41: -0.73049058 | AO41: -0.71542339 | AP41: -0.79671555 | AQ41: -0.031262916
B42: E00 | C42: G33 | D42: 0.38793366 | E42: 0.38572058 | F42: 0.51067283 | G42: 0.77550209 | H42: 0.72910263 | I42: 0.64033767 | J42: 0.57420045 | K42: 0.45490397 | M42: E00 | N42: G33 | O42: -0.14795399 | P42: -0.089320921 | Q42: -0.45327103 | R42: -0.81619359 | S42: -0.75585042 | T42: -0.67177835 | U42: -0.56253036 | V42: 0.014886027
B43: =X43 -> F45 | D43: =Y43 -> 1.1868154 | E43: =Z43 -> 1.3112558 | F43: =AA43 -> 1.4765662 | G43: =AB43 -> 1.6711537 | H43: =AC43 -> 2.2300531 | I43: =AD43 -> 1.2623007 | J43: =AE43 -> 0.67152646 | K43: =AF43 -> 0.87165062 | M43: =AI43 -> F45 | O43: =AJ43 -> -1.2178608 | P43: =AK43 -> -1.3060886 | Q43: =AL43 -> -1.6851956 | R43: =AM43 -> -1.7994724 | S43: =AN43 -> -2.3574664 | T43: =AO43 -> -1.6750633 | U43: =AP43 -> -0.9360088 | V43: =AQ43 -> -0.61547878 | X43: F45 | Y43: 1.1868154 | Z43: 1.3112558 | AA43: 1.4765662 | AB43: 1.6711537 | AC43: 2.2300531 | AD43: 1.2623007 | AE43: 0.67152646 | AF43: 0.87165062 | AI43: F45 | AJ43: -1.2178608 | AK43: -1.3060886 | AL43: -1.6851956 | AM43: -1.7994724 | AN43: -2.3574664 | AO43: -1.6750633 | AP43: -0.9360088 | AQ43: -0.61547878
B44: =X44 -> G00 | D44: =Y44 -> 3.2609659 | E44: =Z44 -> 3.1345558 | F44: =AA44 -> 3.037674 | G44: =AB44 -> 1.5272769 | H44: =AC44 -> 2.0564493 | I44: =AD44 -> 1.2022577 | J44: =AE44 -> 1.8433186 | K44: =AF44 -> 2.5699361 | M44: =AI44 -> G00 | O44: =AJ44 -> -3.2733947 | P44: =AK44 -> -3.061588 | Q44: =AL44 -> -4.0703434 | R44: =AM44 -> -3.0359568 | S44: =AN44 -> -3.6454687 | T44: =AO44 -> -3.7637503 | U44: =AP44 -> -3.1531767 | V44: =AQ44 -> -2.0594184 | X44: G00 | Y44: 3.2609659 | Z44: 3.1345558 | AA44: 3.037674 | AB44: 1.5272769 | AC44: 2.0564493 | AD44: 1.2022577 | AE44: 1.8433186 | AF44: 2.5699361 | AI44: G00 | AJ44: -3.2733947 | AK44: -3.061588 | AL44: -4.0703434 | AM44: -3.0359568 | AN44: -3.6454687 | AO44: -3.7637503 | AP44: -3.1531767 | AQ44: -2.0594184
B45: G00 | C45: G32 | D45: 1.1868154 | E45: 1.3112558 | F45: 1.4765662 | G45: 1.768864 | H45: 1.1524041 | I45: 1.0907673 | J45: 1.4102218 | K45: 1.0257155 | M45: G00 | N45: G32 | O45: -0.486074 | P45: -0.40173509 | Q45: -1.259037 | R45: -1.8826047 | S45: -1.1810185 | T45: -1.1296237 | U45: -1.3108469 | V45: -0.17902252
B46: =X46 -> H55 | D46: =Y46 -> 1.3769094 | E46: =Z46 -> 1.3563485 | F46: =AA46 -> 1.5379625 | G46: =AB46 -> 0.7536589 | H46: =AC46 -> 1.2531061 | I46: =AD46 -> 1.7785035 | J46: =AE46 -> 1.4367002 | K46: =AF46 -> 1.1223479 | M46: =AI46 -> H55 | O46: =AJ46 -> -1.3829102 | P46: =AK46 -> -1.3401275 | Q46: =AL46 -> -1.7343831 | R46: =AM46 -> -0.86876871 | S46: =AN46 -> -1.4010484 | T46: =AO46 -> -2.0445033 | U46: =AP46 -> -1.590402 | V46: =AQ46 -> -0.93950557 | X46: H55 | Y46: 1.3769094 | Z46: 1.3563485 | AA46: 1.5379625 | AB46: 0.7536589 | AC46: 1.2531061 | AD46: 1.7785035 | AE46: 1.4367002 | AF46: 1.1223479 | AI46: H55 | AJ46: -1.3829102 | AK46: -1.3401275 | AL46: -1.7343831 | AM46: -0.86876871 | AN46: -1.4010484 | AO46: -2.0445033 | AP46: -1.590402 | AQ46: -0.93950557
B47: H55 | C47: G15 | D47: 1.036578 | E47: 1.0063071 | F47: 1.0743266 | G47: 1.1934181 | H47: 1.2506639 | I47: 1.4602769 | J47: 1.2029043 | K47: 0.97137818 | M47: H55 | N47: G15 | O47: -0.15182074 | P47: -0.049519955 | Q47: -0.72075368 | R47: -1.3695983 | S47: -1.2828277 | T47: -1.4852011 | U47: -1.096465 | V47: 0.2148612
B48: =X48 -> I01 | D48: =Y48 -> 0.70044221 | E48: =Z48 -> 0.70288401 | F48: =AA48 -> 0.77700004 | G48: =AB48 -> 1.3975174 | H48: =AC48 -> 1.2742034 | I48: =AD48 -> 1.242612 | J48: =AE48 -> 1.1639309 | K48: =AF48 -> 0.45783386 | M48: =AI48 -> I01 | O48: =AJ48 -> -0.75449173 | P48: =AK48 -> -0.71258583 | Q48: =AL48 -> -1.1702273 | R48: =AM48 -> -1.5356697 | S48: =AN48 -> -1.4594833 | T48: =AO48 -> -1.6651033 | U48: =AP48 -> -1.4290137 | V48: =AQ48 -> -0.015498431 | X48: I01 | Y48: 0.70044221 | Z48: 0.70288401 | AA48: 0.77700004 | AB48: 1.3975174 | AC48: 1.2742034 | AD48: 1.242612 | AE48: 1.1639309 | AF48: 0.45783386 | AI48: I01 | AJ48: -0.75449173 | AK48: -0.71258583 | AL48: -1.1702273 | AM48: -1.5356697 | AN48: -1.4594833 | AO48: -1.6651033 | AP48: -1.4290137 | AQ48: -0.015498431
B49: I01 | C49: G61 | D49: 3.5412915 | E49: 3.3676911 | F49: 3.4049455 | G49: 2.0256299 | H49: 2.4116259 | I49: 2.0311089 | J49: 3.0831971 | K49: 2.5412155 | M49: I01 | N49: G61 | O49: -2.703195 | P49: -2.5391767 | Q49: -2.8771342 | R49: -2.2451687 | S49: -2.4029672 | T49: -2.0340259 | U49: -2.7822556 | V49: -1.9185286
B50: I01 | C50: G62 | D50: 0.45716492 | E50: 0.42211953 | F50: 0.74662743 | G50: 1.5219083 | H50: 1.2305443 | I50: 1.20702 | J50: 0.72076394 | K50: 0.28076852 | M50: I01 | N50: G62 | O50: 0.61596028 | P50: 0.86139983 | Q50: -0.40589584 | R50: -1.6374623 | S50: -1.2624527 | T50: -1.2477605 | U50: -0.60869553 | V50: 1.4257514
B51: =X51 -> I02 | D51: =Y51 -> 1.3831852 | E51: =Z51 -> 1.2163922 | F51: =AA51 -> 1.6983794 | G51: =AB51 -> 1.4887823 | H51: =AC51 -> 1.7636996 | I51: =AD51 -> 1.6630948 | J51: =AE51 -> 1.8271494 | K51: =AF51 -> 1.0549981 | M51: =AI51 -> I02 | O51: =AJ51 -> -1.4114229 | P51: =AK51 -> -1.2127451 | Q51: =AL51 -> -2.2041382 | R51: =AM51 -> -1.6967573 | S51: =AN51 -> -1.9805241 | T51: =AO51 -> -2.1617911 | U51: =AP51 -> -2.0683094 | V51: =AQ51 -> -0.7797451 | X51: I02 | Y51: 1.3831852 | Z51: 1.2163922 | AA51: 1.6983794 | AB51: 1.4887823 | AC51: 1.7636996 | AD51: 1.6630948 | AE51: 1.8271494 | AF51: 1.0549981 | AI51: I02 | AJ51: -1.4114229 | AK51: -1.2127451 | AL51: -2.2041382 | AM51: -1.6967573 | AN51: -1.9805241 | AO51: -2.1617911 | AP51: -2.0683094 | AQ51: -0.7797451
B52: I02 | C52: G63 | D52: 1.3831831 | E52: 1.2163926 | F52: 1.6983799 | G52: 1.1782759 | H52: 1.257216 | I52: 1.4448757 | J52: 1.2664133 | K52: 1.0680407 | M52: I02 | N52: G63 | O52: -0.68563133 | P52: -0.54315262 | Q52: -1.2963623 | R52: -1.3550642 | S52: -1.2913023 | T52: -1.4754983 | U52: -1.1606841 | V52: -0.33552805
B53: =X53 -> J00 | D53: =Y53 -> 1.6592627 | E53: =Z53 -> 1.3678567 | F53: =AA53 -> 2.5460391 | G53: =AB53 -> 1.1568496 | H53: =AC53 -> 1.6426932 | I53: =AD53 -> 2.5035739 | J53: =AE53 -> 2.2098953 | K53: =AF53 -> 1.0283247 | M53: =AI53 -> J00 | O53: =AJ53 -> -1.6862693 | P53: =AK53 -> -1.3593114 | Q53: =AL53 -> -3.4014942 | R53: =AM53 -> -1.8665344 | S53: =AN53 -> -1.5593189 | T53: =AO53 -> -3.1804993 | U53: =AP53 -> -2.5550977 | V53: =AQ53 -> -0.74896705 | X53: J00 | Y53: 1.6592627 | Z53: 1.3678567 | AA53: 2.5460391 | AB53: 1.1568496 | AC53: 1.6426932 | AD53: 2.5035739 | AE53: 2.2098953 | AF53: 1.0283247 | AI53: J00 | AJ53: -1.6862693 | AK53: -1.3593114 | AL53: -3.4014942 | AM53: -1.8665344 | AN53: -1.5593189 | AO53: -3.1804993 | AP53: -2.5550977 | AQ53: -0.74896705
B54: =X54 -> K00 | D54: =Y54 -> 0.98224909 | E54: =Z54 -> 0.85323426 | F54: =AA54 -> 0.61706525 | G54: =AB54 -> 0.77067166 | H54: =AC54 -> 0.73179202 | I54: =AD54 -> 1.1543103 | J54: =AE54 -> 0.81120122 | K54: =AF54 -> 1.1988897 | M54: =AI54 -> K00 | O54: =AJ54 -> -0.9932991 | P54: =AK54 -> -0.86949575 | Q54: =AL54 -> -0.77935449 | R54: =AM54 -> -0.81337294 | S54: =AN54 -> -0.78629747 | T54: =AO54 -> -1.2137186 | U54: =AP54 -> -0.88832056 | V54: =AQ54 -> -1.0939572 | X54: K00 | Y54: 0.98224909 | Z54: 0.85323426 | AA54: 0.61706525 | AB54: 0.77067166 | AC54: 0.73179202 | AD54: 1.1543103 | AE54: 0.81120122 | AF54: 1.1988897 | AI54: K00 | AJ54: -0.9932991 | AK54: -0.86949575 | AL54: -0.77935449 | AM54: -0.81337294 | AN54: -0.78629747 | AO54: -1.2137186 | AP54: -0.88832056 | AQ54: -1.0939572
B55: K00 | C55: G31 | D55: 0.92840207 | E55: 0.80308916 | F55: 0.54256306 | G55: 0.46810189 | H55: 0.41263048 | I55: 0.54286574 | J55: 0.3727393 | K55: 0.90607331 | M55: K00 | N55: G31 | O55: -0.75748131 | P55: -0.65657521 | Q55: -0.43165581 | R55: -0.51806896 | S55: -0.44342209 | T55: -0.57732334 | U55: -0.37036916 | V55: -0.68304513
B56: K00 | C56: G72 | D56: 1.6555121 | E56: 1.9262011 | F56: 0.86438273 | G56: 2.0306662 | H56: 1.4234362 | I56: 2.204261 | J56: 1.014553 | K56: 1.64782 | M56: K00 | N56: G72 | O56: 13.059385 | P56: 15.458955 | Q56: 3.9713975 | R56: -3.2495012 | S56: -1.7766364 | T56: -3.0279645 | U56: 1.731637 | V56: 15.493938
B57: =X57 -> L75 | D57: =Y57 -> 1.9527274 | E57: =Z57 -> 1.6222884 | F57: =AA57 -> 2.3384541 | G57: =AB57 -> 0.92173223 | H57: =AC57 -> 1.9581996 | I57: =AD57 -> 2.6750721 | J57: =AE57 -> 3.019763 | K57: =AF57 -> 1.1659663 | M57: =AI57 -> L75 | O57: =AJ57 -> -2.0978673 | P57: =AK57 -> -1.6266855 | Q57: =AL57 -> -4.6650295 | R57: =AM57 -> -2.5291359 | S57: =AN57 -> -3.8484896 | T57: =AO57 -> -4.5288145 | U57: =AP57 -> -4.6447056 | V57: =AQ57 -> -0.3705804 | X57: L75 | Y57: 1.9527274 | Z57: 1.6222884 | AA57: 2.3384541 | AB57: 0.92173223 | AC57: 1.9581996 | AD57: 2.6750721 | AE57: 3.019763 | AF57: 1.1659663 | AI57: L75 | AJ57: -2.0978673 | AK57: -1.6266855 | AL57: -4.6650295 | AM57: -2.5291359 | AN57: -3.8484896 | AO57: -4.5288145 | AP57: -4.6447056 | AQ57: -0.3705804
B58: =X58 -> MN0 | D58: =Y58 -> 1.4683368 | E58: =Z58 -> 1.3806677 | F58: =AA58 -> 1.2256597 | G58: =AB58 -> 1.1633297 | H58: =AC58 -> 1.1517501 | I58: =AD58 -> 1.9537728 | J58: =AE58 -> 1.1922489 | K58: =AF58 -> 1.2166409 | M58: =AI58 -> MN0 | O58: =AJ58 -> -1.4505004 | P58: =AK58 -> -0.98429546 | Q58: =AL58 -> -1.4362992 | R58: =AM58 -> -1.2523219 | S58: =AN58 -> -1.2556036 | T58: =AO58 -> -2.1008554 | U58: =AP58 -> -1.3132051 | V58: =AQ58 -> -1.0766414 | X58: MN0 | Y58: 1.4683368 | Z58: 1.3806677 | AA58: 1.2256597 | AB58: 1.1633297 | AC58: 1.1517501 | AD58: 1.9537728 | AE58: 1.1922489 | AF58: 1.2166409 | AI58: MN0 | AJ58: -1.4505004 | AK58: -0.98429546 | AL58: -1.4362992 | AM58: -1.2523219 | AN58: -1.2556036 | AO58: -2.1008554 | AP58: -1.3132051 | AQ58: -1.0766414
B59: MN0 | C59: G52 | D59: 1.0130664 | E59: 0.94466687 | F59: 1.1912323 | G59: 1.5586828 | H59: 1.3354627 | I59: 1.3439514 | J59: 1.3221624 | K59: 0.78899636 | M59: MN0 | N59: G52 | O59: -0.589747 | P59: -0.4982011 | Q59: -1.0053259 | R59: -1.6203615 | S59: -1.3380895 | T59: -1.3461798 | U59: -1.2497855 | V59: -0.27765646
B60: MN0 | C60: G75 | D60: 0.80003632 | E60: 0.83917273 | F60: 0.74022409 | G60: 0.55049688 | H60: -0.016904925 | I60: 1.5942817 | J60: 0.73525055 | K60: 0.88700307 | M60: MN0 | N60: G75 | O60: 73.679292 | P60: 85.563227 | Q60: 24.613788 | R60: -7.2638432 | S60: -2.0785403 | T60: -4.2391021 | U60: 16.685548 | V60: 107.23713
B61: MN0 | C61: G76 | D61: 1.7331879 | E61: 1.5290113 | F61: 0.92870646 | G61: 0.92889775 | H61: 1.063885 | I61: 1.1742778 | J61: 1.3184659 | K61: 1.5813436 | M61: MN0 | N61: G76 | O61: -0.98077008 | P61: -0.85803831 | Q61: -0.32848301 | R61: -1.0484127 | S61: -1.0991697 | T61: -1.2136001 | U61: -1.1856692 | V61: -0.77456884
B62: =X62 -> OP0 | D62: =Y62 -> 1.5007382 | E62: =Z62 -> 1.4112976 | F62: =AA62 -> 1.4666599 | G62: =AB62 -> 1.3202003 | H62: =AC62 -> 1.0095392 | I62: =AD62 -> 2.0659569 | J62: =AE62 -> 1.3238973 | K62: =AF62 -> 1.3529573 | M62: =AI62 -> OP0 | O62: =AJ62 -> -1.4979457 | P62: =AK62 -> -1.3893299 | Q62: =AL62 -> -1.7355895 | R62: =AM62 -> -1.4308825 | S62: =AN62 -> -1.1449405 | T62: =AO62 -> -1.2367871 | U62: =AP62 -> -1.5015167 | V62: =AQ62 -> -1.1546702 | X62: OP0 | Y62: 1.5007382 | Z62: 1.4112976 | AA62: 1.4666599 | AB62: 1.3202003 | AC62: 1.0095392 | AD62: 2.0659569 | AE62: 1.3238973 | AF62: 1.3529573 | AI62: OP0 | AJ62: -1.4979457 | AK62: -1.3893299 | AL62: -1.7355895 | AM62: -1.4308825 | AN62: -1.1449405 | AO62: -1.2367871 | AP62: -1.5015167 | AQ62: -1.1546702
B63: OP0 | C63: G73 | D63: 2.4083207 | E63: 1.9992284 | F63: 2.3691471 | G63: 1.6594146 | H63: 0.98981616 | I63: 2.0476095 | J63: 1.2888773 | K63: 1.6317338 | M63: OP0 | N63: G73 | O63: 2.8279453 | P63: 2.4087688 | Q63: 6.3374788 | R63: -6.6295394 | S63: -1.8255295 | T63: -2.581372 | U63: -0.099243156 | V63: 2.6419162
B64: OP0 | C64: G74 | D64: 2.2584477 | E64: 2.1337508 | F64: 1.1517164 | G64: 1.86411 | H64: 1.7562953 | I64: 2.3936647 | J64: 1.4123889 | K64: 1.6961797 | M64: OP0 | N64: G74 | O64: 1.6708974 | P64: 1.5916533 | Q64: 1.273937 | R64: -4.0306218 | S64: -2.0376922 | T64: -2.7103825 | U64: -0.62936313 | V64: 1.829451
B67: Elas-revenu 2014 | D67: National | E67: URB | F67: RUR | G67: Q1 | H67: Q2 | I67: Q3 | J67: Q4 | K67: Q5 | M67: Elas-Prix 2014 | O67: National | P67: URB | Q67: RUR | R67: Q1 | S67: Q2 | T67: Q3 | U67: Q4 | V67: Q5 | X67: Elas-revenu 2014 | Y67: National | Z67: M URB | AA67: M RUR | AB67: Q- 1 | AC67: Q- 2 | AD67: Q- 3 | AE67: Q- 4 | AF67: Q- 5 | AI67: Elas-revenu 2014 | AJ67: National | AK67: M URB | AL67: M RUR | AM67: Q- 1 | AN67: Q- 2 | AO67: Q- 3 | AP67: Q- 4 | AQ67: Q- 5
B69: =X69 -> A00 | D69: =Y69 -> 0.40012939 | E69: =Z69 -> 0.43941571 | F69: =AA69 -> 0.68726763 | G69: =AB69 -> 1.0081283 | H69: =AC69 -> 0.92102559 | I69: =AD69 -> 0.93601863 | J69: =AE69 -> 0.7847426 | K69: =AF69 -> 0.44912121 | M69: =AI69 -> A00 | O69: =AJ69 -> -0.43917364 | P69: =AK69 -> -0.46925147 | Q69: =AL69 -> -0.76764886 | R69: =AM69 -> -1.0159987 | S69: =AN69 -> -0.9571373 | T69: =AO69 -> -0.96999894 | U69: =AP69 -> -0.83774863 | V69: =AQ69 -> -0.43986601 | X69: A00 | Y69: 0.40012939 | Z69: 0.43941571 | AA69: 0.68726763 | AB69: 1.0081283 | AC69: 0.92102559 | AD69: 0.93601863 | AE69: 0.7847426 | AF69: 0.44912121 | AI69: A00 | AJ69: -0.43917364 | AK69: -0.46925147 | AL69: -0.76764886 | AM69: -1.0159987 | AN69: -0.9571373 | AO69: -0.96999894 | AP69: -0.83774863 | AQ69: -0.43986601
B70: A00 | C70: G06 | D70: 0.30119517 | E70: 0.30298035 | F70: 0.62281423 | G70: 1.0057887 | H70: 0.96716211 | I70: 0.86617103 | J70: 0.79806216 | K70: 0.34905292 | M70: A00 | N70: G06 | O70: -0.1188808 | P70: -0.10149238 | Q70: -0.54799901 | R70: -1.0362901 | S70: -0.97550507 | T70: -0.89721754 | U70: -0.77683411 | V70: -0.049851921
B71: A00 | C71: G08 | D71: 0.85898116 | E71: 0.87349927 | F71: 1.157327 | G71: 1.5378127 | H71: 1.4378361 | I71: 1.2555693 | J71: 1.1706852 | K71: 0.74056885 | M71: A00 | N71: G08 | O71: -0.66002588 | P71: -0.67655806 | Q71: -1.0398525 | R71: -1.5840519 | S71: -1.4319636 | T71: -1.2838947 | U71: -1.1361192 | V71: -0.52917002
B72: =X72 -> B05 | D72: =Y72 -> 0.93716484 | E72: =Z72 -> 0.91298027 | F72: =AA72 -> 0.87564473 | G72: =AB72 -> 1.0302135 | H72: =AC72 -> 0.84754111 | I72: =AD72 -> 0.93151282 | J72: =AE72 -> 1.0645746 | K72: =AF72 -> 0.89581221 | M72: =AI72 -> B05 | O72: =AJ72 -> -1.0131318 | P72: =AK72 -> -0.94078405 | Q72: =AL72 -> -1.5381681 | R72: =AM72 -> -1.2070165 | S72: =AN72 -> -1.1760003 | T72: =AO72 -> -1.2419467 | U72: =AP72 -> -1.3734577 | V72: =AQ72 -> -0.70906684 | X72: B05 | Y72: 0.93716484 | Z72: 0.91298027 | AA72: 0.87564473 | AB72: 1.0302135 | AC72: 0.84754111 | AD72: 0.93151282 | AE72: 1.0645746 | AF72: 0.89581221 | AI72: B05 | AJ72: -1.0131318 | AK72: -0.94078405 | AL72: -1.5381681 | AM72: -1.2070165 | AN72: -1.1760003 | AO72: -1.2419467 | AP72: -1.3734577 | AQ72: -0.70906684
B73: B05 | C73: G05 | D73: 0.94808612 | E73: 0.92276047 | F73: 0.86084618 | G73: 1.1333234 | H73: 0.8059048 | I73: 0.88706886 | J73: 1.0173309 | K73: 0.9105316 | M73: B05 | N73: G05 | O73: -0.5677808 | P73: -0.58683942 | Q73: -0.57777631 | R73: -1.2460603 | S73: -0.83100752 | T73: -0.95837665 | U73: -0.95824551 | V73: -0.51706234
B74: =X74 -> C00 | D74: =Y74 -> 0.10493074 | E74: =Z74 -> 0.14988081 | F74: =AA74 -> 0.49977364 | G74: =AB74 -> 0.70487045 | H74: =AC74 -> 0.80695521 | I74: =AD74 -> 0.6035612 | J74: =AE74 -> 0.55729799 | K74: =AF74 -> 0.19943148 | M74: =AI74 -> C00 | O74: =AJ74 -> -1.8853369 | P74: =AK74 -> -1.1464155 | Q74: =AL74 -> -7.7351474 | R74: =AM74 -> -2.5757508 | S74: =AN74 -> -6.056691 | T74: =AO74 -> -6.7855923 | U74: =AP74 -> -8.5095617 | V74: =AQ74 -> 9.6770588 | X74: C00 | Y74: 0.10493074 | Z74: 0.14988081 | AA74: 0.49977364 | AB74: 0.70487045 | AC74: 0.80695521 | AD74: 0.6035612 | AE74: 0.55729799 | AF74: 0.19943148 | AI74: C00 | AJ74: -1.8853369 | AK74: -1.1464155 | AL74: -7.7351474 | AM74: -2.5757508 | AN74: -6.056691 | AO74: -6.7855923 | AP74: -8.5095617 | AQ74: 9.6770588
